Workbook

Sheet panel_choc_taux_suisse_2014_202
A1: canton | B1: year | C1: CLUSTER 0 | D1: CLUSTER 1 | E1: CLUSTER 2 | F1: rent_avg | G1: Z_score_rent | H1: log_rent_avg | I1: pop_cant | J1: Solde_migratoire | K1: migration_rate | L1: migration_rate_zscore | M1: immo_price_index | N1: immoo_price_index_zscore | O1: mortgage_rate | P1: change_mrtgrate | Q1: logement_propr | R1: debt_per_household_*1000 | S1: homeownership_rate | T1: Z-score-debt | U1: Z-score-ownrrate | V1: avg_income | W1: avg_income_zscore | X1: log_avg_income | Y1: unemployment_rate | Z1: z-score_unemployment | AA1: log_unemployment | AB1: share_65plus | AC1: housing_constr_tot | AD1: housing_construction_pc | AE1: exposure_index | AF1: shock_exposure | AG1: log_schockexposure | AH1: shockexposure_zscore | AI1: delta_rent | AJ1: delta_migration | AK1: delta_unemployment | AL1: delta_income
A2: AG | B2: 2014 | C2: 1 | D2: 0 | E2: 0 | F2: 1294.83 | G2: =(F2-AVERAGE($F$2:$F$261))/STDEV($F$2:$F$261) -> 0.10583317 | H2: =LN(F2) -> 7.1661347 | I2: 645277 | J2: 1819 | K2: =(J2/I2)*100 -> 0.28189444 | L2: =(K2-AVERAGE($K$2:$K$261))/STDEV($K$2:$K$261) -> 0.91569056 | M2: 1.0281149 | N2: =(M2-AVERAGE($M$2:$M$261))/STDEV($M$2:$M$261) -> 0.060154245 | O2: 1.95 | P2: 0 | Q2: 114360 | R2: =[1]Feuil1!J36/panel_choc_taux_suisse_2014_202!Q2 -> 5550.9998 | S2: 28.5 | T2: =(R2-AVERAGE($R$2:$R$261))/STDEV($R$2:$R$261) -> -0.85084975 | U2: =(S2-AVERAGE($S$2:$S$261))/STDEV($S$2:$S$261) -> -1.233605 | V2: 80757.233 | W2: =(V2-AVERAGE($V$2:$V$261))/STDEV($V$2:$V$261) -> -0.4447083 | X2: =LN(V2) -> 11.299203 | Y2: 2.8 | Z2: =(Y2-AVERAGE($Y$2:$Y$261))/STDEV($Y$2:$Y$261) -> 0.22959394 | AA2: =LN(Y2) -> 1.0296194 | AB2: 104387 | AC2: 4937 | AD2: =AC2/I2 -> 0.0076509778 | AE2: =0.5*T2+0.5*U2 -> -1.0422274 | AF2: =AE2*P2 -> 0 | AG2: =LN(1+AF2) -> 0 | AH2: =(AF2-AVERAGE($AF$2:$AF$261))/STDEV($AF$2:$AF$261) -> 0.0055297297 | AI2: =AF2*Q2 -> 0 | AJ2: =AI2*R2 -> 0 | AK2: 0 | AL2: 0
A3: AG | B3: 2015 | C3: 1 | D3: 0 | E3: 0 | F3: 1258.33 | G3: =(F3-AVERAGE($F$2:$F$261))/STDEV($F$2:$F$261) -> -0.079186785 | H3: =LN(F3) -> 7.1375407 | I3: 653675 | J3: 1501 | K3: =(J3/I3)*100 -> 0.22962481 | L3: =(K3-AVERAGE($K$2:$K$261))/STDEV($K$2:$K$261) -> 0.75396915 | M3: 1.0174024 | N3: =(M3-AVERAGE($M$2:$M$261))/STDEV($M$2:$M$261) -> -0.38706257 | O3: 1.84 | P3: =O3-O2 -> -0.11 | Q3: 117510 | R3: =[1]Feuil1!J37/panel_choc_taux_suisse_2014_202!Q3 -> 5583.203 | S3: 29.1 | T3: =(R3-AVERAGE($R$2:$R$261))/STDEV($R$2:$R$261) -> -0.8503082 | U3: =(S3-AVERAGE($S$2:$S$261))/STDEV($S$2:$S$261) -> -1.1730275 | V3: 81080.262 | W3: =(V3-AVERAGE($V$2:$V$261))/STDEV($V$2:$V$261) -> -0.42638089 | X3: =LN(V3) -> 11.303195 | Y3: 3 | Z3: =(Y3-AVERAGE($Y$2:$Y$261))/STDEV($Y$2:$Y$261) -> 0.40187222 | AA3: =LN(Y3) -> 1.0986123 | AB3: 107352 | AC3: 4839 | AD3: =AC3/I3 -> 0.0074027613 | AE3: =0.5*T3+0.5*U3 -> -1.0116679 | AF3: =AE3*P3 -> 0.11128347 | AG3: =LN(1+AF3) -> 0.10551562 | AH3: =(AF3-AVERAGE($AF$2:$AF$261))/STDEV($AF$2:$AF$261) -> 1.1499281 | AI3: =LN(F3)-LN(F2) -> -0.028593967 | AJ3: =K3-K2 -> -0.052269629 | AK3: =Y3-Y2 -> 0.2 | AL3: =LN(V3)-LN(V2) -> 0.0039920213
A4: AG | B4: 2016 | C4: 1 | D4: 0 | E4: 0 | F4: 1277 | G4: =(F4-AVERAGE($F$2:$F$261))/STDEV($F$2:$F$261) -> 0.015452188 | H4: =LN(F4) -> 7.1522689 | I4: 663462 | J4: 2036 | K4: =(J4/I4)*100 -> 0.30687515 | L4: =(K4-AVERAGE($K$2:$K$261))/STDEV($K$2:$K$261) -> 0.99298047 | M4: 0.98347652 | N4: =(M4-AVERAGE($M$2:$M$261))/STDEV($M$2:$M$261) -> -1.8033694 | O4: 1.71 | P4: =O4-O3 -> -0.13 | Q4: 118803 | R4: =[1]Feuil1!J38/panel_choc_taux_suisse_2014_202!Q4 -> 5686.5828 | S4: 29.4 | T4: =(R4-AVERAGE($R$2:$R$261))/STDEV($R$2:$R$261) -> -0.84856972 | U4: =(S4-AVERAGE($S$2:$S$261))/STDEV($S$2:$S$261) -> -1.1427388 | V4: 81647.824 | W4: =(V4-AVERAGE($V$2:$V$261))/STDEV($V$2:$V$261) -> -0.39417964 | X4: =LN(V4) -> 11.31017 | Y4: 3.2 | Z4: =(Y4-AVERAGE($Y$2:$Y$261))/STDEV($Y$2:$Y$261) -> 0.5741505 | AA4: =LN(Y4) -> 1.1631508 | AB4: 110298 | AC4: 5011 | AD4: =AC4/I4 -> 0.0075528063 | AE4: =0.5*T4+0.5*U4 -> -0.99565428 | AF4: =AE4*P4 -> 0.12943506 | AG4: =LN(1+AF4) -> 0.12171756 | AH4: =(AF4-AVERAGE($AF$2:$AF$261))/STDEV($AF$2:$AF$261) -> 1.3365924 | AI4: =LN(F4)-LN(F3) -> 0.014728132 | AJ4: =K4-K3 -> 0.077250335 | AK4: =Y4-Y3 -> 0.2 | AL4: =LN(V4)-LN(V3) -> 0.0069756137
A5: AG | B5: 2017 | C5: 1 | D5: 0 | E5: 0 | F5: 1274.5 | G5: =(F5-AVERAGE($F$2:$F$261))/STDEV($F$2:$F$261) -> 0.0027795885 | H5: =LN(F5) -> 7.1503092 | I5: 670988 | J5: 2175 | K5: =(J5/I5)*100 -> 0.32414887 | L5: =(K5-AVERAGE($K$2:$K$261))/STDEV($K$2:$K$261) -> 1.0464251 | M5: 1.0635157 | N5: =(M5-AVERAGE($M$2:$M$261))/STDEV($M$2:$M$261) -> 1.538032 | O5: 1.56 | P5: =O5-O4 -> -0.15 | Q5: 119226 | R5: =[1]Feuil1!J39/panel_choc_taux_suisse_2014_202!Q5 -> 5807.2275 | S5: 29.2 | T5: =(R5-AVERAGE($R$2:$R$261))/STDEV($R$2:$R$261) -> -0.84654089 | U5: =(S5-AVERAGE($S$2:$S$261))/STDEV($S$2:$S$261) -> -1.1629313 | V5: 81974.415 | W5: =(V5-AVERAGE($V$2:$V$261))/STDEV($V$2:$V$261) -> -0.37565011 | X5: =LN(V5) -> 11.314162 | Y5: 3 | Z5: =(Y5-AVERAGE($Y$2:$Y$261))/STDEV($Y$2:$Y$261) -> 0.40187222 | AA5: =LN(Y5) -> 1.0986123 | AB5: 116424 | AC5: 5680 | AD5: =AC5/I5 -> 0.008465129 | AE5: =0.5*T5+0.5*U5 -> -1.0047361 | AF5: =AE5*P5 -> 0.15071042 | AG5: =LN(1+AF5) -> 0.1403795 | AH5: =(AF5-AVERAGE($AF$2:$AF$261))/STDEV($AF$2:$AF$261) -> 1.5553804 | AI5: =LN(F5)-LN(F4) -> -0.0019596322 | AJ5: =K5-K4 -> 0.017273718 | AK5: =Y5-Y4 -> -0.2 | AL5: =LN(V5)-LN(V4) -> 0.0039920212
A6: AG | B6: 2018 | C6: 1 | D6: 0 | E6: 0 | F6: 1305.83 | G6: =(F6-AVERAGE($F$2:$F$261))/STDEV($F$2:$F$261) -> 0.16159261 | H6: =LN(F6) -> 7.1745941 | I6: 678207 | J6: 1875 | K6: =(J6/I6)*100 -> 0.27646427 | L6: =(K6-AVERAGE($K$2:$K$261))/STDEV($K$2:$K$261) -> 0.89888968 | M6: 1.0301139 | N6: =(M6-AVERAGE($M$2:$M$261))/STDEV($M$2:$M$261) -> 0.14360417 | O6: 1.5 | P6: =O6-O5 -> -0.06 | Q6: 114635 | R6: =[1]Feuil1!J40/panel_choc_taux_suisse_2014_202!Q6 -> 6200.891 | S6: 27.5 | T6: =(R6-AVERAGE($R$2:$R$261))/STDEV($R$2:$R$261) -> -0.83992085 | U6: =(S6-AVERAGE($S$2:$S$261))/STDEV($S$2:$S$261) -> -1.3345674 | V6: 82384.287 | W6: =(V6-AVERAGE($V$2:$V$261))/STDEV($V$2:$V$261) -> -0.35239556 | X6: =LN(V6) -> 11.31915 | Y6: 2.6 | Z6: =(Y6-AVERAGE($Y$2:$Y$261))/STDEV($Y$2:$Y$261) -> 0.057315659 | AA6: =LN(Y6) -> 0.95551145 | AB6: 119708 | AC6: 5113 | AD6: =AC6/I6 -> 0.0075389962 | AE6: =0.5*T6+0.5*U6 -> -1.0872441 | AF6: =AE6*P6 -> 0.065234646 | AG6: =LN(1+AF6) -> 0.0631951 | AH6: =(AF6-AVERAGE($AF$2:$AF$261))/STDEV($AF$2:$AF$261) -> 0.67637891 | AI6: =LN(F6)-LN(F5) -> 0.024284909 | AJ6: =K6-K5 -> -0.047684602 | AK6: =Y6-Y5 -> -0.4 | AL6: =LN(V6)-LN(V5) -> 0.0049875416
A7: AG | B7: 2019 | C7: 1 | D7: 0 | E7: 0 | F7: 1318.33 | G7: =(F7-AVERAGE($F$2:$F$261))/STDEV($F$2:$F$261) -> 0.2249556 | H7: =LN(F7) -> 7.1841211 | I7: 685845 | J7: 2041 | K7: =(J7/I7)*100 -> 0.29758911 | L7: =(K7-AVERAGE($K$2:$K$261))/STDEV($K$2:$K$261) -> 0.9642496 | M7: 1.0368889 | N7: =(M7-AVERAGE($M$2:$M$261))/STDEV($M$2:$M$261) -> 0.42644191 | O7: 1.43 | P7: =O7-O6 -> -0.07 | Q7: 116235 | R7: =[1]Feuil1!J41/panel_choc_taux_suisse_2014_202!Q7 -> 6281.8149 | S7: 27.7 | T7: =(R7-AVERAGE($R$2:$R$261))/STDEV($R$2:$R$261) -> -0.83855999 | U7: =(S7-AVERAGE($S$2:$S$261))/STDEV($S$2:$S$261) -> -1.3143749 | V7: 83126 | W7: =(V7-AVERAGE($V$2:$V$261))/STDEV($V$2:$V$261) -> -0.31031364 | X7: =LN(V7) -> 11.328113 | Y7: 2.5 | Z7: =(Y7-AVERAGE($Y$2:$Y$261))/STDEV($Y$2:$Y$261) -> -0.028823482 | AA7: =LN(Y7) -> 0.91629073 | AB7: 123012 | AC7: 4775 | AD7: =AC7/I7 -> 0.0069622145 | AE7: =0.5*T7+0.5*U7 -> -1.0764674 | AF7: =AE7*P7 -> 0.075352721 | AG7: =LN(1+AF7) -> 0.07264872 | AH7: =(AF7-AVERAGE($AF$2:$AF$261))/STDEV($AF$2:$AF$261) -> 0.78042947 | AI7: =LN(F7)-LN(F6) -> 0.0095269302 | AJ7: =K7-K6 -> 0.02112484 | AK7: =Y7-Y6 -> -0.1 | AL7: =LN(V7)-LN(V6) -> 0.0089628028
A8: AG | B8: 2020 | C8: 1 | D8: 0 | E8: 0 | F8: 1335.17 | G8: =(F8-AVERAGE($F$2:$F$261))/STDEV($F$2:$F$261) -> 0.31031823 | H8: =LN(F8) -> 7.1968139 | I8: 694072 | J8: 2769 | K8: =(J8/I8)*100 -> 0.39894996 | L8: =(K8-AVERAGE($K$2:$K$261))/STDEV($K$2:$K$261) -> 1.2778585 | M8: 1.0413346 | N8: =(M8-AVERAGE($M$2:$M$261))/STDEV($M$2:$M$261) -> 0.61203885 | O8: 1.33 | P8: =O8-O7 -> -0.1 | Q8: 113779 | R8: =[1]Feuil1!J42/panel_choc_taux_suisse_2014_202!Q8 -> 6586.6001 | S8: 27.4 | T8: =(R8-AVERAGE($R$2:$R$261))/STDEV($R$2:$R$261) -> -0.83343457 | U8: =(S8-AVERAGE($S$2:$S$261))/STDEV($S$2:$S$261) -> -1.3446636 | V8: 83790.751 | W8: =(V8-AVERAGE($V$2:$V$261))/STDEV($V$2:$V$261) -> -0.27259822 | X8: =LN(V8) -> 11.336078 | Y8: 3.4 | Z8: =(Y8-AVERAGE($Y$2:$Y$261))/STDEV($Y$2:$Y$261) -> 0.74642878 | AA8: =LN(Y8) -> 1.2237754 | AB8: 126168 | AC8: 3771 | AD8: =AC8/I8 -> 0.0054331539 | AE8: =0.5*T8+0.5*U8 -> -1.0890491 | AF8: =AE8*P8 -> 0.10890491 | AG8: =LN(1+AF8) -> 0.10337296 | AH8: =(AF8-AVERAGE($AF$2:$AF$261))/STDEV($AF$2:$AF$261) -> 1.1254679 | AI8: =LN(F8)-LN(F7) -> 0.01269284 | AJ8: =K8-K7 -> 0.10136086 | AK8: =Y8-Y7 -> 0.9 | AL8: =LN(V8)-LN(V7) -> 0.0079651081
A9: AG | B9: 2021 | C9: 1 | D9: 0 | E9: 0 | F9: 1341.67 | G9: =(F9-AVERAGE($F$2:$F$261))/STDEV($F$2:$F$261) -> 0.34326699 | H9: =LN(F9) -> 7.2016704 | I9: 703086 | J9: 3429 | K9: =(J9/I9)*100 -> 0.48770705 | L9: =(K9-AVERAGE($K$2:$K$261))/STDEV($K$2:$K$261) -> 1.5524715 | M9: 1.0457436 | N9: =(M9-AVERAGE($M$2:$M$261))/STDEV($M$2:$M$261) -> 0.79609897 | O9: 1.25 | P9: =O9-O8 -> -0.08 | Q9: 116256 | R9: =[1]Feuil1!J43/panel_choc_taux_suisse_2014_202!Q9 -> 6650.4076 | S9: 27.6 | T9: =(R9-AVERAGE($R$2:$R$261))/STDEV($R$2:$R$261) -> -0.83236155 | U9: =(S9-AVERAGE($S$2:$S$261))/STDEV($S$2:$S$261) -> -1.3244711 | V9: 83623.17 | W9: =(V9-AVERAGE($V$2:$V$261))/STDEV($V$2:$V$261) -> -0.28210614 | X9: =LN(V9) -> 11.334076 | Y9: 3.4 | Z9: =(Y9-AVERAGE($Y$2:$Y$261))/STDEV($Y$2:$Y$261) -> 0.74642878 | AA9: =LN(Y9) -> 1.2237754 | AB9: 129531 | AC9: 3815 | AD9: =AC9/I9 -> 0.0054260787 | AE9: =0.5*T9+0.5*U9 -> -1.0784163 | AF9: =AE9*P9 -> 0.086273307 | AG9: =LN(1+AF9) -> 0.082752854 | AH9: =(AF9-AVERAGE($AF$2:$AF$261))/STDEV($AF$2:$AF$261) -> 0.89273278 | AI9: =LN(F9)-LN(F8) -> 0.0048564821 | AJ9: =K9-K8 -> 0.088757087 | AK9: =Y9-Y8 -> 0 | AL9: =LN(V9)-LN(V8) -> -0.0020020026
A10: AG | B10: 2022 | C10: 1 | D10: 0 | E10: 0 | F10: 1369.17 | G10: =(F10-AVERAGE($F$2:$F$261))/STDEV($F$2:$F$261) -> 0.48266559 | H10: =LN(F10) -> 7.22196 | I10: 711232 | J10: 2615 | K10: =(J10/I10)*100 -> 0.36767187 | L10: =(K10-AVERAGE($K$2:$K$261))/STDEV($K$2:$K$261) -> 1.1810846 | M10: 0.98600652 | N10: =(M10-AVERAGE($M$2:$M$261))/STDEV($M$2:$M$261) -> -1.6977493 | O10: 1.21 | P10: =O10-O9 -> -0.04 | Q10: 112419 | R10: =[1]Feuil1!J44/panel_choc_taux_suisse_2014_202!Q10 -> 7081.8322 | S10: 26.8 | T10: =(R10-AVERAGE($R$2:$R$261))/STDEV($R$2:$R$261) -> -0.8251065 | U10: =(S10-AVERAGE($S$2:$S$261))/STDEV($S$2:$S$261) -> -1.405241 | V10: 84375.779 | W10: =(V10-AVERAGE($V$2:$V$261))/STDEV($V$2:$V$261) -> -0.23940605 | X10: =LN(V10) -> 11.343036 | Y10: 2.5 | Z10: =(Y10-AVERAGE($Y$2:$Y$261))/STDEV($Y$2:$Y$261) -> -0.028823482 | AA10: =LN(Y10) -> 0.91629073 | AB10: 133099 | AC10: 3679 | AD10: =AC10/I10 -> 0.0051727144 | AE10: =0.5*T10+0.5*U10 -> -1.1151738 | AF10: =AE10*P10 -> 0.044606951 | AG10: =LN(1+AF10) -> 0.043640691 | AH10: =(AF10-AVERAGE($AF$2:$AF$261))/STDEV($AF$2:$AF$261) -> 0.46425125 | AI10: =LN(F10)-LN(F9) -> 0.02028961 | AJ10: =K10-K9 -> -0.12003518 | AK10: =Y10-Y9 -> -0.9 | AL10: =LN(V10)-LN(V9) -> 0.0089597414
A11: AG | B11: 2023 | C11: 1 | D11: 0 | E11: 0 | F11: 1523.14 | G11: =(F11-AVERAGE($F$2:$F$261))/STDEV($F$2:$F$261) -> 1.2631457 | H11: =LN(F11) -> 7.3285293 | I11: 726894 | J11: 3128 | K11: =(J11/I11)*100 -> 0.43032409 | L11: =(K11-AVERAGE($K$2:$K$261))/STDEV($K$2:$K$261) -> 1.3749295 | M11: 1.0341431 | N11: =(M11-AVERAGE($M$2:$M$261))/STDEV($M$2:$M$261) -> 0.31181116 | O11: 1.48 | P11: =O11-O10 -> 0.27 | Q11: 111712 | R11: =[1]Feuil1!J45/panel_choc_taux_suisse_2014_202!Q11 -> 7278.4333 | S11: 26.7 | T11: =(R11-AVERAGE($R$2:$R$261))/STDEV($R$2:$R$261) -> -0.82180036 | U11: =(S11-AVERAGE($S$2:$S$261))/STDEV($S$2:$S$261) -> -1.4153373 | V11: 98719.661 | W11: =(V11-AVERAGE($V$2:$V$261))/STDEV($V$2:$V$261) -> 0.57441021 | X11: =LN(V11) -> 11.500039 | Y11: 2.2 | Z11: =(Y11-AVERAGE($Y$2:$Y$261))/STDEV($Y$2:$Y$261) -> -0.2872409 | AA11: =LN(Y11) -> 0.78845736 | AB11: 137011 | AC11: 4193 | AD11: =AC11/I11 -> 0.0057683789 | AE11: =0.5*T11+0.5*U11 -> -1.1185688 | AF11: =AE11*P11 -> -0.30201358 | AG11: =LN(1+AF11) -> -0.35955563 | AH11: =(AF11-AVERAGE($AF$2:$AF$261))/STDEV($AF$2:$AF$261) -> -3.1002672 | AI11: =LN(F11)-LN(F10) -> 0.10656928 | AJ11: =K11-K10 -> 0.06265222 | AK11: =Y11-Y10 -> -0.3 | AL11: =LN(V11)-LN(V10) -> 0.15700375
A12: AI | B12: 2014 | C12: 1 | D12: 0 | E12: 0 | F12: 1299 | G12: =(F12-AVERAGE($F$2:$F$261))/STDEV($F$2:$F$261) -> 0.12697106 | H12: =LN(F12) -> 7.16935 | I12: 15854 | J12: 18 | K12: =(J12/I12)*100 -> 0.11353602 | L12: =(K12-AVERAGE($K$2:$K$261))/STDEV($K$2:$K$261) -> 0.39479225 | M12: 1.0281149 | N12: =(M12-AVERAGE($M$2:$M$261))/STDEV($M$2:$M$261) -> 0.060154245 | O12: 1.95 | P12: 0 | Q12: 131949 | R12: =[1]Feuil1!J46/panel_choc_taux_suisse_2014_202!Q12 -> 4811.0432 | S12: 39.8 | T12: =(R12-AVERAGE($R$2:$R$261))/STDEV($R$2:$R$261) -> -0.86329323 | U12: =(S12-AVERAGE($S$2:$S$261))/STDEV($S$2:$S$261) -> -0.092730065 | V12: 86397.741 | W12: =(V12-AVERAGE($V$2:$V$261))/STDEV($V$2:$V$261) -> -0.12468772 | X12: =LN(V12) -> 11.366717 | Y12: 1.1 | Z12: =(Y12-AVERAGE($Y$2:$Y$261))/STDEV($Y$2:$Y$261) -> -1.2347714 | AA12: =LN(Y12) -> 0.09531018 | AB12: 2813 | AC12: 53 | AD12: =AC12/I12 -> 0.0033430049 | AE12: =0.5*T12+0.5*U12 -> -0.47801165 | AF12: =AE12*P12 -> 0 | AG12: =LN(1+AF12) -> 0 | AH12: =(AF12-AVERAGE($AF$2:$AF$261))/STDEV($AF$2:$AF$261) -> 0.0055297297 | AI12: 0 | AJ12: 0 | AK12: 0 | AL12: 0
A13: AI | B13: 2015 | C13: 1 | D13: 0 | E13: 0 | F13: 1204 | G13: =(F13-AVERAGE($F$2:$F$261))/STDEV($F$2:$F$261) -> -0.35458772 | H13: =LN(F13) -> 7.0934046 | I13: 15974 | J13: 32 | K13: =(J13/I13)*100 -> 0.20032553 | L13: =(K13-AVERAGE($K$2:$K$261))/STDEV($K$2:$K$261) -> 0.66331763 | M13: 1.0174024 | N13: =(M13-AVERAGE($M$2:$M$261))/STDEV($M$2:$M$261) -> -0.38706257 | O13: 1.84 | P13: -0.11 | Q13: 134396 | R13: =[1]Feuil1!J47/panel_choc_taux_suisse_2014_202!Q13 -> 4881.7092 | S13: 40.9 | T13: =(R13-AVERAGE($R$2:$R$261))/STDEV($R$2:$R$261) -> -0.86210487 | U13: =(S13-AVERAGE($S$2:$S$261))/STDEV($S$2:$S$261) -> 0.018328555 | V13: 86743.332 | W13: =(V13-AVERAGE($V$2:$V$261))/STDEV($V$2:$V$261) -> -0.10508023 | X13: =LN(V13) -> 11.370709 | Y13: 1 | Z13: =(Y13-AVERAGE($Y$2:$Y$261))/STDEV($Y$2:$Y$261) -> -1.3209106 | AA13: =LN(Y13) -> 0 | AB13: 2865 | AC13: 146 | AD13: =AC13/I13 -> 0.0091398523 | AE13: =0.5*T13+0.5*U13 -> -0.42188816 | AF13: =AE13*P13 -> 0.046407697 | AG13: =LN(1+AF13) -> 0.045363058 | AH13: =(AF13-AVERAGE($AF$2:$AF$261))/STDEV($AF$2:$AF$261) -> 0.48276947 | AI13: =LN(F13)-LN(F12) -> -0.075945391 | AJ13: =K13-K12 -> 0.086789513 | AK13: =Y13-Y12 -> -0.1 | AL13: =LN(V13)-LN(V12) -> 0.0039920212
A14: AI | B14: 2016 | C14: 1 | D14: 0 | E14: 0 | F14: 1110.17 | G14: =(F14-AVERAGE($F$2:$F$261))/STDEV($F$2:$F$261) -> -0.83021573 | H14: =LN(F14) -> 7.0122684 | I14: 16003 | J14: -8 | K14: =(J14/I14)*100 -> -0.049990627 | L14: =(K14-AVERAGE($K$2:$K$261))/STDEV($K$2:$K$261) -> -0.11115659 | M14: 0.98347652 | N14: =(M14-AVERAGE($M$2:$M$261))/STDEV($M$2:$M$261) -> -1.8033694 | O14: 1.71 | P14: -0.13 | Q14: 137001 | R14: =[1]Feuil1!J48/panel_choc_taux_suisse_2014_202!Q14 -> 4931.2274 | S14: 40.3 | T14: =(R14-AVERAGE($R$2:$R$261))/STDEV($R$2:$R$261) -> -0.86127215 | U14: =(S14-AVERAGE($S$2:$S$261))/STDEV($S$2:$S$261) -> -0.042248874 | V14: 87350.536 | W14: =(V14-AVERAGE($V$2:$V$261))/STDEV($V$2:$V$261) -> -0.070629867 | X14: =LN(V14) -> 11.377684 | Y14: 1.1 | Z14: =(Y14-AVERAGE($Y$2:$Y$261))/STDEV($Y$2:$Y$261) -> -1.2347714 | AA14: =LN(Y14) -> 0.09531018 | AB14: 2924 | AC14: 49 | AD14: =AC14/I14 -> 0.0030619259 | AE14: =0.5*T14+0.5*U14 -> -0.45176051 | AF14: =AE14*P14 -> 0.058728866 | AG14: =LN(1+AF14) -> 0.057069006 | AH14: =(AF14-AVERAGE($AF$2:$AF$261))/STDEV($AF$2:$AF$261) -> 0.60947585 | AI14: =LN(F14)-LN(F13) -> -0.08113619 | AJ14: =K14-K13 -> -0.25031616 | AK14: =Y14-Y13 -> 0.1 | AL14: =LN(V14)-LN(V13) -> 0.0069756138
A15: AI | B15: 2017 | C15: 1 | D15: 0 | E15: 0 | F15: 1087.17 | G15: =(F15-AVERAGE($F$2:$F$261))/STDEV($F$2:$F$261) -> -0.94680364 | H15: =LN(F15) -> 6.9913333 | I15: 16105 | J15: -43 | K15: =(J15/I15)*100 -> -0.26699783 | L15: =(K15-AVERAGE($K$2:$K$261))/STDEV($K$2:$K$261) -> -0.78257344 | M15: 1.0635157 | N15: =(M15-AVERAGE($M$2:$M$261))/STDEV($M$2:$M$261) -> 1.538032 | O15: 1.56 | P15: -0.15 | Q15: 137023 | R15: =[1]Feuil1!J49/panel_choc_taux_suisse_2014_202!Q15 -> 5052.9656 | S15: 40.3 | T15: =(R15-AVERAGE($R$2:$R$261))/STDEV($R$2:$R$261) -> -0.85922494 | U15: =(S15-AVERAGE($S$2:$S$261))/STDEV($S$2:$S$261) -> -0.042248874 | V15: 87699.938 | W15: =(V15-AVERAGE($V$2:$V$261))/STDEV($V$2:$V$261) -> -0.050806144 | X15: =LN(V15) -> 11.381676 | Y15: 1 | Z15: =(Y15-AVERAGE($Y$2:$Y$261))/STDEV($Y$2:$Y$261) -> -1.3209106 | AA15: =LN(Y15) -> 0 | AB15: 3013 | AC15: 63 | AD15: =AC15/I15 -> 0.0039118286 | AE15: =0.5*T15+0.5*U15 -> -0.45073691 | AF15: =AE15*P15 -> 0.067610536 | AG15: =LN(1+AF15) -> 0.065423007 | AH15: =(AF15-AVERAGE($AF$2:$AF$261))/STDEV($AF$2:$AF$261) -> 0.70081168 | AI15: =LN(F15)-LN(F14) -> -0.020935167 | AJ15: =K15-K14 -> -0.2170072 | AK15: =Y15-Y14 -> -0.1 | AL15: =LN(V15)-LN(V14) -> 0.0039920212
A16: AI | B16: 2018 | C16: 1 | D16: 0 | E16: 0 | F16: 1134.17 | G16: =(F16-AVERAGE($F$2:$F$261))/STDEV($F$2:$F$261) -> -0.70855877 | H16: =LN(F16) -> 7.0336564 | I16: 16145 | J16: -53 | K16: =(J16/I16)*100 -> -0.32827501 | L16: =(K16-AVERAGE($K$2:$K$261))/STDEV($K$2:$K$261) -> -0.97216407 | M16: 1.0301139 | N16: =(M16-AVERAGE($M$2:$M$261))/STDEV($M$2:$M$261) -> 0.14360417 | O16: 1.5 | P16: -0.06 | Q16: 131491 | R16: =[1]Feuil1!J50/panel_choc_taux_suisse_2014_202!Q16 -> 5405.9908 | S16: 38.8 | T16: =(R16-AVERAGE($R$2:$R$261))/STDEV($R$2:$R$261) -> -0.85328829 | U16: =(S16-AVERAGE($S$2:$S$261))/STDEV($S$2:$S$261) -> -0.19369245 | V16: 88138.438 | W16: =(V16-AVERAGE($V$2:$V$261))/STDEV($V$2:$V$261) -> -0.025927372 | X16: =LN(V16) -> 11.386664 | Y16: 1 | Z16: =(Y16-AVERAGE($Y$2:$Y$261))/STDEV($Y$2:$Y$261) -> -1.3209106 | AA16: =LN(Y16) -> 0 | AB16: 3091 | AC16: 134 | AD16: =AC16/I16 -> 0.0082997832 | AE16: =0.5*T16+0.5*U16 -> -0.52349037 | AF16: =AE16*P16 -> 0.031409422 | AG16: =LN(1+AF16) -> 0.030926238 | AH16: =(AF16-AVERAGE($AF$2:$AF$261))/STDEV($AF$2:$AF$261) -> 0.32853271 | AI16: =LN(F16)-LN(F15) -> 0.042323116 | AJ16: =K16-K15 -> -0.061277181 | AK16: =Y16-Y15 -> 0 | AL16: =LN(V16)-LN(V15) -> 0.0049875415
A17: AI | B17: 2019 | C17: 1 | D17: 0 | E17: 0 | F17: 1345.2 | G17: =(F17-AVERAGE($F$2:$F$261))/STDEV($F$2:$F$261) -> 0.3611607 | H17: =LN(F17) -> 7.204298 | I17: 16128 | J17: -96 | K17: =(J17/I17)*100 -> -0.5952381 | L17: =(K17-AVERAGE($K$2:$K$261))/STDEV($K$2:$K$261) -> -1.7981436 | M17: 1.0368889 | N17: =(M17-AVERAGE($M$2:$M$261))/STDEV($M$2:$M$261) -> 0.42644191 | O17: 1.43 | P17: -0.07 | Q17: 131076 | R17: =[1]Feuil1!J51/panel_choc_taux_suisse_2014_202!Q17 -> 5570.5602 | S17: 38.8 | T17: =(R17-AVERAGE($R$2:$R$261))/STDEV($R$2:$R$261) -> -0.85052081 | U17: =(S17-AVERAGE($S$2:$S$261))/STDEV($S$2:$S$261) -> -0.19369245 | V17: 88932 | W17: =(V17-AVERAGE($V$2:$V$261))/STDEV($V$2:$V$261) -> 0.019096286 | X17: =LN(V17) -> 11.395627 | Y17: 1.1 | Z17: =(Y17-AVERAGE($Y$2:$Y$261))/STDEV($Y$2:$Y$261) -> -1.2347714 | AA17: =LN(Y17) -> 0.09531018 | AB17: 3157 | AC17: 45 | AD17: =AC17/I17 -> 0.0027901786 | AE17: =0.5*T17+0.5*U17 -> -0.52210663 | AF17: =AE17*P17 -> 0.036547464 | AG17: =LN(1+AF17) -> 0.035895444 | AH17: =(AF17-AVERAGE($AF$2:$AF$261))/STDEV($AF$2:$AF$261) -> 0.38137044 | AI17: =LN(F17)-LN(F16) -> 0.17064159 | AJ17: =K17-K16 -> -0.26696309 | AK17: =Y17-Y16 -> 0.1 | AL17: =LN(V17)-LN(V16) -> 0.008963301
A18: AI | B18: 2020 | C18: 1 | D18: 0 | E18: 0 | F18: 1354.4 | G18: =(F18-AVERAGE($F$2:$F$261))/STDEV($F$2:$F$261) -> 0.40779587 | H18: =LN(F18) -> 7.2111138 | I18: 16145 | J18: 75 | K18: =(J18/I18)*100 -> 0.46454011 | L18: =(K18-AVERAGE($K$2:$K$261))/STDEV($K$2:$K$261) -> 1.4807934 | M18: 1.0413346 | N18: =(M18-AVERAGE($M$2:$M$261))/STDEV($M$2:$M$261) -> 0.61203885 | O18: 1.33 | P18: -0.1 | Q18: 131551 | R18: =[1]Feuil1!J52/panel_choc_taux_suisse_2014_202!Q18 -> 5696.7774 | S18: 38.3 | T18: =(R18-AVERAGE($R$2:$R$261))/STDEV($R$2:$R$261) -> -0.84839828 | U18: =(S18-AVERAGE($S$2:$S$261))/STDEV($S$2:$S$261) -> -0.24417364 | V18: 89643.137 | W18: =(V18-AVERAGE($V$2:$V$261))/STDEV($V$2:$V$261) -> 0.059443437 | X18: =LN(V18) -> 11.403592 | Y18: 1.1 | Z18: =(Y18-AVERAGE($Y$2:$Y$261))/STDEV($Y$2:$Y$261) -> -1.2347714 | AA18: =LN(Y18) -> 0.09531018 | AB18: 3258 | AC18: 196 | AD18: =AC18/I18 -> 0.012139981 | AE18: =0.5*T18+0.5*U18 -> -0.54628596 | AF18: =AE18*P18 -> 0.054628596 | AG18: =LN(1+AF18) -> 0.053188663 | AH18: =(AF18-AVERAGE($AF$2:$AF$261))/STDEV($AF$2:$AF$261) -> 0.56731017 | AI18: =LN(F18)-LN(F17) -> 0.006815851 | AJ18: =K18-K17 -> 1.0597782 | AK18: =Y18-Y17 -> 0 | AL18: =LN(V18)-LN(V17) -> 0.0079646101
A19: AI | B19: 2021 | C19: 1 | D19: 0 | E19: 0 | F19: 1388.6 | G19: =(F19-AVERAGE($F$2:$F$261))/STDEV($F$2:$F$261) -> 0.58115703 | H19: =LN(F19) -> 7.2360513 | I19: 16128 | J19: -6 | K19: =(J19/I19)*100 -> -0.037202381 | L19: =(K19-AVERAGE($K$2:$K$261))/STDEV($K$2:$K$261) -> -0.071589964 | M19: 1.0457436 | N19: =(M19-AVERAGE($M$2:$M$261))/STDEV($M$2:$M$261) -> 0.79609897 | O19: 1.25 | P19: -0.08 | Q19: 132102 | R19: =[1]Feuil1!J53/panel_choc_taux_suisse_2014_202!Q19 -> 5852.6728 | S19: 38.4 | T19: =(R19-AVERAGE($R$2:$R$261))/STDEV($R$2:$R$261) -> -0.84577666 | U19: =(S19-AVERAGE($S$2:$S$261))/STDEV($S$2:$S$261) -> -0.2340774 | V19: 89463.851 | W19: =(V19-AVERAGE($V$2:$V$261))/STDEV($V$2:$V$261) -> 0.049271429 | X19: =LN(V19) -> 11.40159 | Y19: 0.8 | Z19: =(Y19-AVERAGE($Y$2:$Y$261))/STDEV($Y$2:$Y$261) -> -1.4931889 | AA19: =LN(Y19) -> -0.22314355 | AB19: 3327 | AC19: 45 | AD19: =AC19/I19 -> 0.0027901786 | AE19: =0.5*T19+0.5*U19 -> -0.53992703 | AF19: =AE19*P19 -> 0.043194162 | AG19: =LN(1+AF19) -> 0.042287316 | AH19: =(AF19-AVERAGE($AF$2:$AF$261))/STDEV($AF$2:$AF$261) -> 0.44972265 | AI19: =LN(F19)-LN(F18) -> 0.024937494 | AJ19: =K19-K18 -> -0.50174249 | AK19: =Y19-Y18 -> -0.3 | AL19: =LN(V19)-LN(V18) -> -0.0020020027
A20: AI | B20: 2022 | C20: 1 | D20: 0 | E20: 0 | F20: 1314.8 | G20: =(F20-AVERAGE($F$2:$F$261))/STDEV($F$2:$F$261) -> 0.20706189 | H20: =LN(F20) -> 7.1814398 | I20: 16360 | J20: 42 | K20: =(J20/I20)*100 -> 0.25672372 | L20: =(K20-AVERAGE($K$2:$K$261))/STDEV($K$2:$K$261) -> 0.83781273 | M20: 0.98600652 | N20: =(M20-AVERAGE($M$2:$M$261))/STDEV($M$2:$M$261) -> -1.6977493 | O20: 1.21 | P20: -0.04 | Q20: 131365 | R20: =[1]Feuil1!J54/panel_choc_taux_suisse_2014_202!Q20 -> 6060.4613 | S20: 38.1 | T20: =(R20-AVERAGE($R$2:$R$261))/STDEV($R$2:$R$261) -> -0.84228239 | U20: =(S20-AVERAGE($S$2:$S$261))/STDEV($S$2:$S$261) -> -0.26436611 | V20: 90269.025 | W20: =(V20-AVERAGE($V$2:$V$261))/STDEV($V$2:$V$261) -> 0.094953916 | X20: =LN(V20) -> 11.41055 | Y20: 0.5 | Z20: =(Y20-AVERAGE($Y$2:$Y$261))/STDEV($Y$2:$Y$261) -> -1.7516063 | AA20: =LN(Y20) -> -0.69314718 | AB20: 3350 | AC20: 73 | AD20: =AC20/I20 -> 0.0044621027 | AE20: =0.5*T20+0.5*U20 -> -0.55332425 | AF20: =AE20*P20 -> 0.02213297 | AG20: =LN(1+AF20) -> 0.021891591 | AH20: =(AF20-AVERAGE($AF$2:$AF$261))/STDEV($AF$2:$AF$261) -> 0.23313708 | AI20: =LN(F20)-LN(F19) -> -0.054611483 | AJ20: =K20-K19 -> 0.2939261 | AK20: =Y20-Y19 -> -0.3 | AL20: =LN(V20)-LN(V19) -> 0.0089597414
A21: AI | B21: 2023 | C21: 1 | D21: 0 | E21: 0 | F21: 1512.17 | G21: =(F21-AVERAGE($F$2:$F$261))/STDEV($F$2:$F$261) -> 1.2075383 | H21: =LN(F21) -> 7.321301 | I21: 16585 | J21: -28 | K21: =(J21/I21)*100 -> -0.16882725 | L21: =(K21-AVERAGE($K$2:$K$261))/STDEV($K$2:$K$261) -> -0.47883524 | M21: 1.0341431 | N21: =(M21-AVERAGE($M$2:$M$261))/STDEV($M$2:$M$261) -> 0.31181116 | O21: 1.48 | P21: 0.27 | Q21: 131788 | R21: =[1]Feuil1!J55/panel_choc_taux_suisse_2014_202!Q21 -> 6169.669 | S21: 38 | T21: =(R21-AVERAGE($R$2:$R$261))/STDEV($R$2:$R$261) -> -0.8404459 | U21: =(S21-AVERAGE($S$2:$S$261))/STDEV($S$2:$S$261) -> -0.27446235 | V21: 105614.76 | W21: =(V21-AVERAGE($V$2:$V$261))/STDEV($V$2:$V$261) -> 0.96561137 | X21: =LN(V21) -> 11.567553 | Y21: 0.5 | Z21: =(Y21-AVERAGE($Y$2:$Y$261))/STDEV($Y$2:$Y$261) -> -1.7516063 | AA21: =LN(Y21) -> -0.69314718 | AB21: 3445 | AC21: 93 | AD21: =AC21/I21 -> 0.0056074766 | AE21: =0.5*T21+0.5*U21 -> -0.55745412 | AF21: =AE21*P21 -> -0.15051261 | AG21: =LN(1+AF21) -> -0.16312219 | AH21: =(AF21-AVERAGE($AF$2:$AF$261))/STDEV($AF$2:$AF$261) -> -1.5422868 | AI21: =LN(F21)-LN(F20) -> 0.13986114 | AJ21: =K21-K20 -> -0.42555097 | AK21: =Y21-Y20 -> 0 | AL21: =LN(V21)-LN(V20) -> 0.15700375
A22: AR | B22: 2014 | C22: 1 | D22: 0 | E22: 0 | F22: 1116.17 | G22: =(F22-AVERAGE($F$2:$F$261))/STDEV($F$2:$F$261) -> -0.79980149 | H22: =LN(F22) -> 7.0176585 | I22: 54064 | J22: 103 | K22: =(J22/I22)*100 -> 0.19051495 | L22: =(K22-AVERAGE($K$2:$K$261))/STDEV($K$2:$K$261) -> 0.63296384 | M22: 1.0281149 | N22: =(M22-AVERAGE($M$2:$M$261))/STDEV($M$2:$M$261) -> 0.060154245 | O22: 1.95 | P22: 0 | Q22: 38293 | R22: =[1]Feuil1!J56/panel_choc_taux_suisse_2014_202!Q22 -> 16577.764 | S22: 34.8 | T22: =(R22-AVERAGE($R$2:$R$261))/STDEV($R$2:$R$261) -> -0.66541816 | U22: =(S22-AVERAGE($S$2:$S$261))/STDEV($S$2:$S$261) -> -0.59754197 | V22: 78168.884 | W22: =(V22-AVERAGE($V$2:$V$261))/STDEV($V$2:$V$261) -> -0.59156115 | X22: =LN(V22) -> 11.266627 | Y22: 1.7 | Z22: =(Y22-AVERAGE($Y$2:$Y$261))/STDEV($Y$2:$Y$261) -> -0.71793661 | AA22: =LN(Y22) -> 0.53062825 | AB22: 9842 | AC22: 307 | AD22: =AC22/I22 -> 0.0056784552 | AE22: =0.5*T22+0.5*U22 -> -0.63148007 | AF22: =AE22*P22 -> 0 | AG22: =LN(1+AF22) -> 0 | AH22: =(AF22-AVERAGE($AF$2:$AF$261))/STDEV($AF$2:$AF$261) -> 0.0055297297 | AI22: 0 | AJ22: 0 | AK22: 0 | AL22: 0
A23: AR | B23: 2015 | C23: 1 | D23: 0 | E23: 0 | F23: 1058.5 | G23: =(F23-AVERAGE($F$2:$F$261))/STDEV($F$2:$F$261) -> -1.092133 | H23: =LN(F23) -> 6.9646081 | I23: 54543 | J23: 71 | K23: =(J23/I23)*100 -> 0.13017252 | L23: =(K23-AVERAGE($K$2:$K$261))/STDEV($K$2:$K$261) -> 0.44626535 | M23: 1.0174024 | N23: =(M23-AVERAGE($M$2:$M$261))/STDEV($M$2:$M$261) -> -0.38706257 | O23: 1.84 | P23: -0.11 | Q23: 40236 | R23: =[1]Feuil1!J57/panel_choc_taux_suisse_2014_202!Q23 -> 16305.85 | S23: 36.3 | T23: =(R23-AVERAGE($R$2:$R$261))/STDEV($R$2:$R$261) -> -0.6699908 | U23: =(S23-AVERAGE($S$2:$S$261))/STDEV($S$2:$S$261) -> -0.4460984 | V23: 78481.56 | W23: =(V23-AVERAGE($V$2:$V$261))/STDEV($V$2:$V$261) -> -0.57382115 | X23: =LN(V23) -> 11.270619 | Y23: 1.9 | Z23: =(Y23-AVERAGE($Y$2:$Y$261))/STDEV($Y$2:$Y$261) -> -0.54565832 | AA23: =LN(Y23) -> 0.64185389 | AB23: 10056 | AC23: 233 | AD23: =AC23/I23 -> 0.0042718589 | AE23: =0.5*T23+0.5*U23 -> -0.5580446 | AF23: =AE23*P23 -> 0.061384906 | AG23: =LN(1+AF23) -> 0.059574571 | AH23: =(AF23-AVERAGE($AF$2:$AF$261))/STDEV($AF$2:$AF$261) -> 0.63678959 | AI23: =LN(F23)-LN(F22) -> -0.053050371 | AJ23: =K23-K22 -> -0.060342421 | AK23: =Y23-Y22 -> 0.2 | AL23: =LN(V23)-LN(V22) -> 0.0039920213
A24: AR | B24: 2016 | C24: 1 | D24: 0 | E24: 0 | F24: 1079.5 | G24: =(F24-AVERAGE($F$2:$F$261))/STDEV($F$2:$F$261) -> -0.98568318 | H24: =LN(F24) -> 6.9842532 | I24: 54954 | J24: -46 | K24: =(J24/I24)*100 -> -0.083706373 | L24: =(K24-AVERAGE($K$2:$K$261))/STDEV($K$2:$K$261) -> -0.21547258 | M24: 0.98347652 | N24: =(M24-AVERAGE($M$2:$M$261))/STDEV($M$2:$M$261) -> -1.8033694 | O24: 1.71 | P24: -0.13 | Q24: 40908 | R24: =[1]Feuil1!J58/panel_choc_taux_suisse_2014_202!Q24 -> 16514.694 | S24: 36.3 | T24: =(R24-AVERAGE($R$2:$R$261))/STDEV($R$2:$R$261) -> -0.66647879 | U24: =(S24-AVERAGE($S$2:$S$261))/STDEV($S$2:$S$261) -> -0.4460984 | V24: 79030.931 | W24: =(V24-AVERAGE($V$2:$V$261))/STDEV($V$2:$V$261) -> -0.54265198 | X24: =LN(V24) -> 11.277595 | Y24: 1.8 | Z24: =(Y24-AVERAGE($Y$2:$Y$261))/STDEV($Y$2:$Y$261) -> -0.63179746 | AA24: =LN(Y24) -> 0.58778666 | AB24: 10244 | AC24: 352 | AD24: =AC24/I24 -> 0.0064053572 | AE24: =0.5*T24+0.5*U24 -> -0.55628859 | AF24: =AE24*P24 -> 0.072317517 | AG24: =LN(1+AF24) -> 0.06982221 | AH24: =(AF24-AVERAGE($AF$2:$AF$261))/STDEV($AF$2:$AF$261) -> 0.74921655 | AI24: =LN(F24)-LN(F23) -> 0.019645159 | AJ24: =K24-K23 -> -0.2138789 | AK24: =Y24-Y23 -> -0.1 | AL24: =LN(V24)-LN(V23) -> 0.0069756137
A25: AR | B25: 2017 | C25: 1 | D25: 0 | E25: 0 | F25: 1086.33 | G25: =(F25-AVERAGE($F$2:$F$261))/STDEV($F$2:$F$261) -> -0.95106164 | H25: =LN(F25) -> 6.9905603 | I25: 55178 | J25: 51 | K25: =(J25/I25)*100 -> 0.092428142 | L25: =(K25-AVERAGE($K$2:$K$261))/STDEV($K$2:$K$261) -> 0.32948482 | M25: 1.0635157 | N25: =(M25-AVERAGE($M$2:$M$261))/STDEV($M$2:$M$261) -> 1.538032 | O25: 1.56 | P25: -0.15 | Q25: 39919 | R25: =[1]Feuil1!J59/panel_choc_taux_suisse_2014_202!Q25 -> 17344.435 | S25: 35.3 | T25: =(R25-AVERAGE($R$2:$R$261))/STDEV($R$2:$R$261) -> -0.65252544 | U25: =(S25-AVERAGE($S$2:$S$261))/STDEV($S$2:$S$261) -> -0.54706078 | V25: 79347.055 | W25: =(V25-AVERAGE($V$2:$V$261))/STDEV($V$2:$V$261) -> -0.52471634 | X25: =LN(V25) -> 11.281587 | Y25: 1.8 | Z25: =(Y25-AVERAGE($Y$2:$Y$261))/STDEV($Y$2:$Y$261) -> -0.63179746 | AA25: =LN(Y25) -> 0.58778666 | AB25: 10590 | AC25: 215 | AD25: =AC25/I25 -> 0.0038964805 | AE25: =0.5*T25+0.5*U25 -> -0.59979311 | AF25: =AE25*P25 -> 0.089968967 | AG25: =LN(1+AF25) -> 0.086149225 | AH25: =(AF25-AVERAGE($AF$2:$AF$261))/STDEV($AF$2:$AF$261) -> 0.93073758 | AI25: =LN(F25)-LN(F24) -> 0.0063070718 | AJ25: =K25-K24 -> 0.17613451 | AK25: =Y25-Y24 -> 0 | AL25: =LN(V25)-LN(V24) -> 0.0039920214
A26: AR | B26: 2018 | C26: 1 | D26: 0 | E26: 0 | F26: 1096.33 | G26: =(F26-AVERAGE($F$2:$F$261))/STDEV($F$2:$F$261) -> -0.90037124 | H26: =LN(F26) -> 6.9997235 | I26: 55234 | J26: -199 | K26: =(J26/I26)*100 -> -0.36028533 | L26: =(K26-AVERAGE($K$2:$K$261))/STDEV($K$2:$K$261) -> -1.0712035 | M26: 1.0301139 | N26: =(M26-AVERAGE($M$2:$M$261))/STDEV($M$2:$M$261) -> 0.14360417 | O26: 1.5 | P26: -0.06 | Q26: 39601 | R26: =[1]Feuil1!J60/panel_choc_taux_suisse_2014_202!Q26 -> 17950.03 | S26: 35 | T26: =(R26-AVERAGE($R$2:$R$261))/STDEV($R$2:$R$261) -> -0.64234145 | U26: =(S26-AVERAGE($S$2:$S$261))/STDEV($S$2:$S$261) -> -0.5773495 | V26: 79743.79 | W26: =(V26-AVERAGE($V$2:$V$261))/STDEV($V$2:$V$261) -> -0.50220712 | X26: =LN(V26) -> 11.286574 | Y26: 1.5 | Z26: =(Y26-AVERAGE($Y$2:$Y$261))/STDEV($Y$2:$Y$261) -> -0.89021489 | AA26: =LN(Y26) -> 0.40546511 | AB26: 10886 | AC26: 248 | AD26: =AC26/I26 -> 0.0044899881 | AE26: =0.5*T26+0.5*U26 -> -0.60984548 | AF26: =AE26*P26 -> 0.036590729 | AG26: =LN(1+AF26) -> 0.035937183 | AH26: =(AF26-AVERAGE($AF$2:$AF$261))/STDEV($AF$2:$AF$261) -> 0.38181536 | AI26: =LN(F26)-LN(F25) -> 0.0091631953 | AJ26: =K26-K25 -> -0.45271347 | AK26: =Y26-Y25 -> -0.3 | AL26: =LN(V26)-LN(V25) -> 0.0049875415
A27: AR | B27: 2019 | C27: 1 | D27: 0 | E27: 0 | F27: 1111.83 | G27: =(F27-AVERAGE($F$2:$F$261))/STDEV($F$2:$F$261) -> -0.82180112 | H27: =LN(F27) -> 7.0137626 | I27: 55445 | J27: 32 | K27: =(J27/I27)*100 -> 0.057714853 | L27: =(K27-AVERAGE($K$2:$K$261))/STDEV($K$2:$K$261) -> 0.22208246 | M27: 1.0368889 | N27: =(M27-AVERAGE($M$2:$M$261))/STDEV($M$2:$M$261) -> 0.42644191 | O27: 1.43 | P27: -0.07 | Q27: 40060 | R27: =[1]Feuil1!J61/panel_choc_taux_suisse_2014_202!Q27 -> 18226.829 | S27: 34.4 | T27: =(R27-AVERAGE($R$2:$R$261))/STDEV($R$2:$R$261) -> -0.63768667 | U27: =(S27-AVERAGE($S$2:$S$261))/STDEV($S$2:$S$261) -> -0.63792693 | V27: 80461 | W27: =(V27-AVERAGE($V$2:$V$261))/STDEV($V$2:$V$261) -> -0.4615154 | X27: =LN(V27) -> 11.295528 | Y27: 1.6 | Z27: =(Y27-AVERAGE($Y$2:$Y$261))/STDEV($Y$2:$Y$261) -> -0.80407575 | AA27: =LN(Y27) -> 0.47000363 | AB27: 11052 | AC27: 163 | AD27: =AC27/I27 -> 0.0029398503 | AE27: =0.5*T27+0.5*U27 -> -0.6378068 | AF27: =AE27*P27 -> 0.044646476 | AG27: =LN(1+AF27) -> 0.043678528 | AH27: =(AF27-AVERAGE($AF$2:$AF$261))/STDEV($AF$2:$AF$261) -> 0.46465771 | AI27: =LN(F27)-LN(F26) -> 0.014039068 | AJ27: =K27-K26 -> 0.41800018 | AK27: =Y27-Y26 -> 0.1 | AL27: =LN(V27)-LN(V26) -> 0.0089537262
A28: AR | B28: 2020 | C28: 1 | D28: 0 | E28: 0 | F28: 1106 | G28: =(F28-AVERAGE($F$2:$F$261))/STDEV($F$2:$F$261) -> -0.85135362 | H28: =LN(F28) -> 7.0085052 | I28: 55309 | J28: -306 | K28: =(J28/I28)*100 -> -0.55325535 | L28: =(K28-AVERAGE($K$2:$K$261))/STDEV($K$2:$K$261) -> -1.6682497 | M28: 1.0413346 | N28: =(M28-AVERAGE($M$2:$M$261))/STDEV($M$2:$M$261) -> 0.61203885 | O28: 1.33 | P28: -0.1 | Q28: 38323 | R28: =[1]Feuil1!J62/panel_choc_taux_suisse_2014_202!Q28 -> 19555.274 | S28: 34 | T28: =(R28-AVERAGE($R$2:$R$261))/STDEV($R$2:$R$261) -> -0.61534687 | U28: =(S28-AVERAGE($S$2:$S$261))/STDEV($S$2:$S$261) -> -0.67831188 | V28: 81105.176 | W28: =(V28-AVERAGE($V$2:$V$261))/STDEV($V$2:$V$261) -> -0.42496736 | X28: =LN(V28) -> 11.303502 | Y28: 2.2 | Z28: =(Y28-AVERAGE($Y$2:$Y$261))/STDEV($Y$2:$Y$261) -> -0.2872409 | AA28: =LN(Y28) -> 0.78845736 | AB28: 11206 | AC28: 215 | AD28: =AC28/I28 -> 0.0038872516 | AE28: =0.5*T28+0.5*U28 -> -0.64682937 | AF28: =AE28*P28 -> 0.064682937 | AG28: =LN(1+AF28) -> 0.062677043 | AH28: =(AF28-AVERAGE($AF$2:$AF$261))/STDEV($AF$2:$AF$261) -> 0.67070533 | AI28: =LN(F28)-LN(F27) -> -0.0052574033 | AJ28: =K28-K27 -> -0.6109702 | AK28: =Y28-Y27 -> 0.6 | AL28: =LN(V28)-LN(V27) -> 0.0079741848
A29: AR | B29: 2021 | C29: 1 | D29: 0 | E29: 0 | F29: 1147.83 | G29: =(F29-AVERAGE($F$2:$F$261))/STDEV($F$2:$F$261) -> -0.63931569 | H29: =LN(F29) -> 7.0456285 | I29: 55585 | J29: 157 | K29: =(J29/I29)*100 -> 0.2824503 | L29: =(K29-AVERAGE($K$2:$K$261))/STDEV($K$2:$K$261) -> 0.91741038 | M29: 1.0457436 | N29: =(M29-AVERAGE($M$2:$M$261))/STDEV($M$2:$M$261) -> 0.79609897 | O29: 1.25 | P29: -0.08 | Q29: 39391 | R29: =[1]Feuil1!J63/panel_choc_taux_suisse_2014_202!Q29 -> 19627.574 | S29: 34 | T29: =(R29-AVERAGE($R$2:$R$261))/STDEV($R$2:$R$261) -> -0.61413103 | U29: =(S29-AVERAGE($S$2:$S$261))/STDEV($S$2:$S$261) -> -0.67831188 | V29: 80942.966 | W29: =(V29-AVERAGE($V$2:$V$261))/STDEV($V$2:$V$261) -> -0.43417055 | X29: =LN(V29) -> 11.3015 | Y29: 1.9 | Z29: =(Y29-AVERAGE($Y$2:$Y$261))/STDEV($Y$2:$Y$261) -> -0.54565832 | AA29: =LN(Y29) -> 0.64185389 | AB29: 11410 | AC29: 241 | AD29: =AC29/I29 -> 0.0043357021 | AE29: =0.5*T29+0.5*U29 -> -0.64622145 | AF29: =AE29*P29 -> 0.051697716 | AG29: =LN(1+AF29) -> 0.050405731 | AH29: =(AF29-AVERAGE($AF$2:$AF$261))/STDEV($AF$2:$AF$261) -> 0.53717008 | AI29: =LN(F29)-LN(F28) -> 0.0371233 | AJ29: =K29-K28 -> 0.83570565 | AK29: =Y29-Y28 -> -0.3 | AL29: =LN(V29)-LN(V28) -> -0.0020020026
A30: AR | B30: 2022 | C30: 1 | D30: 0 | E30: 0 | F30: 1157.83 | G30: =(F30-AVERAGE($F$2:$F$261))/STDEV($F$2:$F$261) -> -0.58862529 | H30: =LN(F30) -> 7.0543028 | I30: 55759 | J30: -91 | K30: =(J30/I30)*100 -> -0.16320235 | L30: =(K30-AVERAGE($K$2:$K$261))/STDEV($K$2:$K$261) -> -0.46143188 | M30: 0.98600652 | N30: =(M30-AVERAGE($M$2:$M$261))/STDEV($M$2:$M$261) -> -1.6977493 | O30: 1.21 | P30: -0.04 | Q30: 38325 | R30: =[1]Feuil1!J64/panel_choc_taux_suisse_2014_202!Q30 -> 20773.19 | S30: 33.4 | T30: =(R30-AVERAGE($R$2:$R$261))/STDEV($R$2:$R$261) -> -0.59486579 | U30: =(S30-AVERAGE($S$2:$S$261))/STDEV($S$2:$S$261) -> -0.73888931 | V30: 81671.452 | W30: =(V30-AVERAGE($V$2:$V$261))/STDEV($V$2:$V$261) -> -0.39283904 | X30: =LN(V30) -> 11.31046 | Y30: 1.3 | Z30: =(Y30-AVERAGE($Y$2:$Y$261))/STDEV($Y$2:$Y$261) -> -1.0624932 | AA30: =LN(Y30) -> 0.26236426 | AB30: 11647 | AC30: 198 | AD30: =AC30/I30 -> 0.0035509963 | AE30: =0.5*T30+0.5*U30 -> -0.66687755 | AF30: =AE30*P30 -> 0.026675102 | AG30: =LN(1+AF30) -> 0.026325524 | AH30: =(AF30-AVERAGE($AF$2:$AF$261))/STDEV($AF$2:$AF$261) -> 0.27984669 | AI30: =LN(F30)-LN(F29) -> 0.0086743602 | AJ30: =K30-K29 -> -0.44565265 | AK30: =Y30-Y29 -> -0.6 | AL30: =LN(V30)-LN(V29) -> 0.0089597414
A31: AR | B31: 2023 | C31: 1 | D31: 0 | E31: 0 | F31: 1285.29 | G31: =(F31-AVERAGE($F$2:$F$261))/STDEV($F$2:$F$261) -> 0.057474528 | H31: =LN(F31) -> 7.1587397 | I31: 56495 | J31: 58 | K31: =(J31/I31)*100 -> 0.10266395 | L31: =(K31-AVERAGE($K$2:$K$261))/STDEV($K$2:$K$261) -> 0.36115426 | M31: 1.0341431 | N31: =(M31-AVERAGE($M$2:$M$261))/STDEV($M$2:$M$261) -> 0.31181116 | O31: 1.48 | P31: 0.27 | Q31: 39609 | R31: =[1]Feuil1!J65/panel_choc_taux_suisse_2014_202!Q31 -> 20527.868 | S31: 34.1 | T31: =(R31-AVERAGE($R$2:$R$261))/STDEV($R$2:$R$261) -> -0.59899123 | U31: =(S31-AVERAGE($S$2:$S$261))/STDEV($S$2:$S$261) -> -0.66821564 | V31: 95555.599 | W31: =(V31-AVERAGE($V$2:$V$261))/STDEV($V$2:$V$261) -> 0.39489361 | X31: =LN(V31) -> 11.467464 | Y31: 1.2 | Z31: =(Y31-AVERAGE($Y$2:$Y$261))/STDEV($Y$2:$Y$261) -> -1.1486323 | AA31: =LN(Y31) -> 0.18232156 | AB31: 11966 | AC31: 215 | AD31: =AC31/I31 -> 0.0038056465 | AE31: =0.5*T31+0.5*U31 -> -0.63360344 | AF31: =AE31*P31 -> -0.17107293 | AG31: =LN(1+AF31) -> -0.1876231 | AH31: =(AF31-AVERAGE($AF$2:$AF$261))/STDEV($AF$2:$AF$261) -> -1.7537215 | AI31: =LN(F31)-LN(F30) -> 0.10443681 | AJ31: =K31-K30 -> 0.26586631 | AK31: =Y31-Y30 -> -0.1 | AL31: =LN(V31)-LN(V30) -> 0.15700375
A32: BE | B32: 2014 | C32: 0 | D32: 0 | E32: 1 | F32: 1176 | G32: =(F32-AVERAGE($F$2:$F$261))/STDEV($F$2:$F$261) -> -0.49652083 | H32: =LN(F32) -> 7.0698741 | I32: 1009370 | J32: 712 | K32: =(J32/I32)*100 -> 0.070539049 | L32: =(K32-AVERAGE($K$2:$K$261))/STDEV($K$2:$K$261) -> 0.26176032 | M32: 1.0281149 | N32: =(M32-AVERAGE($M$2:$M$261))/STDEV($M$2:$M$261) -> 0.060154245 | O32: 1.95 | P32: 0 | Q32: 5311 | R32: =[1]Feuil1!J66/panel_choc_taux_suisse_2014_202!Q32 -> 119527.84 | S32: 47 | T32: =(R32-AVERAGE($R$2:$R$261))/STDEV($R$2:$R$261) -> 1.0658417 | U32: =(S32-AVERAGE($S$2:$S$261))/STDEV($S$2:$S$261) -> 0.63419908 | V32: 74053.074 | W32: =(V32-AVERAGE($V$2:$V$261))/STDEV($V$2:$V$261) -> -0.82507629 | X32: =LN(V32) -> 11.212537 | Y32: 2.3 | Z32: =(Y32-AVERAGE($Y$2:$Y$261))/STDEV($Y$2:$Y$261) -> -0.20110176 | AA32: =LN(Y32) -> 0.83290912 | AB32: 197134 | AC32: 4240 | AD32: =AC32/I32 -> 0.00420064 | AE32: =0.5*T32+0.5*U32 -> 0.8500204 | AF32: =AE32*P32 -> 0 | AG32: =LN(1+AF32) -> 0 | AH32: =(AF32-AVERAGE($AF$2:$AF$261))/STDEV($AF$2:$AF$261) -> 0.0055297297 | AI32: 0 | AJ32: 0 | AK32: 0 | AL32: 0
A33: BE | B33: 2015 | C33: 0 | D33: 0 | E33: 1 | F33: 1131.83 | G33: =(F33-AVERAGE($F$2:$F$261))/STDEV($F$2:$F$261) -> -0.72042032 | H33: =LN(F33) -> 7.0315911 | I33: 1017434 | J33: 856 | K33: =(J33/I33)*100 -> 0.084133221 | L33: =(K33-AVERAGE($K$2:$K$261))/STDEV($K$2:$K$261) -> 0.30382047 | M33: 1.0174024 | N33: =(M33-AVERAGE($M$2:$M$261))/STDEV($M$2:$M$261) -> -0.38706257 | O33: 1.84 | P33: -0.11 | Q33: 5595 | R33: =[1]Feuil1!J67/panel_choc_taux_suisse_2014_202!Q33 -> 117262.23 | S33: 49.7 | T33: =(R33-AVERAGE($R$2:$R$261))/STDEV($R$2:$R$261) -> 1.0277422 | U33: =(S33-AVERAGE($S$2:$S$261))/STDEV($S$2:$S$261) -> 0.90679752 | V33: 74349.286 | W33: =(V33-AVERAGE($V$2:$V$261))/STDEV($V$2:$V$261) -> -0.80827035 | X33: =LN(V33) -> 11.216529 | Y33: 2.5 | Z33: =(Y33-AVERAGE($Y$2:$Y$261))/STDEV($Y$2:$Y$261) -> -0.028823482 | AA33: =LN(Y33) -> 0.91629073 | AB33: 201208 | AC33: 4812 | AD33: =AC33/I33 -> 0.0047295451 | AE33: =0.5*T33+0.5*U33 -> 0.96726985 | AF33: =AE33*P33 -> -0.10639968 | AG33: =LN(1+AF33) -> -0.11249668 | AH33: =(AF33-AVERAGE($AF$2:$AF$261))/STDEV($AF$2:$AF$261) -> -1.0886456 | AI33: =LN(F33)-LN(F32) -> -0.038283058 | AJ33: =K33-K32 -> 0.013594172 | AK33: =Y33-Y32 -> 0.2 | AL33: =LN(V33)-LN(V32) -> 0.0039920213
A34: BE | B34: 2016 | C34: 0 | D34: 0 | E34: 1 | F34: 1151.17 | G34: =(F34-AVERAGE($F$2:$F$261))/STDEV($F$2:$F$261) -> -0.62238509 | H34: =LN(F34) -> 7.0485341 | I34: 1026464 | J34: 748 | K34: =(J34/I34)*100 -> 0.072871528 | L34: =(K34-AVERAGE($K$2:$K$261))/STDEV($K$2:$K$261) -> 0.26897697 | M34: 0.98347652 | N34: =(M34-AVERAGE($M$2:$M$261))/STDEV($M$2:$M$261) -> -1.8033694 | O34: 1.71 | P34: -0.13 | Q34: 5583 | R34: =[1]Feuil1!J68/panel_choc_taux_suisse_2014_202!Q34 -> 121007.18 | S34: 50.6 | T34: =(R34-AVERAGE($R$2:$R$261))/STDEV($R$2:$R$261) -> 1.0907191 | U34: =(S34-AVERAGE($S$2:$S$261))/STDEV($S$2:$S$261) -> 0.99766366 | V34: 74869.731 | W34: =(V34-AVERAGE($V$2:$V$261))/STDEV($V$2:$V$261) -> -0.77874232 | X34: =LN(V34) -> 11.223505 | Y34: 2.7 | Z34: =(Y34-AVERAGE($Y$2:$Y$261))/STDEV($Y$2:$Y$261) -> 0.1434548 | AA34: =LN(Y34) -> 0.99325177 | AB34: 204977 | AC34: 4283 | AD34: =AC34/I34 -> 0.0041725769 | AE34: =0.5*T34+0.5*U34 -> 1.0441914 | AF34: =AE34*P34 -> -0.13574488 | AG34: =LN(1+AF34) -> -0.14588728 | AH34: =(AF34-AVERAGE($AF$2:$AF$261))/STDEV($AF$2:$AF$261) -> -1.3904208 | AI34: =LN(F34)-LN(F33) -> 0.016943025 | AJ34: =K34-K33 -> -0.011261694 | AK34: =Y34-Y33 -> 0.2 | AL34: =LN(V34)-LN(V33) -> 0.0069756137
A35: BE | B35: 2017 | C35: 0 | D35: 0 | E35: 1 | F35: 1153.83 | G35: =(F35-AVERAGE($F$2:$F$261))/STDEV($F$2:$F$261) -> -0.60890145 | H35: =LN(F35) -> 7.0508421 | I35: 1031080 | J35: 364 | K35: =(J35/I35)*100 -> 0.035302789 | L35: =(K35-AVERAGE($K$2:$K$261))/STDEV($K$2:$K$261) -> 0.15273989 | M35: 1.0635157 | N35: =(M35-AVERAGE($M$2:$M$261))/STDEV($M$2:$M$261) -> 1.538032 | O35: 1.56 | P35: -0.15 | Q35: 5814 | R35: =[1]Feuil1!J69/panel_choc_taux_suisse_2014_202!Q35 -> 119087.12 | S35: 49.1 | T35: =(R35-AVERAGE($R$2:$R$261))/STDEV($R$2:$R$261) -> 1.0584304 | U35: =(S35-AVERAGE($S$2:$S$261))/STDEV($S$2:$S$261) -> 0.84622009 | V35: 75169.21 | W35: =(V35-AVERAGE($V$2:$V$261))/STDEV($V$2:$V$261) -> -0.76175104 | X35: =LN(V35) -> 11.227497 | Y35: 2.5 | Z35: =(Y35-AVERAGE($Y$2:$Y$261))/STDEV($Y$2:$Y$261) -> -0.028823482 | AA35: =LN(Y35) -> 0.91629073 | AB35: 211983 | AC35: 4282 | AD35: =AC35/I35 -> 0.004152927 | AE35: =0.5*T35+0.5*U35 -> 0.95232525 | AF35: =AE35*P35 -> -0.14284879 | AG35: =LN(1+AF35) -> -0.15414093 | AH35: =(AF35-AVERAGE($AF$2:$AF$261))/STDEV($AF$2:$AF$261) -> -1.4634748 | AI35: =LN(F35)-LN(F34) -> 0.0023080271 | AJ35: =K35-K34 -> -0.037568739 | AK35: =Y35-Y34 -> -0.2 | AL35: =LN(V35)-LN(V34) -> 0.0039920213
A36: BE | B36: 2018 | C36: 0 | D36: 0 | E36: 1 | F36: 1181 | G36: =(F36-AVERAGE($F$2:$F$261))/STDEV($F$2:$F$261) -> -0.47117564 | H36: =LN(F36) -> 7.0741168 | I36: 1034931 | J36: 57 | K36: =(J36/I36)*100 -> 0.0055076136 | L36: =(K36-AVERAGE($K$2:$K$261))/STDEV($K$2:$K$261) -> 0.060554083 | M36: 1.0301139 | N36: =(M36-AVERAGE($M$2:$M$261))/STDEV($M$2:$M$261) -> 0.14360417 | O36: 1.5 | P36: -0.06 | Q36: 5523 | R36: =[1]Feuil1!J70/panel_choc_taux_suisse_2014_202!Q36 -> 128705.26 | S36: 46.2 | T36: =(R36-AVERAGE($R$2:$R$261))/STDEV($R$2:$R$261) -> 1.2201738 | U36: =(S36-AVERAGE($S$2:$S$261))/STDEV($S$2:$S$261) -> 0.55342918 | V36: 75545.056 | W36: =(V36-AVERAGE($V$2:$V$261))/STDEV($V$2:$V$261) -> -0.740427 | X36: =LN(V36) -> 11.232485 | Y36: 1.9 | Z36: =(Y36-AVERAGE($Y$2:$Y$261))/STDEV($Y$2:$Y$261) -> -0.54565832 | AA36: =LN(Y36) -> 0.64185389 | AB36: 215471 | AC36: 4970 | AD36: =AC36/I36 -> 0.0048022525 | AE36: =0.5*T36+0.5*U36 -> 0.88680151 | AF36: =AE36*P36 -> -0.053208091 | AG36: =LN(1+AF36) -> -0.054675947 | AH36: =(AF36-AVERAGE($AF$2:$AF$261))/STDEV($AF$2:$AF$261) -> -0.54164276 | AI36: =LN(F36)-LN(F35) -> 0.023274694 | AJ36: =K36-K35 -> -0.029795176 | AK36: =Y36-Y35 -> -0.6 | AL36: =LN(V36)-LN(V35) -> 0.0049875415
A37: BE | B37: 2019 | C37: 0 | D37: 0 | E37: 1 | F37: 1201.33 | G37: =(F37-AVERAGE($F$2:$F$261))/STDEV($F$2:$F$261) -> -0.36812206 | H37: =LN(F37) -> 7.0911846 | I37: 1039426 | J37: 75 | K37: =(J37/I37)*100 -> 0.0072155209 | L37: =(K37-AVERAGE($K$2:$K$261))/STDEV($K$2:$K$261) -> 0.065838322 | M37: 1.0368889 | N37: =(M37-AVERAGE($M$2:$M$261))/STDEV($M$2:$M$261) -> 0.42644191 | O37: 1.43 | P37: -0.07 | Q37: 5263 | R37: =[1]Feuil1!J71/panel_choc_taux_suisse_2014_202!Q37 -> 138735.85 | S37: 42.9 | T37: =(R37-AVERAGE($R$2:$R$261))/STDEV($R$2:$R$261) -> 1.3888532 | U37: =(S37-AVERAGE($S$2:$S$261))/STDEV($S$2:$S$261) -> 0.22025332 | V37: 76225 | W37: =(V37-AVERAGE($V$2:$V$261))/STDEV($V$2:$V$261) -> -0.70184961 | X37: =LN(V37) -> 11.241445 | Y37: 1.8 | Z37: =(Y37-AVERAGE($Y$2:$Y$261))/STDEV($Y$2:$Y$261) -> -0.63179746 | AA37: =LN(Y37) -> 0.58778666 | AB37: 218932 | AC37: 3417 | AD37: =AC37/I37 -> 0.0032873913 | AE37: =0.5*T37+0.5*U37 -> 0.80455327 | AF37: =AE37*P37 -> -0.056318729 | AG37: =LN(1+AF37) -> -0.057966806 | AH37: =(AF37-AVERAGE($AF$2:$AF$261))/STDEV($AF$2:$AF$261) -> -0.57363142 | AI37: =LN(F37)-LN(F36) -> 0.017067739 | AJ37: =K37-K36 -> 0.0017079073 | AK37: =Y37-Y36 -> -0.1 | AL37: =LN(V37)-LN(V36) -> 0.0089602457
A38: BE | B38: 2020 | C38: 0 | D38: 0 | E38: 1 | F38: 1216.5 | G38: =(F38-AVERAGE($F$2:$F$261))/STDEV($F$2:$F$261) -> -0.29122472 | H38: =LN(F38) -> 7.1037332 | I38: 1043081 | J38: 250 | K38: =(J38/I38)*100 -> 0.023967458 | L38: =(K38-AVERAGE($K$2:$K$261))/STDEV($K$2:$K$261) -> 0.11766855 | M38: 1.0413346 | N38: =(M38-AVERAGE($M$2:$M$261))/STDEV($M$2:$M$261) -> 0.61203885 | O38: 1.33 | P38: -0.1 | Q38: 5262 | R38: =[1]Feuil1!J72/panel_choc_taux_suisse_2014_202!Q38 -> 142420.52 | S38: 44.4 | T38: =(R38-AVERAGE($R$2:$R$261))/STDEV($R$2:$R$261) -> 1.4508165 | U38: =(S38-AVERAGE($S$2:$S$261))/STDEV($S$2:$S$261) -> 0.37169689 | V38: 76834.761 | W38: =(V38-AVERAGE($V$2:$V$261))/STDEV($V$2:$V$261) -> -0.66725413 | X38: =LN(V38) -> 11.249412 | Y38: 2.5 | Z38: =(Y38-AVERAGE($Y$2:$Y$261))/STDEV($Y$2:$Y$261) -> -0.028823482 | AA38: =LN(Y38) -> 0.91629073 | AB38: 222418 | AC38: 3613 | AD38: =AC38/I38 -> 0.003463777 | AE38: =0.5*T38+0.5*U38 -> 0.9112567 | AF38: =AE38*P38 -> -0.09112567 | AG38: =LN(1+AF38) -> -0.095548446 | AH38: =(AF38-AVERAGE($AF$2:$AF$261))/STDEV($AF$2:$AF$261) -> -0.93157324 | AI38: =LN(F38)-LN(F37) -> 0.012548607 | AJ38: =K38-K37 -> 0.016751937 | AK38: =Y38-Y37 -> 0.7 | AL38: =LN(V38)-LN(V37) -> 0.0079676652
A39: BE | B39: 2021 | C39: 0 | D39: 0 | E39: 1 | F39: 1232 | G39: =(F39-AVERAGE($F$2:$F$261))/STDEV($F$2:$F$261) -> -0.2126546 | H39: =LN(F39) -> 7.1163941 | I39: 1047422 | J39: 183 | K39: =(J39/I39)*100 -> 0.017471468 | L39: =(K39-AVERAGE($K$2:$K$261))/STDEV($K$2:$K$261) -> 0.09757006 | M39: 1.0457436 | N39: =(M39-AVERAGE($M$2:$M$261))/STDEV($M$2:$M$261) -> 0.79609897 | O39: 1.25 | P39: -0.08 | Q39: 5700 | R39: =[1]Feuil1!J73/panel_choc_taux_suisse_2014_202!Q39 -> 135640.31 | S39: 48.2 | T39: =(R39-AVERAGE($R$2:$R$261))/STDEV($R$2:$R$261) -> 1.3367972 | U39: =(S39-AVERAGE($S$2:$S$261))/STDEV($S$2:$S$261) -> 0.75535394 | V39: 76681.092 | W39: =(V39-AVERAGE($V$2:$V$261))/STDEV($V$2:$V$261) -> -0.67597274 | X39: =LN(V39) -> 11.24741 | Y39: 2.4 | Z39: =(Y39-AVERAGE($Y$2:$Y$261))/STDEV($Y$2:$Y$261) -> -0.11496262 | AA39: =LN(Y39) -> 0.87546874 | AB39: 226516 | AC39: 3532 | AD39: =AC39/I39 -> 0.0033720888 | AE39: =0.5*T39+0.5*U39 -> 1.0460756 | AF39: =AE39*P39 -> -0.083686046 | AG39: =LN(1+AF39) -> -0.087396228 | AH39: =(AF39-AVERAGE($AF$2:$AF$261))/STDEV($AF$2:$AF$261) -> -0.85506687 | AI39: =LN(F39)-LN(F38) -> 0.012660982 | AJ39: =K39-K38 -> -0.0064959899 | AK39: =Y39-Y38 -> -0.1 | AL39: =LN(V39)-LN(V38) -> -0.0020020026
A40: BE | B40: 2022 | C40: 0 | D40: 0 | E40: 1 | F40: 1243.67 | G40: =(F40-AVERAGE($F$2:$F$261))/STDEV($F$2:$F$261) -> -0.15349891 | H40: =LN(F40) -> 7.125822 | I40: 1051437 | J40: -296 | K40: =(J40/I40)*100 -> -0.028151948 | L40: =(K40-AVERAGE($K$2:$K$261))/STDEV($K$2:$K$261) -> -0.043588068 | M40: 0.98600652 | N40: =(M40-AVERAGE($M$2:$M$261))/STDEV($M$2:$M$261) -> -1.6977493 | O40: 1.21 | P40: -0.04 | Q40: 5339 | R40: =[1]Feuil1!J74/panel_choc_taux_suisse_2014_202!Q40 -> 149116.41 | S40: 46.1 | T40: =(R40-AVERAGE($R$2:$R$261))/STDEV($R$2:$R$261) -> 1.5634179 | U40: =(S40-AVERAGE($S$2:$S$261))/STDEV($S$2:$S$261) -> 0.54333294 | V40: 77371.222 | W40: =(V40-AVERAGE($V$2:$V$261))/STDEV($V$2:$V$261) -> -0.63681745 | X40: =LN(V40) -> 11.25637 | Y40: 1.7 | Z40: =(Y40-AVERAGE($Y$2:$Y$261))/STDEV($Y$2:$Y$261) -> -0.71793661 | AA40: =LN(Y40) -> 0.53062825 | AB40: 230151 | AC40: 4361 | AD40: =AC40/I40 -> 0.004147657 | AE40: =0.5*T40+0.5*U40 -> 1.0533754 | AF40: =AE40*P40 -> -0.042135017 | AG40: =LN(1+AF40) -> -0.043048448 | AH40: =(AF40-AVERAGE($AF$2:$AF$261))/STDEV($AF$2:$AF$261) -> -0.42777134 | AI40: =LN(F40)-LN(F39) -> 0.0094278207 | AJ40: =K40-K39 -> -0.045623416 | AK40: =Y40-Y39 -> -0.7 | AL40: =LN(V40)-LN(V39) -> 0.0089597414
A41: BE | B41: 2023 | C41: 0 | D41: 0 | E41: 1 | F41: 1424.57 | G41: =(F41-AVERAGE($F$2:$F$261))/STDEV($F$2:$F$261) -> 0.7634904 | H41: =LN(F41) -> 7.2616253 | I41: 1063533 | J41: -70 | K41: =(J41/I41)*100 -> -0.0065818362 | L41: =(K41-AVERAGE($K$2:$K$261))/STDEV($K$2:$K$261) -> 0.023149517 | M41: 1.0341431 | N41: =(M41-AVERAGE($M$2:$M$261))/STDEV($M$2:$M$261) -> 0.31181116 | O41: 1.48 | P41: 0.27 | Q41: 5321 | R41: =[1]Feuil1!J75/panel_choc_taux_suisse_2014_202!Q41 -> 152807.43 | S41: 46.8 | T41: =(R41-AVERAGE($R$2:$R$261))/STDEV($R$2:$R$261) -> 1.625488 | U41: =(S41-AVERAGE($S$2:$S$261))/STDEV($S$2:$S$261) -> 0.61400661 | V41: 90524.329 | W41: =(V41-AVERAGE($V$2:$V$261))/STDEV($V$2:$V$261) -> 0.10943887 | X41: =LN(V41) -> 11.413374 | Y41: 1.4 | Z41: =(Y41-AVERAGE($Y$2:$Y$261))/STDEV($Y$2:$Y$261) -> -0.97635403 | AA41: =LN(Y41) -> 0.33647224 | AB41: 234806 | AC41: 3165 | AD41: =AC41/I41 -> 0.0029759302 | AE41: =0.5*T41+0.5*U41 -> 1.1197473 | AF41: =AE41*P41 -> 0.30233178 | AG41: =LN(1+AF41) -> 0.26415633 | AH41: =(AF41-AVERAGE($AF$2:$AF$261))/STDEV($AF$2:$AF$261) -> 3.1145988 | AI41: =LN(F41)-LN(F40) -> 0.13580333 | AJ41: =K41-K40 -> 0.021570112 | AK41: =Y41-Y40 -> -0.3 | AL41: =LN(V41)-LN(V40) -> 0.15700375
A42: BL | B42: 2014 | C42: 0 | D42: 1 | E42: 0 | F42: 1344.17 | G42: =(F42-AVERAGE($F$2:$F$261))/STDEV($F$2:$F$261) -> 0.35593959 | H42: =LN(F42) -> 7.203532 | I42: 281301 | J42: 835 | K42: =(J42/I42)*100 -> 0.29683506 | L42: =(K42-AVERAGE($K$2:$K$261))/STDEV($K$2:$K$261) -> 0.9619166 | M42: 1.0281149 | N42: =(M42-AVERAGE($M$2:$M$261))/STDEV($M$2:$M$261) -> 0.060154245 | O42: 1.95 | P42: 0 | Q42: 18080 | R42: =[1]Feuil1!J76/panel_choc_taux_suisse_2014_202!Q42 -> 35111.302 | S42: 41.6 | T42: =(R42-AVERAGE($R$2:$R$261))/STDEV($R$2:$R$261) -> -0.35374893 | U42: =(S42-AVERAGE($S$2:$S$261))/STDEV($S$2:$S$261) -> 0.089002223 | V42: 91180.267 | W42: =(V42-AVERAGE($V$2:$V$261))/STDEV($V$2:$V$261) -> 0.14665421 | X42: =LN(V42) -> 11.420594 | Y42: 2.7 | Z42: =(Y42-AVERAGE($Y$2:$Y$261))/STDEV($Y$2:$Y$261) -> 0.1434548 | AA42: =LN(Y42) -> 0.99325177 | AB42: 57721 | AC42: 1196 | AD42: =AC42/I42 -> 0.0042516735 | AE42: =0.5*T42+0.5*U42 -> -0.13237335 | AF42: =AE42*P42 -> 0 | AG42: =LN(1+AF42) -> 0 | AH42: =(AF42-AVERAGE($AF$2:$AF$261))/STDEV($AF$2:$AF$261) -> 0.0055297297 | AI42: 0 | AJ42: 0 | AK42: 0 | AL42: 0
A43: BL | B43: 2015 | C43: 0 | D43: 1 | E43: 0 | F43: 1299.33 | G43: =(F43-AVERAGE($F$2:$F$261))/STDEV($F$2:$F$261) -> 0.12864385 | H43: =LN(F43) -> 7.169604 | I43: 283231 | J43: 613 | K43: =(J43/I43)*100 -> 0.21643111 | L43: =(K43-AVERAGE($K$2:$K$261))/STDEV($K$2:$K$261) -> 0.71314805 | M43: 1.0174024 | N43: =(M43-AVERAGE($M$2:$M$261))/STDEV($M$2:$M$261) -> -0.38706257 | O43: 1.84 | P43: -0.11 | Q43: 18823 | R43: =[1]Feuil1!J77/panel_choc_taux_suisse_2014_202!Q43 -> 34855.347 | S43: 42.8 | T43: =(R43-AVERAGE($R$2:$R$261))/STDEV($R$2:$R$261) -> -0.3580532 | U43: =(S43-AVERAGE($S$2:$S$261))/STDEV($S$2:$S$261) -> 0.21015708 | V43: 91544.988 | W43: =(V43-AVERAGE($V$2:$V$261))/STDEV($V$2:$V$261) -> 0.16734707 | X43: =LN(V43) -> 11.424586 | Y43: 2.7 | Z43: =(Y43-AVERAGE($Y$2:$Y$261))/STDEV($Y$2:$Y$261) -> 0.1434548 | AA43: =LN(Y43) -> 0.99325177 | AB43: 59013 | AC43: 1678 | AD43: =AC43/I43 -> 0.0059244927 | AE43: =0.5*T43+0.5*U43 -> -0.073948059 | AF43: =AE43*P43 -> 0.0081342865 | AG43: =LN(1+AF43) -> 0.0081013815 | AH43: =(AF43-AVERAGE($AF$2:$AF$261))/STDEV($AF$2:$AF$261) -> 0.089179748 | AI43: =LN(F43)-LN(F42) -> -0.033927975 | AJ43: =K43-K42 -> -0.080403952 | AK43: =Y43-Y42 -> 0 | AL43: =LN(V43)-LN(V42) -> 0.0039920212
A44: BL | B44: 2016 | C44: 0 | D44: 1 | E44: 0 | F44: 1309.17 | G44: =(F44-AVERAGE($F$2:$F$261))/STDEV($F$2:$F$261) -> 0.1785232 | H44: =LN(F44) -> 7.1771486 | I44: 285624 | J44: 834 | K44: =(J44/I44)*100 -> 0.29199227 | L44: =(K44-AVERAGE($K$2:$K$261))/STDEV($K$2:$K$261) -> 0.94693308 | M44: 0.98347652 | N44: =(M44-AVERAGE($M$2:$M$261))/STDEV($M$2:$M$261) -> -1.8033694 | O44: 1.71 | P44: -0.13 | Q44: 18471 | R44: =[1]Feuil1!J78/panel_choc_taux_suisse_2014_202!Q44 -> 36575.339 | S44: 43.3 | T44: =(R44-AVERAGE($R$2:$R$261))/STDEV($R$2:$R$261) -> -0.32912894 | U44: =(S44-AVERAGE($S$2:$S$261))/STDEV($S$2:$S$261) -> 0.26063827 | V44: 92185.803 | W44: =(V44-AVERAGE($V$2:$V$261))/STDEV($V$2:$V$261) -> 0.20370442 | X44: =LN(V44) -> 11.431561 | Y44: 3 | Z44: =(Y44-AVERAGE($Y$2:$Y$261))/STDEV($Y$2:$Y$261) -> 0.40187222 | AA44: =LN(Y44) -> 1.0986123 | AB44: 60116 | AC44: 1586 | AD44: =AC44/I44 -> 0.0055527547 | AE44: =0.5*T44+0.5*U44 -> -0.034245334 | AF44: =AE44*P44 -> 0.0044518935 | AG44: =LN(1+AF44) -> 0.0044420131 | AH44: =(AF44-AVERAGE($AF$2:$AF$261))/STDEV($AF$2:$AF$261) -> 0.051311369 | AI44: =LN(F44)-LN(F43) -> 0.0075446016 | AJ44: =K44-K43 -> 0.075561159 | AK44: =Y44-Y43 -> 0.3 | AL44: =LN(V44)-LN(V43) -> 0.0069756138
A45: BL | B45: 2017 | C45: 0 | D45: 1 | E45: 0 | F45: 1332.83 | G45: =(F45-AVERAGE($F$2:$F$261))/STDEV($F$2:$F$261) -> 0.29845668 | H45: =LN(F45) -> 7.1950598 | I45: 287023 | J45: 702 | K45: =(J45/I45)*100 -> 0.2445797 | L45: =(K45-AVERAGE($K$2:$K$261))/STDEV($K$2:$K$261) -> 0.80023934 | M45: 1.0635157 | N45: =(M45-AVERAGE($M$2:$M$261))/STDEV($M$2:$M$261) -> 1.538032 | O45: 1.56 | P45: -0.15 | Q45: 17903 | R45: =[1]Feuil1!J79/panel_choc_taux_suisse_2014_202!Q45 -> 38673.547 | S45: 42.7 | T45: =(R45-AVERAGE($R$2:$R$261))/STDEV($R$2:$R$261) -> -0.29384443 | U45: =(S45-AVERAGE($S$2:$S$261))/STDEV($S$2:$S$261) -> 0.20006084 | V45: 92554.546 | W45: =(V45-AVERAGE($V$2:$V$261))/STDEV($V$2:$V$261) -> 0.22462548 | X45: =LN(V45) -> 11.435553 | Y45: 2.9 | Z45: =(Y45-AVERAGE($Y$2:$Y$261))/STDEV($Y$2:$Y$261) -> 0.31573308 | AA45: =LN(Y45) -> 1.0647107 | AB45: 62227 | AC45: 1479 | AD45: =AC45/I45 -> 0.0051528972 | AE45: =0.5*T45+0.5*U45 -> -0.046891795 | AF45: =AE45*P45 -> 0.0070337692 | AG45: =LN(1+AF45) -> 0.0070091476 | AH45: =(AF45-AVERAGE($AF$2:$AF$261))/STDEV($AF$2:$AF$261) -> 0.077862432 | AI45: =LN(F45)-LN(F44) -> 0.017911153 | AJ45: =K45-K44 -> -0.047412567 | AK45: =Y45-Y44 -> -0.1 | AL45: =LN(V45)-LN(V44) -> 0.0039920213
A46: BL | B46: 2018 | C46: 0 | D46: 1 | E46: 0 | F46: 1372.67 | G46: =(F46-AVERAGE($F$2:$F$261))/STDEV($F$2:$F$261) -> 0.50040723 | H46: =LN(F46) -> 7.224513 | I46: 288132 | J46: 314 | K46: =(J46/I46)*100 -> 0.10897783 | L46: =(K46-AVERAGE($K$2:$K$261))/STDEV($K$2:$K$261) -> 0.38068929 | M46: 1.0301139 | N46: =(M46-AVERAGE($M$2:$M$261))/STDEV($M$2:$M$261) -> 0.14360417 | O46: 1.5 | P46: -0.06 | Q46: 17932 | R46: =[1]Feuil1!J80/panel_choc_taux_suisse_2014_202!Q46 -> 39640.818 | S46: 39.9 | T46: =(R46-AVERAGE($R$2:$R$261))/STDEV($R$2:$R$261) -> -0.27757832 | U46: =(S46-AVERAGE($S$2:$S$261))/STDEV($S$2:$S$261) -> -0.082633826 | V46: 93017.318 | W46: =(V46-AVERAGE($V$2:$V$261))/STDEV($V$2:$V$261) -> 0.25088141 | X46: =LN(V46) -> 11.440541 | Y46: 2.2 | Z46: =(Y46-AVERAGE($Y$2:$Y$261))/STDEV($Y$2:$Y$261) -> -0.2872409 | AA46: =LN(Y46) -> 0.78845736 | AB46: 63207 | AC46: 1329 | AD46: =AC46/I46 -> 0.0046124693 | AE46: =0.5*T46+0.5*U46 -> -0.18010608 | AF46: =AE46*P46 -> 0.010806365 | AG46: =LN(1+AF46) -> 0.010748393 | AH46: =(AF46-AVERAGE($AF$2:$AF$261))/STDEV($AF$2:$AF$261) -> 0.11665842 | AI46: =LN(F46)-LN(F45) -> 0.029453247 | AJ46: =K46-K45 -> -0.13560187 | AK46: =Y46-Y45 -> -0.7 | AL46: =LN(V46)-LN(V45) -> 0.0049875415
A47: BL | B47: 2019 | C47: 0 | D47: 1 | E47: 0 | F47: 1374.5 | G47: =(F47-AVERAGE($F$2:$F$261))/STDEV($F$2:$F$261) -> 0.50968357 | H47: =LN(F47) -> 7.2258453 | I47: 289468 | J47: 467 | K47: =(J47/I47)*100 -> 0.16133044 | L47: =(K47-AVERAGE($K$2:$K$261))/STDEV($K$2:$K$261) -> 0.54266745 | M47: 1.0368889 | N47: =(M47-AVERAGE($M$2:$M$261))/STDEV($M$2:$M$261) -> 0.42644191 | O47: 1.43 | P47: -0.07 | Q47: 16844 | R47: =[1]Feuil1!J81/panel_choc_taux_suisse_2014_202!Q47 -> 43348.774 | S47: 39.4 | T47: =(R47-AVERAGE($R$2:$R$261))/STDEV($R$2:$R$261) -> -0.21522347 | U47: =(S47-AVERAGE($S$2:$S$261))/STDEV($S$2:$S$261) -> -0.13311502 | V47: 93854 | W47: =(V47-AVERAGE($V$2:$V$261))/STDEV($V$2:$V$261) -> 0.29835148 | X47: =LN(V47) -> 11.449496 | Y47: 1.9 | Z47: =(Y47-AVERAGE($Y$2:$Y$261))/STDEV($Y$2:$Y$261) -> -0.54565832 | AA47: =LN(Y47) -> 0.64185389 | AB47: 64200 | AC47: 1191 | AD47: =AC47/I47 -> 0.0041144444 | AE47: =0.5*T47+0.5*U47 -> -0.17416924 | AF47: =AE47*P47 -> 0.012191847 | AG47: =LN(1+AF47) -> 0.012118125 | AH47: =(AF47-AVERAGE($AF$2:$AF$261))/STDEV($AF$2:$AF$261) -> 0.13090621 | AI47: =LN(F47)-LN(F46) -> 0.0013322803 | AJ47: =K47-K46 -> 0.052352611 | AK47: =Y47-Y46 -> -0.3 | AL47: =LN(V47)-LN(V46) -> 0.0089546872
A48: BL | B48: 2020 | C48: 0 | D48: 1 | E48: 0 | F48: 1384.83 | G48: =(F48-AVERAGE($F$2:$F$261))/STDEV($F$2:$F$261) -> 0.56204675 | H48: =LN(F48) -> 7.2333327 | I48: 290969 | J48: 693 | K48: =(J48/I48)*100 -> 0.2381697 | L48: =(K48-AVERAGE($K$2:$K$261))/STDEV($K$2:$K$261) -> 0.7804069 | M48: 1.0413346 | N48: =(M48-AVERAGE($M$2:$M$261))/STDEV($M$2:$M$261) -> 0.61203885 | O48: 1.33 | P48: -0.1 | Q48: 18637 | R48: =[1]Feuil1!J82/panel_choc_taux_suisse_2014_202!Q48 -> 40211.234 | S48: 41 | T48: =(R48-AVERAGE($R$2:$R$261))/STDEV($R$2:$R$261) -> -0.26798592 | U48: =(S48-AVERAGE($S$2:$S$261))/STDEV($S$2:$S$261) -> 0.028424794 | V48: 94605.31 | W48: =(V48-AVERAGE($V$2:$V$261))/STDEV($V$2:$V$261) -> 0.3409779 | X48: =LN(V48) -> 11.457469 | Y48: 2.6 | Z48: =(Y48-AVERAGE($Y$2:$Y$261))/STDEV($Y$2:$Y$261) -> 0.057315659 | AA48: =LN(Y48) -> 0.95551145 | AB48: 65116 | AC48: 1619 | AD48: =AC48/I48 -> 0.0055641666 | AE48: =0.5*T48+0.5*U48 -> -0.11978056 | AF48: =AE48*P48 -> 0.011978056 | AG48: =LN(1+AF48) -> 0.011906887 | AH48: =(AF48-AVERAGE($AF$2:$AF$261))/STDEV($AF$2:$AF$261) -> 0.12870767 | AI48: =LN(F48)-LN(F47) -> 0.0074873598 | AJ48: =K48-K47 -> 0.076839261 | AK48: =Y48-Y47 -> 0.7 | AL48: =LN(V48)-LN(V47) -> 0.0079732238
A49: BL | B49: 2021 | C49: 0 | D49: 1 | E49: 0 | F49: 1417.17 | G49: =(F49-AVERAGE($F$2:$F$261))/STDEV($F$2:$F$261) -> 0.7259795 | H49: =LN(F49) -> 7.2564172 | I49: 292817 | J49: 1411 | K49: =(J49/I49)*100 -> 0.48187093 | L49: =(K49-AVERAGE($K$2:$K$261))/STDEV($K$2:$K$261) -> 1.5344146 | M49: 1.0457436 | N49: =(M49-AVERAGE($M$2:$M$261))/STDEV($M$2:$M$261) -> 0.79609897 | O49: 1.25 | P49: -0.08 | Q49: 18090 | R49: =[1]Feuil1!J83/panel_choc_taux_suisse_2014_202!Q49 -> 42739.071 | S49: 40.2 | T49: =(R49-AVERAGE($R$2:$R$261))/STDEV($R$2:$R$261) -> -0.22547655 | U49: =(S49-AVERAGE($S$2:$S$261))/STDEV($S$2:$S$261) -> -0.052345112 | V49: 94416.1 | W49: =(V49-AVERAGE($V$2:$V$261))/STDEV($V$2:$V$261) -> 0.33024283 | X49: =LN(V49) -> 11.455467 | Y49: 2.5 | Z49: =(Y49-AVERAGE($Y$2:$Y$261))/STDEV($Y$2:$Y$261) -> -0.028823482 | AA49: =LN(Y49) -> 0.91629073 | AB49: 66312 | AC49: 1617 | AD49: =AC49/I49 -> 0.0055222204 | AE49: =0.5*T49+0.5*U49 -> -0.13891083 | AF49: =AE49*P49 -> 0.011112867 | AG49: =LN(1+AF49) -> 0.011051572 | AH49: =(AF49-AVERAGE($AF$2:$AF$261))/STDEV($AF$2:$AF$261) -> 0.11981037 | AI49: =LN(F49)-LN(F48) -> 0.023084537 | AJ49: =K49-K48 -> 0.24370123 | AK49: =Y49-Y48 -> -0.1 | AL49: =LN(V49)-LN(V48) -> -0.0020020027
A50: BL | B50: 2022 | C50: 0 | D50: 1 | E50: 0 | F50: 1440.83 | G50: =(F50-AVERAGE($F$2:$F$261))/STDEV($F$2:$F$261) -> 0.84591298 | H50: =LN(F50) -> 7.2729746 | I50: 294417 | J50: 1068 | K50: =(J50/I50)*100 -> 0.36275079 | L50: =(K50-AVERAGE($K$2:$K$261))/STDEV($K$2:$K$261) -> 1.1658588 | M50: 0.98600652 | N50: =(M50-AVERAGE($M$2:$M$261))/STDEV($M$2:$M$261) -> -1.6977493 | O50: 1.21 | P50: -0.04 | Q50: 17225 | R50: =[1]Feuil1!J84/panel_choc_taux_suisse_2014_202!Q50 -> 46219.593 | S50: 38.5 | T50: =(R50-AVERAGE($R$2:$R$261))/STDEV($R$2:$R$261) -> -0.16694634 | U50: =(S50-AVERAGE($S$2:$S$261))/STDEV($S$2:$S$261) -> -0.22398116 | V50: 95265.844 | W50: =(V50-AVERAGE($V$2:$V$261))/STDEV($V$2:$V$261) -> 0.37845406 | X50: =LN(V50) -> 11.464427 | Y50: 1.9 | Z50: =(Y50-AVERAGE($Y$2:$Y$261))/STDEV($Y$2:$Y$261) -> -0.54565832 | AA50: =LN(Y50) -> 0.64185389 | AB50: 67286 | AC50: 1643 | AD50: =AC50/I50 -> 0.0055805201 | AE50: =0.5*T50+0.5*U50 -> -0.19546375 | AF50: =AE50*P50 -> 0.00781855 | AG50: =LN(1+AF50) -> 0.0077881435 | AH50: =(AF50-AVERAGE($AF$2:$AF$261))/STDEV($AF$2:$AF$261) -> 0.08593283 | AI50: =LN(F50)-LN(F49) -> 0.016557411 | AJ50: =K50-K49 -> -0.11912014 | AK50: =Y50-Y49 -> -0.6 | AL50: =LN(V50)-LN(V49) -> 0.0089597413
A51: BL | B51: 2023 | C51: 0 | D51: 1 | E51: 0 | F51: 1654.57 | G51: =(F51-AVERAGE($F$2:$F$261))/STDEV($F$2:$F$261) -> 1.9293696 | H51: =LN(F51) -> 7.4112964 | I51: 298837 | J51: 842 | K51: =(J51/I51)*100 -> 0.28175895 | L51: =(K51-AVERAGE($K$2:$K$261))/STDEV($K$2:$K$261) -> 0.91527135 | M51: 1.0341431 | N51: =(M51-AVERAGE($M$2:$M$261))/STDEV($M$2:$M$261) -> 0.31181116 | O51: 1.48 | P51: 0.27 | Q51: 17797 | R51: =[1]Feuil1!J85/panel_choc_taux_suisse_2014_202!Q51 -> 45686.82 | S51: 39.3 | T51: =(R51-AVERAGE($R$2:$R$261))/STDEV($R$2:$R$261) -> -0.17590572 | U51: =(S51-AVERAGE($S$2:$S$261))/STDEV($S$2:$S$261) -> -0.14321126 | V51: 111461.04 | W51: =(V51-AVERAGE($V$2:$V$261))/STDEV($V$2:$V$261) -> 1.2973065 | X51: =LN(V51) -> 11.62143 | Y51: 1.8 | Z51: =(Y51-AVERAGE($Y$2:$Y$261))/STDEV($Y$2:$Y$261) -> -0.63179746 | AA51: =LN(Y51) -> 0.58778666 | AB51: 68536 | AC51: 1480 | AD51: =AC51/I51 -> 0.0049525327 | AE51: =0.5*T51+0.5*U51 -> -0.15955849 | AF51: =AE51*P51 -> -0.043080791 | AG51: =LN(1+AF51) -> -0.044036313 | AH51: =(AF51-AVERAGE($AF$2:$AF$261))/STDEV($AF$2:$AF$261) -> -0.43749733 | AI51: =LN(F51)-LN(F50) -> 0.13832182 | AJ51: =K51-K50 -> -0.08099184 | AK51: =Y51-Y50 -> -0.1 | AL51: =LN(V51)-LN(V50) -> 0.15700375
A52: BS | B52: 2014 | C52: 0 | D52: 0 | E52: 1 | F52: 1361.17 | G52: =(F52-AVERAGE($F$2:$F$261))/STDEV($F$2:$F$261) -> 0.44211327 | H52: =LN(F52) -> 7.2160999 | I52: 190580 | J52: -1552 | K52: =(J52/I52)*100 -> -0.81435618 | L52: =(K52-AVERAGE($K$2:$K$261))/STDEV($K$2:$K$261) -> -2.4760915 | M52: 1.0281149 | N52: =(M52-AVERAGE($M$2:$M$261))/STDEV($M$2:$M$261) -> 0.060154245 | O52: 1.95 | P52: 0 | Q52: 4463 | R52: =[1]Feuil1!J86/panel_choc_taux_suisse_2014_202!Q52 -> 142238.93 | S52: 41.7 | T52: =(R52-AVERAGE($R$2:$R$261))/STDEV($R$2:$R$261) -> 1.4477628 | U52: =(S52-AVERAGE($S$2:$S$261))/STDEV($S$2:$S$261) -> 0.099098461 | V52: 94405.057 | W52: =(V52-AVERAGE($V$2:$V$261))/STDEV($V$2:$V$261) -> 0.32961634 | X52: =LN(V52) -> 11.45535 | Y52: 3.4 | Z52: =(Y52-AVERAGE($Y$2:$Y$261))/STDEV($Y$2:$Y$261) -> 0.74642878 | AA52: =LN(Y52) -> 1.2237754 | AB52: 38809 | AC52: 377 | AD52: =AC52/I52 -> 0.0019781719 | AE52: =0.5*T52+0.5*U52 -> 0.77343063 | AF52: =AE52*P52 -> 0 | AG52: =LN(1+AF52) -> 0 | AH52: =(AF52-AVERAGE($AF$2:$AF$261))/STDEV($AF$2:$AF$261) -> 0.0055297297 | AI52: 0 | AJ52: 0 | AK52: 0 | AL52: 0
A53: BS | B53: 2015 | C53: 0 | D53: 0 | E53: 1 | F53: 1321.5 | G53: =(F53-AVERAGE($F$2:$F$261))/STDEV($F$2:$F$261) -> 0.24102446 | H53: =LN(F53) -> 7.1865227 | I53: 191817 | J53: -1485 | K53: =(J53/I53)*100 -> -0.77417539 | L53: =(K53-AVERAGE($K$2:$K$261))/STDEV($K$2:$K$261) -> -2.3517728 | M53: 1.0174024 | N53: =(M53-AVERAGE($M$2:$M$261))/STDEV($M$2:$M$261) -> -0.38706257 | O53: 1.84 | P53: -0.11 | Q53: 5044 | R53: =[1]Feuil1!J87/panel_choc_taux_suisse_2014_202!Q53 -> 130071.81 | S53: 48.4 | T53: =(R53-AVERAGE($R$2:$R$261))/STDEV($R$2:$R$261) -> 1.2431544 | U53: =(S53-AVERAGE($S$2:$S$261))/STDEV($S$2:$S$261) -> 0.77554642 | V53: 94782.678 | W53: =(V53-AVERAGE($V$2:$V$261))/STDEV($V$2:$V$261) -> 0.35104105 | X53: =LN(V53) -> 11.459342 | Y53: 3.7 | Z53: =(Y53-AVERAGE($Y$2:$Y$261))/STDEV($Y$2:$Y$261) -> 1.0048462 | AA53: =LN(Y53) -> 1.3083328 | AB53: 38866 | AC53: 780 | AD53: =AC53/I53 -> 0.0040663758 | AE53: =0.5*T53+0.5*U53 -> 1.0093504 | AF53: =AE53*P53 -> -0.11102854 | AG53: =LN(1+AF53) -> -0.11769015 | AH53: =(AF53-AVERAGE($AF$2:$AF$261))/STDEV($AF$2:$AF$261) -> -1.1362471 | AI53: =LN(F53)-LN(F52) -> -0.029577169 | AJ53: =K53-K52 -> 0.04018079 | AK53: =Y53-Y52 -> 0.3 | AL53: =LN(V53)-LN(V52) -> 0.0039920213
A54: BS | B54: 2016 | C54: 0 | D54: 0 | E54: 1 | F54: 1326.33 | G54: =(F54-AVERAGE($F$2:$F$261))/STDEV($F$2:$F$261) -> 0.26550792 | H54: =LN(F54) -> 7.190171 | I54: 193070 | J54: -1718 | K54: =(J54/I54)*100 -> -0.8898327 | L54: =(K54-AVERAGE($K$2:$K$261))/STDEV($K$2:$K$261) -> -2.7096147 | M54: 0.98347652 | N54: =(M54-AVERAGE($M$2:$M$261))/STDEV($M$2:$M$261) -> -1.8033694 | O54: 1.71 | P54: -0.13 | Q54: 4509 | R54: =[1]Feuil1!J88/panel_choc_taux_suisse_2014_202!Q54 -> 149829.92 | S54: 47.5 | T54: =(R54-AVERAGE($R$2:$R$261))/STDEV($R$2:$R$261) -> 1.5754167 | U54: =(S54-AVERAGE($S$2:$S$261))/STDEV($S$2:$S$261) -> 0.68468028 | V54: 95446.156 | W54: =(V54-AVERAGE($V$2:$V$261))/STDEV($V$2:$V$261) -> 0.38868426 | X54: =LN(V54) -> 11.466318 | Y54: 3.9 | Z54: =(Y54-AVERAGE($Y$2:$Y$261))/STDEV($Y$2:$Y$261) -> 1.1771245 | AA54: =LN(Y54) -> 1.3609766 | AB54: 38834 | AC54: 412 | AD54: =AC54/I54 -> 0.0021339411 | AE54: =0.5*T54+0.5*U54 -> 1.1300485 | AF54: =AE54*P54 -> -0.1469063 | AG54: =LN(1+AF54) -> -0.15888589 | AH54: =(AF54-AVERAGE($AF$2:$AF$261))/STDEV($AF$2:$AF$261) -> -1.5052008 | AI54: =LN(F54)-LN(F53) -> 0.0036482745 | AJ54: =K54-K53 -> -0.11565732 | AK54: =Y54-Y53 -> 0.2 | AL54: =LN(V54)-LN(V53) -> 0.0069756137
A55: BS | B55: 2017 | C55: 0 | D55: 0 | E55: 1 | F55: 1330.83 | G55: =(F55-AVERAGE($F$2:$F$261))/STDEV($F$2:$F$261) -> 0.2883186 | H55: =LN(F55) -> 7.1935581 | I55: 193908 | J55: -1308 | K55: =(J55/I55)*100 -> -0.67454669 | L55: =(K55-AVERAGE($K$2:$K$261))/STDEV($K$2:$K$261) -> -2.0435232 | M55: 1.0635157 | N55: =(M55-AVERAGE($M$2:$M$261))/STDEV($M$2:$M$261) -> 1.538032 | O55: 1.56 | P55: -0.15 | Q55: 5230 | R55: =[1]Feuil1!J89/panel_choc_taux_suisse_2014_202!Q55 -> 132384.8 | S55: 49.1 | T55: =(R55-AVERAGE($R$2:$R$261))/STDEV($R$2:$R$261) -> 1.2820509 | U55: =(S55-AVERAGE($S$2:$S$261))/STDEV($S$2:$S$261) -> 0.84622009 | V55: 95827.941 | W55: =(V55-AVERAGE($V$2:$V$261))/STDEV($V$2:$V$261) -> 0.41034524 | X55: =LN(V55) -> 11.47031 | Y55: 3.6 | Z55: =(Y55-AVERAGE($Y$2:$Y$261))/STDEV($Y$2:$Y$261) -> 0.91870706 | AA55: =LN(Y55) -> 1.2809338 | AB55: 38739 | AC55: 372 | AD55: =AC55/I55 -> 0.0019184355 | AE55: =0.5*T55+0.5*U55 -> 1.0641355 | AF55: =AE55*P55 -> -0.15962032 | AG55: =LN(1+AF55) -> -0.17390149 | AH55: =(AF55-AVERAGE($AF$2:$AF$261))/STDEV($AF$2:$AF$261) -> -1.6359471 | AI55: =LN(F55)-LN(F54) -> 0.0033870782 | AJ55: =K55-K54 -> 0.21528601 | AK55: =Y55-Y54 -> -0.3 | AL55: =LN(V55)-LN(V54) -> 0.0039920213
A56: BS | B56: 2018 | C56: 0 | D56: 0 | E56: 1 | F56: 1410.33 | G56: =(F56-AVERAGE($F$2:$F$261))/STDEV($F$2:$F$261) -> 0.69130727 | H56: =LN(F56) -> 7.251579 | I56: 194766 | J56: -1525 | K56: =(J56/I56)*100 -> -0.78299087 | L56: =(K56-AVERAGE($K$2:$K$261))/STDEV($K$2:$K$261) -> -2.3790478 | M56: 1.0301139 | N56: =(M56-AVERAGE($M$2:$M$261))/STDEV($M$2:$M$261) -> 0.14360417 | O56: 1.5 | P56: -0.06 | Q56: 4783 | R56: =[1]Feuil1!J90/panel_choc_taux_suisse_2014_202!Q56 -> 148617.84 | S56: 45.1 | T56: =(R56-AVERAGE($R$2:$R$261))/STDEV($R$2:$R$261) -> 1.5550338 | U56: =(S56-AVERAGE($S$2:$S$261))/STDEV($S$2:$S$261) -> 0.44237056 | V56: 96307.081 | W56: =(V56-AVERAGE($V$2:$V$261))/STDEV($V$2:$V$261) -> 0.43752977 | X56: =LN(V56) -> 11.475297 | Y56: 3.3 | Z56: =(Y56-AVERAGE($Y$2:$Y$261))/STDEV($Y$2:$Y$261) -> 0.66028964 | AA56: =LN(Y56) -> 1.1939225 | AB56: 38715 | AC56: 795 | AD56: =AC56/I56 -> 0.0040818213 | AE56: =0.5*T56+0.5*U56 -> 0.99870219 | AF56: =AE56*P56 -> -0.059922131 | AG56: =LN(1+AF56) -> -0.061792568 | AH56: =(AF56-AVERAGE($AF$2:$AF$261))/STDEV($AF$2:$AF$261) -> -0.61068749 | AI56: =LN(F56)-LN(F55) -> 0.058020912 | AJ56: =K56-K55 -> -0.10844418 | AK56: =Y56-Y55 -> -0.3 | AL56: =LN(V56)-LN(V55) -> 0.0049875416
A57: BS | B57: 2019 | C57: 0 | D57: 0 | E57: 1 | F57: 1401.83 | G57: =(F57-AVERAGE($F$2:$F$261))/STDEV($F$2:$F$261) -> 0.64822043 | H57: =LN(F57) -> 7.2455338 | I57: 195844 | J57: -1265 | K57: =(J57/I57)*100 -> -0.64592226 | L57: =(K57-AVERAGE($K$2:$K$261))/STDEV($K$2:$K$261) -> -1.9549597 | M57: 1.0368889 | N57: =(M57-AVERAGE($M$2:$M$261))/STDEV($M$2:$M$261) -> 0.42644191 | O57: 1.43 | P57: -0.07 | Q57: 5028 | R57: =[1]Feuil1!J91/panel_choc_taux_suisse_2014_202!Q57 -> 145220.12 | S57: 47.3 | T57: =(R57-AVERAGE($R$2:$R$261))/STDEV($R$2:$R$261) -> 1.497896 | U57: =(S57-AVERAGE($S$2:$S$261))/STDEV($S$2:$S$261) -> 0.6644878 | V57: 97174 | W57: =(V57-AVERAGE($V$2:$V$261))/STDEV($V$2:$V$261) -> 0.4867154 | X57: =LN(V57) -> 11.484258 | Y57: 3 | Z57: =(Y57-AVERAGE($Y$2:$Y$261))/STDEV($Y$2:$Y$261) -> 0.40187222 | AA57: =LN(Y57) -> 1.0986123 | AB57: 38760 | AC57: 875 | AD57: =AC57/I57 -> 0.0044678418 | AE57: =0.5*T57+0.5*U57 -> 1.0811919 | AF57: =AE57*P57 -> -0.075683432 | AG57: =LN(1+AF57) -> -0.07870066 | AH57: =(AF57-AVERAGE($AF$2:$AF$261))/STDEV($AF$2:$AF$261) -> -0.77277093 | AI57: =LN(F57)-LN(F56) -> -0.0060451936 | AJ57: =K57-K56 -> 0.13706861 | AK57: =Y57-Y56 -> -0.3 | AL57: =LN(V57)-LN(V56) -> 0.0089613413
A58: BS | B58: 2020 | C58: 0 | D58: 0 | E58: 1 | F58: 1434.33 | G58: =(F58-AVERAGE($F$2:$F$261))/STDEV($F$2:$F$261) -> 0.81296422 | H58: =LN(F58) -> 7.2684531 | I58: 196735 | J58: -1716 | K58: =(J58/I58)*100 -> -0.87223931 | L58: =(K58-AVERAGE($K$2:$K$261))/STDEV($K$2:$K$261) -> -2.655181 | M58: 1.0413346 | N58: =(M58-AVERAGE($M$2:$M$261))/STDEV($M$2:$M$261) -> 0.61203885 | O58: 1.33 | P58: -0.1 | Q58: 5553 | R58: =[1]Feuil1!J92/panel_choc_taux_suisse_2014_202!Q58 -> 134957.1 | S58: 47.7 | T58: =(R58-AVERAGE($R$2:$R$261))/STDEV($R$2:$R$261) -> 1.3253079 | U58: =(S58-AVERAGE($S$2:$S$261))/STDEV($S$2:$S$261) -> 0.70487275 | V58: 97951.235 | W58: =(V58-AVERAGE($V$2:$V$261))/STDEV($V$2:$V$261) -> 0.53081272 | X58: =LN(V58) -> 11.492225 | Y58: 3.9 | Z58: =(Y58-AVERAGE($Y$2:$Y$261))/STDEV($Y$2:$Y$261) -> 1.1771245 | AA58: =LN(Y58) -> 1.3609766 | AB58: 38729 | AC58: 540 | AD58: =AC58/I58 -> 0.002744809 | AE58: =0.5*T58+0.5*U58 -> 1.0150903 | AF58: =AE58*P58 -> -0.10150903 | AG58: =LN(1+AF58) -> -0.10703863 | AH58: =(AF58-AVERAGE($AF$2:$AF$261))/STDEV($AF$2:$AF$261) -> -1.0383519 | AI58: =LN(F58)-LN(F57) -> 0.022919315 | AJ58: =K58-K57 -> -0.22631704 | AK58: =Y58-Y57 -> 0.9 | AL58: =LN(V58)-LN(V57) -> 0.0079665697
A59: BS | B59: 2021 | C59: 0 | D59: 0 | E59: 1 | F59: 1453.5 | G59: =(F59-AVERAGE($F$2:$F$261))/STDEV($F$2:$F$261) -> 0.91013772 | H59: =LN(F59) -> 7.2817297 | I59: 196036 | J59: -2464 | K59: =(J59/I59)*100 -> -1.256912 | L59: =(K59-AVERAGE($K$2:$K$261))/STDEV($K$2:$K$261) -> -3.8453522 | M59: 1.0457436 | N59: =(M59-AVERAGE($M$2:$M$261))/STDEV($M$2:$M$261) -> 0.79609897 | O59: 1.25 | P59: -0.08 | Q59: 4634 | R59: =[1]Feuil1!J93/panel_choc_taux_suisse_2014_202!Q59 -> 166842.85 | S59: 44.2 | T59: =(R59-AVERAGE($R$2:$R$261))/STDEV($R$2:$R$261) -> 1.8615147 | U59: =(S59-AVERAGE($S$2:$S$261))/STDEV($S$2:$S$261) -> 0.35150442 | V59: 97755.333 | W59: =(V59-AVERAGE($V$2:$V$261))/STDEV($V$2:$V$261) -> 0.51969797 | X59: =LN(V59) -> 11.490223 | Y59: 3.9 | Z59: =(Y59-AVERAGE($Y$2:$Y$261))/STDEV($Y$2:$Y$261) -> 1.1771245 | AA59: =LN(Y59) -> 1.3609766 | AB59: 38827 | AC59: 912 | AD59: =AC59/I59 -> 0.0046522067 | AE59: =0.5*T59+0.5*U59 -> 1.1065096 | AF59: =AE59*P59 -> -0.088520766 | AG59: =LN(1+AF59) -> -0.092686467 | AH59: =(AF59-AVERAGE($AF$2:$AF$261))/STDEV($AF$2:$AF$261) -> -0.90478536 | AI59: =LN(F59)-LN(F58) -> 0.0132766 | AJ59: =K59-K58 -> -0.38467269 | AK59: =Y59-Y58 -> 0 | AL59: =LN(V59)-LN(V58) -> -0.0020020027
A60: BS | B60: 2022 | C60: 0 | D60: 0 | E60: 1 | F60: 1454.5 | G60: =(F60-AVERAGE($F$2:$F$261))/STDEV($F$2:$F$261) -> 0.91520676 | H60: =LN(F60) -> 7.2824175 | I60: 196786 | J60: -1936 | K60: =(J60/I60)*100 -> -0.98380982 | L60: =(K60-AVERAGE($K$2:$K$261))/STDEV($K$2:$K$261) -> -3.0003784 | M60: 0.98600652 | N60: =(M60-AVERAGE($M$2:$M$261))/STDEV($M$2:$M$261) -> -1.6977493 | O60: 1.21 | P60: -0.04 | Q60: 5268 | R60: =[1]Feuil1!J94/panel_choc_taux_suisse_2014_202!Q60 -> 151126.14 | S60: 46.8 | T60: =(R60-AVERAGE($R$2:$R$261))/STDEV($R$2:$R$261) -> 1.5972146 | U60: =(S60-AVERAGE($S$2:$S$261))/STDEV($S$2:$S$261) -> 0.61400661 | V60: 98635.131 | W60: =(V60-AVERAGE($V$2:$V$261))/STDEV($V$2:$V$261) -> 0.5696143 | X60: =LN(V60) -> 11.499183 | Y60: 3 | Z60: =(Y60-AVERAGE($Y$2:$Y$261))/STDEV($Y$2:$Y$261) -> 0.40187222 | AA60: =LN(Y60) -> 1.0986123 | AB60: 38894 | AC60: 900 | AD60: =AC60/I60 -> 0.0045734961 | AE60: =0.5*T60+0.5*U60 -> 1.1056106 | AF60: =AE60*P60 -> -0.044224424 | AG60: =LN(1+AF60) -> -0.045232146 | AH60: =(AF60-AVERAGE($AF$2:$AF$261))/STDEV($AF$2:$AF$261) -> -0.44925802 | AI60: =LN(F60)-LN(F59) -> 0.00068775794 | AJ60: =K60-K59 -> 0.27310217 | AK60: =Y60-Y59 -> -0.9 | AL60: =LN(V60)-LN(V59) -> 0.0089597413
A61: BS | B61: 2023 | C61: 0 | D61: 0 | E61: 1 | F61: 1712.14 | G61: =(F61-AVERAGE($F$2:$F$261))/STDEV($F$2:$F$261) -> 2.2211942 | H61: =LN(F61) -> 7.4454993 | I61: 200031 | J61: -1651 | K61: =(J61/I61)*100 -> -0.82537207 | L61: =(K61-AVERAGE($K$2:$K$261))/STDEV($K$2:$K$261) -> -2.5101745 | M61: 1.0341431 | N61: =(M61-AVERAGE($M$2:$M$261))/STDEV($M$2:$M$261) -> 0.31181116 | O61: 1.48 | P61: 0.27 | Q61: 4753 | R61: =[1]Feuil1!J95/panel_choc_taux_suisse_2014_202!Q61 -> 171068.45 | S61: 43.2 | T61: =(R61-AVERAGE($R$2:$R$261))/STDEV($R$2:$R$261) -> 1.9325745 | U61: =(S61-AVERAGE($S$2:$S$261))/STDEV($S$2:$S$261) -> 0.25054203 | V61: 115403.1 | W61: =(V61-AVERAGE($V$2:$V$261))/STDEV($V$2:$V$261) -> 1.520964 | X61: =LN(V61) -> 11.656187 | Y61: 3.1 | Z61: =(Y61-AVERAGE($Y$2:$Y$261))/STDEV($Y$2:$Y$261) -> 0.48801136 | AA61: =LN(Y61) -> 1.1314021 | AB61: 39294 | AC61: 778 | AD61: =AC61/I61 -> 0.0038893971 | AE61: =0.5*T61+0.5*U61 -> 1.0915582 | AF61: =AE61*P61 -> 0.29472073 | AG61: =LN(1+AF61) -> 0.25829502 | AH61: =(AF61-AVERAGE($AF$2:$AF$261))/STDEV($AF$2:$AF$261) -> 3.0363296 | AI61: =LN(F61)-LN(F60) -> 0.16308185 | AJ61: =K61-K60 -> 0.15843776 | AK61: =Y61-Y60 -> 0.1 | AL61: =LN(V61)-LN(V60) -> 0.15700375
A62: FR | B62: 2014 | C62: 0 | D62: 0 | E62: 1 | F62: 1206.17 | G62: =(F62-AVERAGE($F$2:$F$261))/STDEV($F$2:$F$261) -> -0.3435879 | H62: =LN(F62) -> 7.0952053 | I62: 303425 | J62: 1569 | K62: =(J62/I62)*100 -> 0.51709648 | L62: =(K62-AVERAGE($K$2:$K$261))/STDEV($K$2:$K$261) -> 1.6434019 | M62: 1.0281149 | N62: =(M62-AVERAGE($M$2:$M$261))/STDEV($M$2:$M$261) -> 0.060154245 | O62: 1.95 | P62: 0 | Q62: 3861 | R62: =[1]Feuil1!J96/panel_choc_taux_suisse_2014_202!Q62 -> 164416.56 | S62: 40.1 | T62: =(R62-AVERAGE($R$2:$R$261))/STDEV($R$2:$R$261) -> 1.8207129 | U62: =(S62-AVERAGE($S$2:$S$261))/STDEV($S$2:$S$261) -> -0.06244135 | V62: 78231.395 | W62: =(V62-AVERAGE($V$2:$V$261))/STDEV($V$2:$V$261) -> -0.58801454 | X62: =LN(V62) -> 11.267426 | Y62: 2.7 | Z62: =(Y62-AVERAGE($Y$2:$Y$261))/STDEV($Y$2:$Y$261) -> 0.1434548 | AA62: =LN(Y62) -> 0.99325177 | AB62: 43493 | AC62: 2135 | AD62: =AC62/I62 -> 0.0070363352 | AE62: =0.5*T62+0.5*U62 -> 0.87913579 | AF62: =AE62*P62 -> 0 | AG62: =LN(1+AF62) -> 0 | AH62: =(AF62-AVERAGE($AF$2:$AF$261))/STDEV($AF$2:$AF$261) -> 0.0055297297 | AI62: 0 | AJ62: 0 | AK62: 0 | AL62: 0
A63: FR | B63: 2015 | C63: 0 | D63: 0 | E63: 1 | F63: 1156.17 | G63: =(F63-AVERAGE($F$2:$F$261))/STDEV($F$2:$F$261) -> -0.59703989 | H63: =LN(F63) -> 7.0528681 | I63: 307510 | J63: 936 | K63: =(J63/I63)*100 -> 0.30438035 | L63: =(K63-AVERAGE($K$2:$K$261))/STDEV($K$2:$K$261) -> 0.98526159 | M63: 1.0174024 | N63: =(M63-AVERAGE($M$2:$M$261))/STDEV($M$2:$M$261) -> -0.38706257 | O63: 1.84 | P63: -0.11 | Q63: 4422 | R63: =[1]Feuil1!J97/panel_choc_taux_suisse_2014_202!Q63 -> 148367.75 | S63: 43.1 | T63: =(R63-AVERAGE($R$2:$R$261))/STDEV($R$2:$R$261) -> 1.5508281 | U63: =(S63-AVERAGE($S$2:$S$261))/STDEV($S$2:$S$261) -> 0.2404458 | V63: 78544.321 | W63: =(V63-AVERAGE($V$2:$V$261))/STDEV($V$2:$V$261) -> -0.57026036 | X63: =LN(V63) -> 11.271418 | Y63: 2.8 | Z63: =(Y63-AVERAGE($Y$2:$Y$261))/STDEV($Y$2:$Y$261) -> 0.22959394 | AA63: =LN(Y63) -> 1.0296194 | AB63: 44779 | AC63: 2635 | AD63: =AC63/I63 -> 0.008568827 | AE63: =0.5*T63+0.5*U63 -> 0.89563696 | AF63: =AE63*P63 -> -0.098520066 | AG63: =LN(1+AF63) -> -0.10371749 | AH63: =(AF63-AVERAGE($AF$2:$AF$261))/STDEV($AF$2:$AF$261) -> -1.0076145 | AI63: =LN(F63)-LN(F62) -> -0.042337232 | AJ63: =K63-K62 -> -0.21271614 | AK63: =Y63-Y62 -> 0.1 | AL63: =LN(V63)-LN(V62) -> 0.0039920213
A64: FR | B64: 2016 | C64: 0 | D64: 0 | E64: 1 | F64: 1162.33 | G64: =(F64-AVERAGE($F$2:$F$261))/STDEV($F$2:$F$261) -> -0.56581461 | H64: =LN(F64) -> 7.0581819 | I64: 311963 | J64: 1187 | K64: =(J64/I64)*100 -> 0.38049384 | L64: =(K64-AVERAGE($K$2:$K$261))/STDEV($K$2:$K$261) -> 1.2207555 | M64: 0.98347652 | N64: =(M64-AVERAGE($M$2:$M$261))/STDEV($M$2:$M$261) -> -1.8033694 | O64: 1.71 | P64: -0.13 | Q64: 4208 | R64: =[1]Feuil1!J98/panel_choc_taux_suisse_2014_202!Q64 -> 160547.31 | S64: 39.9 | T64: =(R64-AVERAGE($R$2:$R$261))/STDEV($R$2:$R$261) -> 1.7556458 | U64: =(S64-AVERAGE($S$2:$S$261))/STDEV($S$2:$S$261) -> -0.082633826 | V64: 79094.131 | W64: =(V64-AVERAGE($V$2:$V$261))/STDEV($V$2:$V$261) -> -0.53906626 | X64: =LN(V64) -> 11.278394 | Y64: 2.8 | Z64: =(Y64-AVERAGE($Y$2:$Y$261))/STDEV($Y$2:$Y$261) -> 0.22959394 | AA64: =LN(Y64) -> 1.0296194 | AB64: 46154 | AC64: 2179 | AD64: =AC64/I64 -> 0.0069848027 | AE64: =0.5*T64+0.5*U64 -> 0.83650596 | AF64: =AE64*P64 -> -0.10874578 | AG64: =LN(1+AF64) -> -0.11512557 | AH64: =(AF64-AVERAGE($AF$2:$AF$261))/STDEV($AF$2:$AF$261) -> -1.1127719 | AI64: =LN(F64)-LN(F63) -> 0.005313793 | AJ64: =K64-K63 -> 0.076113495 | AK64: =Y64-Y63 -> 0 | AL64: =LN(V64)-LN(V63) -> 0.0069756137
A65: FR | B65: 2017 | C65: 0 | D65: 0 | E65: 1 | F65: 1189.33 | G65: =(F65-AVERAGE($F$2:$F$261))/STDEV($F$2:$F$261) -> -0.42895053 | H65: =LN(F65) -> 7.0811454 | I65: 315120 | J65: 1203 | K65: =(J65/I65)*100 -> 0.38175933 | L65: =(K65-AVERAGE($K$2:$K$261))/STDEV($K$2:$K$261) -> 1.2246709 | M65: 1.0635157 | N65: =(M65-AVERAGE($M$2:$M$261))/STDEV($M$2:$M$261) -> 1.538032 | O65: 1.56 | P65: -0.15 | Q65: 3937 | R65: =[1]Feuil1!J99/panel_choc_taux_suisse_2014_202!Q65 -> 175862.97 | S65: 39.9 | T65: =(R65-AVERAGE($R$2:$R$261))/STDEV($R$2:$R$261) -> 2.0132015 | U65: =(S65-AVERAGE($S$2:$S$261))/STDEV($S$2:$S$261) -> -0.082633826 | V65: 79410.507 | W65: =(V65-AVERAGE($V$2:$V$261))/STDEV($V$2:$V$261) -> -0.52111628 | X65: =LN(V65) -> 11.282386 | Y65: 2.6 | Z65: =(Y65-AVERAGE($Y$2:$Y$261))/STDEV($Y$2:$Y$261) -> 0.057315659 | AA65: =LN(Y65) -> 0.95551145 | AB65: 48891 | AC65: 2185 | AD65: =AC65/I65 -> 0.0069338665 | AE65: =0.5*T65+0.5*U65 -> 0.96528383 | AF65: =AE65*P65 -> -0.14479258 | AG65: =LN(1+AF65) -> -0.15641124 | AH65: =(AF65-AVERAGE($AF$2:$AF$261))/STDEV($AF$2:$AF$261) -> -1.483464 | AI65: =LN(F65)-LN(F64) -> 0.022963512 | AJ65: =K65-K64 -> 0.0012654892 | AK65: =Y65-Y64 -> -0.2 | AL65: =LN(V65)-LN(V64) -> 0.0039920212
A66: FR | B66: 2018 | C66: 0 | D66: 0 | E66: 1 | F66: 1196.83 | G66: =(F66-AVERAGE($F$2:$F$261))/STDEV($F$2:$F$261) -> -0.39093273 | H66: =LN(F66) -> 7.0874317 | I66: 318760 | J66: 1536 | K66: =(J66/I66)*100 -> 0.48186724 | L66: =(K66-AVERAGE($K$2:$K$261))/STDEV($K$2:$K$261) -> 1.5344032 | M66: 1.0301139 | N66: =(M66-AVERAGE($M$2:$M$261))/STDEV($M$2:$M$261) -> 0.14360417 | O66: 1.5 | P66: -0.06 | Q66: 3846 | R66: =[1]Feuil1!J100/panel_choc_taux_suisse_2014_202!Q66 -> 184825.57 | S66: 40.7 | T66: =(R66-AVERAGE($R$2:$R$261))/STDEV($R$2:$R$261) -> 2.1639211 | U66: =(S66-AVERAGE($S$2:$S$261))/STDEV($S$2:$S$261) -> -0.0018639209 | V66: 79807.56 | W66: =(V66-AVERAGE($V$2:$V$261))/STDEV($V$2:$V$261) -> -0.49858906 | X66: =LN(V66) -> 11.287374 | Y66: 2.6 | Z66: =(Y66-AVERAGE($Y$2:$Y$261))/STDEV($Y$2:$Y$261) -> 0.057315659 | AA66: =LN(Y66) -> 0.95551145 | AB66: 50139 | AC66: 2863 | AD66: =AC66/I66 -> 0.008981679 | AE66: =0.5*T66+0.5*U66 -> 1.0810286 | AF66: =AE66*P66 -> -0.064861714 | AG66: =LN(1+AF66) -> -0.067060861 | AH66: =(AF66-AVERAGE($AF$2:$AF$261))/STDEV($AF$2:$AF$261) -> -0.66148435 | AI66: =LN(F66)-LN(F65) -> 0.0062862714 | AJ66: =K66-K65 -> 0.10010791 | AK66: =Y66-Y65 -> 0 | AL66: =LN(V66)-LN(V65) -> 0.0049875416
A67: FR | B67: 2019 | C67: 0 | D67: 0 | E67: 1 | F67: 1217.33 | G67: =(F67-AVERAGE($F$2:$F$261))/STDEV($F$2:$F$261) -> -0.28701742 | H67: =LN(F67) -> 7.1044152 | I67: 321831 | J67: 1148 | K67: =(J67/I67)*100 -> 0.35670896 | L67: =(K67-AVERAGE($K$2:$K$261))/STDEV($K$2:$K$261) -> 1.1471655 | M67: 1.0368889 | N67: =(M67-AVERAGE($M$2:$M$261))/STDEV($M$2:$M$261) -> 0.42644191 | O67: 1.43 | P67: -0.07 | Q67: 3964 | R67: =[1]Feuil1!J101/panel_choc_taux_suisse_2014_202!Q67 -> 184199.48 | S67: 39.7 | T67: =(R67-AVERAGE($R$2:$R$261))/STDEV($R$2:$R$261) -> 2.1533925 | U67: =(S67-AVERAGE($S$2:$S$261))/STDEV($S$2:$S$261) -> -0.1028263 | V67: 80526 | W67: =(V67-AVERAGE($V$2:$V$261))/STDEV($V$2:$V$261) -> -0.45782755 | X67: =LN(V67) -> 11.296335 | Y67: 2.5 | Z67: =(Y67-AVERAGE($Y$2:$Y$261))/STDEV($Y$2:$Y$261) -> -0.028823482 | AA67: =LN(Y67) -> 0.91629073 | AB67: 51509 | AC67: 3146 | AD67: =AC67/I67 -> 0.0097753169 | AE67: =0.5*T67+0.5*U67 -> 1.0252831 | AF67: =AE67*P67 -> -0.071769817 | AG67: =LN(1+AF67) -> -0.074475534 | AH67: =(AF67-AVERAGE($AF$2:$AF$261))/STDEV($AF$2:$AF$261) -> -0.73252474 | AI67: =LN(F67)-LN(F66) -> 0.016983541 | AJ67: =K67-K66 -> -0.12515828 | AK67: =Y67-Y66 -> -0.1 | AL67: =LN(V67)-LN(V66) -> 0.0089618787
A68: FR | B68: 2020 | C68: 0 | D68: 0 | E68: 1 | F68: 1234 | G68: =(F68-AVERAGE($F$2:$F$261))/STDEV($F$2:$F$261) -> -0.20251652 | H68: =LN(F68) -> 7.1180162 | I68: 325547 | J68: 1709 | K68: =(J68/I68)*100 -> 0.5249626 | L68: =(K68-AVERAGE($K$2:$K$261))/STDEV($K$2:$K$261) -> 1.6677396 | M68: 1.0413346 | N68: =(M68-AVERAGE($M$2:$M$261))/STDEV($M$2:$M$261) -> 0.61203885 | O68: 1.33 | P68: -0.1 | Q68: 4049 | R68: =[1]Feuil1!J102/panel_choc_taux_suisse_2014_202!Q68 -> 185086.88 | S68: 38.8 | T68: =(R68-AVERAGE($R$2:$R$261))/STDEV($R$2:$R$261) -> 2.1683154 | U68: =(S68-AVERAGE($S$2:$S$261))/STDEV($S$2:$S$261) -> -0.19369245 | V68: 81170.035 | W68: =(V68-AVERAGE($V$2:$V$261))/STDEV($V$2:$V$261) -> -0.42128753 | X68: =LN(V68) -> 11.304301 | Y68: 3.3 | Z68: =(Y68-AVERAGE($Y$2:$Y$261))/STDEV($Y$2:$Y$261) -> 0.66028964 | AA68: =LN(Y68) -> 1.1939225 | AB68: 52615 | AC68: 2972 | AD68: =AC68/I68 -> 0.0091292502 | AE68: =0.5*T68+0.5*U68 -> 0.98731145 | AF68: =AE68*P68 -> -0.098731145 | AG68: =LN(1+AF68) -> -0.10395167 | AH68: =(AF68-AVERAGE($AF$2:$AF$261))/STDEV($AF$2:$AF$261) -> -1.0097852 | AI68: =LN(F68)-LN(F67) -> 0.01360099 | AJ68: =K68-K67 -> 0.16825365 | AK68: =Y68-Y67 -> 0.8 | AL68: =LN(V68)-LN(V67) -> 0.0079660323
A69: FR | B69: 2021 | C69: 0 | D69: 0 | E69: 1 | F69: 1249.67 | G69: =(F69-AVERAGE($F$2:$F$261))/STDEV($F$2:$F$261) -> -0.12308467 | H69: =LN(F69) -> 7.1306348 | I69: 329860 | J69: 1731 | K69: =(J69/I69)*100 -> 0.52476808 | L69: =(K69-AVERAGE($K$2:$K$261))/STDEV($K$2:$K$261) -> 1.6671378 | M69: 1.0457436 | N69: =(M69-AVERAGE($M$2:$M$261))/STDEV($M$2:$M$261) -> 0.79609897 | O69: 1.25 | P69: -0.08 | Q69: 4189 | R69: =[1]Feuil1!J103/panel_choc_taux_suisse_2014_202!Q69 -> 184566.67 | S69: 39.7 | T69: =(R69-AVERAGE($R$2:$R$261))/STDEV($R$2:$R$261) -> 2.1595673 | U69: =(S69-AVERAGE($S$2:$S$261))/STDEV($S$2:$S$261) -> -0.1028263 | V69: 81007.694 | W69: =(V69-AVERAGE($V$2:$V$261))/STDEV($V$2:$V$261) -> -0.43049808 | X69: =LN(V69) -> 11.302299 | Y69: 3 | Z69: =(Y69-AVERAGE($Y$2:$Y$261))/STDEV($Y$2:$Y$261) -> 0.40187222 | AA69: =LN(Y69) -> 1.0986123 | AB69: 54164 | AC69: 2127 | AD69: =AC69/I69 -> 0.0064481901 | AE69: =0.5*T69+0.5*U69 -> 1.0283705 | AF69: =AE69*P69 -> -0.08226964 | AG69: =LN(1+AF69) -> -0.085851657 | AH69: =(AF69-AVERAGE($AF$2:$AF$261))/STDEV($AF$2:$AF$261) -> -0.84050107 | AI69: =LN(F69)-LN(F68) -> 0.012618591 | AJ69: =K69-K68 -> -0.00019451798 | AK69: =Y69-Y68 -> -0.3 | AL69: =LN(V69)-LN(V68) -> -0.0020020027
A70: FR | B70: 2022 | C70: 0 | D70: 0 | E70: 1 | F70: 1252.33 | G70: =(F70-AVERAGE($F$2:$F$261))/STDEV($F$2:$F$261) -> -0.10960102 | H70: =LN(F70) -> 7.1327611 | I70: 334465 | J70: 1952 | K70: =(J70/I70)*100 -> 0.58361861 | L70: =(K70-AVERAGE($K$2:$K$261))/STDEV($K$2:$K$261) -> 1.8492204 | M70: 0.98600652 | N70: =(M70-AVERAGE($M$2:$M$261))/STDEV($M$2:$M$261) -> -1.6977493 | O70: 1.21 | P70: -0.04 | Q70: 3744 | R70: =[1]Feuil1!J104/panel_choc_taux_suisse_2014_202!Q70 -> 212642.23 | S70: 37.4 | T70: =(R70-AVERAGE($R$2:$R$261))/STDEV($R$2:$R$261) -> 2.6316999 | U70: =(S70-AVERAGE($S$2:$S$261))/STDEV($S$2:$S$261) -> -0.33503978 | V70: 81736.764 | W70: =(V70-AVERAGE($V$2:$V$261))/STDEV($V$2:$V$261) -> -0.38913352 | X70: =LN(V70) -> 11.311259 | Y70: 2.3 | Z70: =(Y70-AVERAGE($Y$2:$Y$261))/STDEV($Y$2:$Y$261) -> -0.20110176 | AA70: =LN(Y70) -> 0.83290912 | AB70: 55618 | AC70: 2501 | AD70: =AC70/I70 -> 0.0074776135 | AE70: =0.5*T70+0.5*U70 -> 1.1483301 | AF70: =AE70*P70 -> -0.045933202 | AG70: =LN(1+AF70) -> -0.047021591 | AH70: =(AF70-AVERAGE($AF$2:$AF$261))/STDEV($AF$2:$AF$261) -> -0.46683047 | AI70: =LN(F70)-LN(F69) -> 0.0021262998 | AJ70: =K70-K69 -> 0.058850531 | AK70: =Y70-Y69 -> -0.7 | AL70: =LN(V70)-LN(V69) -> 0.0089597414
A71: FR | B71: 2023 | C71: 0 | D71: 0 | E71: 1 | F71: 1388.29 | G71: =(F71-AVERAGE($F$2:$F$261))/STDEV($F$2:$F$261) -> 0.57958563 | H71: =LN(F71) -> 7.2358281 | I71: 341537 | J71: 1773 | K71: =(J71/I71)*100 -> 0.51912384 | L71: =(K71-AVERAGE($K$2:$K$261))/STDEV($K$2:$K$261) -> 1.6496746 | M71: 1.0341431 | N71: =(M71-AVERAGE($M$2:$M$261))/STDEV($M$2:$M$261) -> 0.31181116 | O71: 1.48 | P71: 0.27 | Q71: 3771 | R71: =[1]Feuil1!J105/panel_choc_taux_suisse_2014_202!Q71 -> 215616.11 | S71: 38.2 | T71: =(R71-AVERAGE($R$2:$R$261))/STDEV($R$2:$R$261) -> 2.6817101 | U71: =(S71-AVERAGE($S$2:$S$261))/STDEV($S$2:$S$261) -> -0.25426988 | V71: 95632.014 | W71: =(V71-AVERAGE($V$2:$V$261))/STDEV($V$2:$V$261) -> 0.39922907 | X71: =LN(V71) -> 11.468263 | Y71: 2.1 | Z71: =(Y71-AVERAGE($Y$2:$Y$261))/STDEV($Y$2:$Y$261) -> -0.37338004 | AA71: =LN(Y71) -> 0.74193734 | AB71: 57524 | AC71: 1803 | AD71: =AC71/I71 -> 0.0052790766 | AE71: =0.5*T71+0.5*U71 -> 1.2137201 | AF71: =AE71*P71 -> 0.32770444 | AG71: =LN(1+AF71) -> 0.28345146 | AH71: =(AF71-AVERAGE($AF$2:$AF$261))/STDEV($AF$2:$AF$261) -> 3.375522 | AI71: =LN(F71)-LN(F70) -> 0.10306696 | AJ71: =K71-K70 -> -0.064494772 | AK71: =Y71-Y70 -> -0.2 | AL71: =LN(V71)-LN(V70) -> 0.15700375
A72: GE | B72: 2014 | C72: 0 | D72: 0 | E72: 1 | F72: 1402.17 | G72: =(F72-AVERAGE($F$2:$F$261))/STDEV($F$2:$F$261) -> 0.6499439 | H72: =LN(F72) -> 7.2457763 | I72: 477385 | J72: -1861 | K72: =(J72/I72)*100 -> -0.38983211 | L72: =(K72-AVERAGE($K$2:$K$261))/STDEV($K$2:$K$261) -> -1.1626208 | M72: 1.0281149 | N72: =(M72-AVERAGE($M$2:$M$261))/STDEV($M$2:$M$261) -> 0.060154245 | O72: 1.95 | P72: 0 | Q72: 7019 | R72: =[1]Feuil1!J106/panel_choc_taux_suisse_2014_202!Q72 -> 90441.991 | S72: 46.6 | T72: =(R72-AVERAGE($R$2:$R$261))/STDEV($R$2:$R$261) -> 0.57671961 | U72: =(S72-AVERAGE($S$2:$S$261))/STDEV($S$2:$S$261) -> 0.59381413 | V72: 105579.31 | W72: =(V72-AVERAGE($V$2:$V$261))/STDEV($V$2:$V$261) -> 0.96360031 | X72: =LN(V72) -> 11.567218 | Y72: 5.5 | Z72: =(Y72-AVERAGE($Y$2:$Y$261))/STDEV($Y$2:$Y$261) -> 2.5553507 | AA72: =LN(Y72) -> 1.7047481 | AB72: 77368 | AC72: 1589 | AD72: =AC72/I72 -> 0.0033285503 | AE72: =0.5*T72+0.5*U72 -> 0.58526687 | AF72: =AE72*P72 -> 0 | AG72: =LN(1+AF72) -> 0 | AH72: =(AF72-AVERAGE($AF$2:$AF$261))/STDEV($AF$2:$AF$261) -> 0.0055297297 | AI72: 0 | AJ72: 0 | AK72: 0 | AL72: 0
A73: GE | B73: 2015 | C73: 0 | D73: 0 | E73: 1 | F73: 1365.83 | G73: =(F73-AVERAGE($F$2:$F$261))/STDEV($F$2:$F$261) -> 0.465735 | H73: =LN(F73) -> 7.2195176 | I73: 484736 | J73: -1546 | K73: =(J73/I73)*100 -> -0.31893649 | L73: =(K73-AVERAGE($K$2:$K$261))/STDEV($K$2:$K$261) -> -0.94327085 | M73: 1.0174024 | N73: =(M73-AVERAGE($M$2:$M$261))/STDEV($M$2:$M$261) -> -0.38706257 | O73: 1.84 | P73: -0.11 | Q73: 7279 | R73: =[1]Feuil1!J107/panel_choc_taux_suisse_2014_202!Q73 -> 90133.561 | S73: 48.7 | T73: =(R73-AVERAGE($R$2:$R$261))/STDEV($R$2:$R$261) -> 0.57153289 | U73: =(S73-AVERAGE($S$2:$S$261))/STDEV($S$2:$S$261) -> 0.80583513 | V73: 106001.63 | W73: =(V73-AVERAGE($V$2:$V$261))/STDEV($V$2:$V$261) -> 0.98756095 | X73: =LN(V73) -> 11.57121 | Y73: 5.6 | Z73: =(Y73-AVERAGE($Y$2:$Y$261))/STDEV($Y$2:$Y$261) -> 2.6414899 | AA73: =LN(Y73) -> 1.7227666 | AB73: 78820 | AC73: 2048 | AD73: =AC73/I73 -> 0.0042249802 | AE73: =0.5*T73+0.5*U73 -> 0.68868401 | AF73: =AE73*P73 -> -0.075755241 | AG73: =LN(1+AF73) -> -0.078778352 | AH73: =(AF73-AVERAGE($AF$2:$AF$261))/STDEV($AF$2:$AF$261) -> -0.77350939 | AI73: =LN(F73)-LN(F72) -> -0.026258734 | AJ73: =K73-K72 -> 0.070895613 | AK73: =Y73-Y72 -> 0.1 | AL73: =LN(V73)-LN(V72) -> 0.0039920217
A74: GE | B74: 2016 | C74: 0 | D74: 0 | E74: 1 | F74: 1360.67 | G74: =(F74-AVERAGE($F$2:$F$261))/STDEV($F$2:$F$261) -> 0.43957875 | H74: =LN(F74) -> 7.2157325 | I74: 489524 | J74: -1669 | K74: =(J74/I74)*100 -> -0.34094345 | L74: =(K74-AVERAGE($K$2:$K$261))/STDEV($K$2:$K$261) -> -1.01136 | M74: 0.98347652 | N74: =(M74-AVERAGE($M$2:$M$261))/STDEV($M$2:$M$261) -> -1.8033694 | O74: 1.71 | P74: -0.13 | Q74: 7427 | R74: =[1]Feuil1!J108/panel_choc_taux_suisse_2014_202!Q74 -> 90963.12 | S74: 50.4 | T74: =(R74-AVERAGE($R$2:$R$261))/STDEV($R$2:$R$261) -> 0.58548317 | U74: =(S74-AVERAGE($S$2:$S$261))/STDEV($S$2:$S$261) -> 0.97747118 | V74: 106743.64 | W74: =(V74-AVERAGE($V$2:$V$261))/STDEV($V$2:$V$261) -> 1.0296598 | X74: =LN(V74) -> 11.578185 | Y74: 5.5 | Z74: =(Y74-AVERAGE($Y$2:$Y$261))/STDEV($Y$2:$Y$261) -> 2.5553507 | AA74: =LN(Y74) -> 1.7047481 | AB74: 79992 | AC74: 1989 | AD74: =AC74/I74 -> 0.0040631307 | AE74: =0.5*T74+0.5*U74 -> 0.78147718 | AF74: =AE74*P74 -> -0.10159203 | AG74: =LN(1+AF74) -> -0.10713101 | AH74: =(AF74-AVERAGE($AF$2:$AF$261))/STDEV($AF$2:$AF$261) -> -1.0392055 | AI74: =LN(F74)-LN(F73) -> -0.003785077 | AJ74: =K74-K73 -> -0.022006954 | AK74: =Y74-Y73 -> -0.1 | AL74: =LN(V74)-LN(V73) -> 0.0069756136
A75: GE | B75: 2017 | C75: 0 | D75: 0 | E75: 1 | F75: 1369.83 | G75: =(F75-AVERAGE($F$2:$F$261))/STDEV($F$2:$F$261) -> 0.48601116 | H75: =LN(F75) -> 7.2224419 | I75: 495249 | J75: -1727 | K75: =(J75/I75)*100 -> -0.34871348 | L75: =(K75-AVERAGE($K$2:$K$261))/STDEV($K$2:$K$261) -> -1.0354004 | M75: 1.0635157 | N75: =(M75-AVERAGE($M$2:$M$261))/STDEV($M$2:$M$261) -> 1.538032 | O75: 1.56 | P75: -0.15 | Q75: 7583 | R75: =[1]Feuil1!J109/panel_choc_taux_suisse_2014_202!Q75 -> 91305.883 | S75: 50.4 | T75: =(R75-AVERAGE($R$2:$R$261))/STDEV($R$2:$R$261) -> 0.59124725 | U75: =(S75-AVERAGE($S$2:$S$261))/STDEV($S$2:$S$261) -> 0.97747118 | V75: 107170.62 | W75: =(V75-AVERAGE($V$2:$V$261))/STDEV($V$2:$V$261) -> 1.0538847 | X75: =LN(V75) -> 11.582177 | Y75: 5 | Z75: =(Y75-AVERAGE($Y$2:$Y$261))/STDEV($Y$2:$Y$261) -> 2.124655 | AA75: =LN(Y75) -> 1.6094379 | AB75: 81286 | AC75: 1977 | AD75: =AC75/I75 -> 0.0039919313 | AE75: =0.5*T75+0.5*U75 -> 0.78435922 | AF75: =AE75*P75 -> -0.11765388 | AG75: =LN(1+AF75) -> -0.12517088 | AH75: =(AF75-AVERAGE($AF$2:$AF$261))/STDEV($AF$2:$AF$261) -> -1.2043796 | AI75: =LN(F75)-LN(F74) -> 0.0067094191 | AJ75: =K75-K74 -> -0.0077700283 | AK75: =Y75-Y74 -> -0.5 | AL75: =LN(V75)-LN(V74) -> 0.0039920216
A76: GE | B76: 2018 | C76: 0 | D76: 0 | E76: 1 | F76: 1384 | G76: =(F76-AVERAGE($F$2:$F$261))/STDEV($F$2:$F$261) -> 0.55783945 | H76: =LN(F76) -> 7.2327331 | I76: 499480 | J76: -1978 | K76: =(J76/I76)*100 -> -0.39601185 | L76: =(K76-AVERAGE($K$2:$K$261))/STDEV($K$2:$K$261) -> -1.1817408 | M76: 1.0301139 | N76: =(M76-AVERAGE($M$2:$M$261))/STDEV($M$2:$M$261) -> 0.14360417 | O76: 1.5 | P76: -0.06 | Q76: 7141 | R76: =[1]Feuil1!J110/panel_choc_taux_suisse_2014_202!Q76 -> 99543.361 | S76: 47.1 | T76: =(R76-AVERAGE($R$2:$R$261))/STDEV($R$2:$R$261) -> 0.7297728 | U76: =(S76-AVERAGE($S$2:$S$261))/STDEV($S$2:$S$261) -> 0.64429532 | V76: 107706.47 | W76: =(V76-AVERAGE($V$2:$V$261))/STDEV($V$2:$V$261) -> 1.0842869 | X76: =LN(V76) -> 11.587165 | Y76: 4.3 | Z76: =(Y76-AVERAGE($Y$2:$Y$261))/STDEV($Y$2:$Y$261) -> 1.521681 | AA76: =LN(Y76) -> 1.458615 | AB76: 81957 | AC76: 2675 | AD76: =AC76/I76 -> 0.0053555698 | AE76: =0.5*T76+0.5*U76 -> 0.68703406 | AF76: =AE76*P76 -> -0.041222044 | AG76: =LN(1+AF76) -> -0.042095768 | AH76: =(AF76-AVERAGE($AF$2:$AF$261))/STDEV($AF$2:$AF$261) -> -0.41838265 | AI76: =LN(F76)-LN(F75) -> 0.010291213 | AJ76: =K76-K75 -> -0.047298377 | AK76: =Y76-Y75 -> -0.7 | AL76: =LN(V76)-LN(V75) -> 0.0049875407
A77: GE | B77: 2019 | C77: 0 | D77: 0 | E77: 1 | F77: 1413.83 | G77: =(F77-AVERAGE($F$2:$F$261))/STDEV($F$2:$F$261) -> 0.70904891 | H77: =LN(F77) -> 7.2540576 | I77: 504128 | J77: -1874 | K77: =(J77/I77)*100 -> -0.37173099 | L77: =(K77-AVERAGE($K$2:$K$261))/STDEV($K$2:$K$261) -> -1.1066162 | M77: 1.0368889 | N77: =(M77-AVERAGE($M$2:$M$261))/STDEV($M$2:$M$261) -> 0.42644191 | O77: 1.43 | P77: -0.07 | Q77: 6844 | R77: =[1]Feuil1!J111/panel_choc_taux_suisse_2014_202!Q77 -> 106687.14 | S77: 44.4 | T77: =(R77-AVERAGE($R$2:$R$261))/STDEV($R$2:$R$261) -> 0.84990608 | U77: =(S77-AVERAGE($S$2:$S$261))/STDEV($S$2:$S$261) -> 0.37169689 | V77: 108676 | W77: =(V77-AVERAGE($V$2:$V$261))/STDEV($V$2:$V$261) -> 1.1392943 | X77: =LN(V77) -> 11.596126 | Y77: 3.9 | Z77: =(Y77-AVERAGE($Y$2:$Y$261))/STDEV($Y$2:$Y$261) -> 1.1771245 | AA77: =LN(Y77) -> 1.3609766 | AB77: 82755 | AC77: 2081 | AD77: =AC77/I77 -> 0.0041279199 | AE77: =0.5*T77+0.5*U77 -> 0.61080149 | AF77: =AE77*P77 -> -0.042756104 | AG77: =LN(1+AF77) -> -0.043697065 | AH77: =(AF77-AVERAGE($AF$2:$AF$261))/STDEV($AF$2:$AF$261) -> -0.43415836 | AI77: =LN(F77)-LN(F76) -> 0.021324477 | AJ77: =K77-K76 -> 0.024280863 | AK77: =Y77-Y76 -> -0.4 | AL77: =LN(V77)-LN(V76) -> 0.0089613219
A78: GE | B78: 2020 | C78: 0 | D78: 0 | E78: 1 | F78: 1417.17 | G78: =(F78-AVERAGE($F$2:$F$261))/STDEV($F$2:$F$261) -> 0.7259795 | H78: =LN(F78) -> 7.2564172 | I78: 506343 | J78: -2649 | K78: =(J78/I78)*100 -> -0.52316315 | L78: =(K78-AVERAGE($K$2:$K$261))/STDEV($K$2:$K$261) -> -1.5751449 | M78: 1.0413346 | N78: =(M78-AVERAGE($M$2:$M$261))/STDEV($M$2:$M$261) -> 0.61203885 | O78: 1.33 | P78: -0.1 | Q78: 7615 | R78: =[1]Feuil1!J112/panel_choc_taux_suisse_2014_202!Q78 -> 98413.233 | S78: 48 | T78: =(R78-AVERAGE($R$2:$R$261))/STDEV($R$2:$R$261) -> 0.710768 | U78: =(S78-AVERAGE($S$2:$S$261))/STDEV($S$2:$S$261) -> 0.73516147 | V78: 109545.23 | W78: =(V78-AVERAGE($V$2:$V$261))/STDEV($V$2:$V$261) -> 1.1886113 | X78: =LN(V78) -> 11.604093 | Y78: 4.9 | Z78: =(Y78-AVERAGE($Y$2:$Y$261))/STDEV($Y$2:$Y$261) -> 2.0385159 | AA78: =LN(Y78) -> 1.5892352 | AB78: 82913 | AC78: 2345 | AD78: =AC78/I78 -> 0.004631248 | AE78: =0.5*T78+0.5*U78 -> 0.72296473 | AF78: =AE78*P78 -> -0.072296473 | AG78: =LN(1+AF78) -> -0.075043073 | AH78: =(AF78-AVERAGE($AF$2:$AF$261))/STDEV($AF$2:$AF$261) -> -0.73794068 | AI78: =LN(F78)-LN(F77) -> 0.0023595913 | AJ78: =K78-K77 -> -0.15143216 | AK78: =Y78-Y77 -> 1 | AL78: =LN(V78)-LN(V77) -> 0.0079665895
A79: GE | B79: 2021 | C79: 0 | D79: 0 | E79: 1 | F79: 1432.83 | G79: =(F79-AVERAGE($F$2:$F$261))/STDEV($F$2:$F$261) -> 0.80536066 | H79: =LN(F79) -> 7.2674068 | I79: 509448 | J79: -3244 | K79: =(J79/I79)*100 -> -0.63676764 | L79: =(K79-AVERAGE($K$2:$K$261))/STDEV($K$2:$K$261) -> -1.9266354 | M79: 1.0457436 | N79: =(M79-AVERAGE($M$2:$M$261))/STDEV($M$2:$M$261) -> 0.79609897 | O79: 1.25 | P79: -0.08 | Q79: 7182 | R79: =[1]Feuil1!J113/panel_choc_taux_suisse_2014_202!Q79 -> 107651.04 | S79: 48.4 | T79: =(R79-AVERAGE($R$2:$R$261))/STDEV($R$2:$R$261) -> 0.86611562 | U79: =(S79-AVERAGE($S$2:$S$261))/STDEV($S$2:$S$261) -> 0.77554642 | V79: 109326.14 | W79: =(V79-AVERAGE($V$2:$V$261))/STDEV($V$2:$V$261) -> 1.1761809 | X79: =LN(V79) -> 11.602091 | Y79: 5 | Z79: =(Y79-AVERAGE($Y$2:$Y$261))/STDEV($Y$2:$Y$261) -> 2.124655 | AA79: =LN(Y79) -> 1.6094379 | AB79: 84094 | AC79: 3229 | AD79: =AC79/I79 -> 0.0063382328 | AE79: =0.5*T79+0.5*U79 -> 0.82083102 | AF79: =AE79*P79 -> -0.065666482 | AG79: =LN(1+AF79) -> -0.067921819 | AH79: =(AF79-AVERAGE($AF$2:$AF$261))/STDEV($AF$2:$AF$261) -> -0.66976028 | AI79: =LN(F79)-LN(F78) -> 0.010989584 | AJ79: =K79-K78 -> -0.11360449 | AK79: =Y79-Y78 -> 0.1 | AL79: =LN(V79)-LN(V78) -> -0.0020020029
A80: GE | B80: 2022 | C80: 0 | D80: 0 | E80: 1 | F80: 1453.83 | G80: =(F80-AVERAGE($F$2:$F$261))/STDEV($F$2:$F$261) -> 0.9118105 | H80: =LN(F80) -> 7.2819567 | I80: 514114 | J80: -2157 | K80: =(J80/I80)*100 -> -0.41955675 | L80: =(K80-AVERAGE($K$2:$K$261))/STDEV($K$2:$K$261) -> -1.2545883 | M80: 0.98600652 | N80: =(M80-AVERAGE($M$2:$M$261))/STDEV($M$2:$M$261) -> -1.6977493 | O80: 1.21 | P80: -0.04 | Q80: 7513 | R80: =[1]Feuil1!J114/panel_choc_taux_suisse_2014_202!Q80 -> 105967.32 | S80: 47 | T80: =(R80-AVERAGE($R$2:$R$261))/STDEV($R$2:$R$261) -> 0.83780136 | U80: =(S80-AVERAGE($S$2:$S$261))/STDEV($S$2:$S$261) -> 0.63419908 | V80: 110310.08 | W80: =(V80-AVERAGE($V$2:$V$261))/STDEV($V$2:$V$261) -> 1.2320056 | X80: =LN(V80) -> 11.611051 | Y80: 3.9 | Z80: =(Y80-AVERAGE($Y$2:$Y$261))/STDEV($Y$2:$Y$261) -> 1.1771245 | AA80: =LN(Y80) -> 1.3609766 | AB80: 84870 | AC80: 3299 | AD80: =AC80/I80 -> 0.0064168647 | AE80: =0.5*T80+0.5*U80 -> 0.73600022 | AF80: =AE80*P80 -> -0.029440009 | AG80: =LN(1+AF80) -> -0.029882064 | AH80: =(AF80-AVERAGE($AF$2:$AF$261))/STDEV($AF$2:$AF$261) -> -0.29722052 | AI80: =LN(F80)-LN(F79) -> 0.014549944 | AJ80: =K80-K79 -> 0.21721089 | AK80: =Y80-Y79 -> -1.1 | AL80: =LN(V80)-LN(V79) -> 0.0089597414
A81: GE | B81: 2023 | C81: 0 | D81: 0 | E81: 1 | F81: 1668.86 | G81: =(F81-AVERAGE($F$2:$F$261))/STDEV($F$2:$F$261) -> 2.0018061 | H81: =LN(F81) -> 7.419896 | I81: 524410 | J81: -1564 | K81: =(J81/I81)*100 -> -0.29823993 | L81: =(K81-AVERAGE($K$2:$K$261))/STDEV($K$2:$K$261) -> -0.879236 | M81: 1.0341431 | N81: =(M81-AVERAGE($M$2:$M$261))/STDEV($M$2:$M$261) -> 0.31181116 | O81: 1.48 | P81: 0.27 | Q81: 7603 | R81: =[1]Feuil1!J115/panel_choc_taux_suisse_2014_202!Q81 -> 106943.09 | S81: 47.3 | T81: =(R81-AVERAGE($R$2:$R$261))/STDEV($R$2:$R$261) -> 0.85421041 | U81: =(S81-AVERAGE($S$2:$S$261))/STDEV($S$2:$S$261) -> 0.6644878 | V81: 129062.79 | W81: =(V81-AVERAGE($V$2:$V$261))/STDEV($V$2:$V$261) -> 2.2959619 | X81: =LN(V81) -> 11.768054 | Y81: 3.8 | Z81: =(Y81-AVERAGE($Y$2:$Y$261))/STDEV($Y$2:$Y$261) -> 1.0909853 | AA81: =LN(Y81) -> 1.3350011 | AB81: 86388 | AC81: 3443 | AD81: =AC81/I81 -> 0.0065654736 | AE81: =0.5*T81+0.5*U81 -> 0.7593491 | AF81: =AE81*P81 -> 0.20502426 | AG81: =LN(1+AF81) -> 0.1864997 | AH81: =(AF81-AVERAGE($AF$2:$AF$261))/STDEV($AF$2:$AF$261) -> 2.113924 | AI81: =LN(F81)-LN(F80) -> 0.13793931 | AJ81: =K81-K80 -> 0.12131683 | AK81: =Y81-Y80 -> -0.1 | AL81: =LN(V81)-LN(V80) -> 0.15700375
A82: GL | B82: 2014 | C82: 1 | D82: 0 | E82: 0 | F82: 1057.17 | G82: =(F82-AVERAGE($F$2:$F$261))/STDEV($F$2:$F$261) -> -1.0988748 | H82: =LN(F82) -> 6.9633508 | I82: 39794 | J82: -75 | K82: =(J82/I82)*100 -> -0.18847062 | L82: =(K82-AVERAGE($K$2:$K$261))/STDEV($K$2:$K$261) -> -0.53961151 | M82: 1.0281149 | N82: =(M82-AVERAGE($M$2:$M$261))/STDEV($M$2:$M$261) -> 0.060154245 | O82: 1.95 | P82: 0 | Q82: 8405 | R82: =[1]Feuil1!J116/panel_choc_taux_suisse_2014_202!Q82 -> 75527.94 | S82: 34.9 | T82: =(R82-AVERAGE($R$2:$R$261))/STDEV($R$2:$R$261) -> 0.32591747 | U82: =(S82-AVERAGE($S$2:$S$261))/STDEV($S$2:$S$261) -> -0.58744574 | V82: 71286.228 | W82: =(V82-AVERAGE($V$2:$V$261))/STDEV($V$2:$V$261) -> -0.98205636 | X82: =LN(V82) -> 11.174458 | Y82: 2.2 | Z82: =(Y82-AVERAGE($Y$2:$Y$261))/STDEV($Y$2:$Y$261) -> -0.2872409 | AA82: =LN(Y82) -> 0.78845736 | AB82: 7280 | AC82: 130 | AD82: =AC82/I82 -> 0.0032668241 | AE82: =0.5*T82+0.5*U82 -> -0.13076413 | AF82: =AE82*P82 -> 0 | AG82: =LN(1+AF82) -> 0 | AH82: =(AF82-AVERAGE($AF$2:$AF$261))/STDEV($AF$2:$AF$261) -> 0.0055297297 | AI82: 0 | AJ82: 0 | AK82: 0 | AL82: 0
A83: GL | B83: 2015 | C83: 1 | D83: 0 | E83: 0 | F83: 1092.6 | G83: =(F83-AVERAGE($F$2:$F$261))/STDEV($F$2:$F$261) -> -0.91927876 | H83: =LN(F83) -> 6.9963155 | I83: 40028 | J83: -124 | K83: =(J83/I83)*100 -> -0.30978315 | L83: =(K83-AVERAGE($K$2:$K$261))/STDEV($K$2:$K$261) -> -0.91495056 | M83: 1.0174024 | N83: =(M83-AVERAGE($M$2:$M$261))/STDEV($M$2:$M$261) -> -0.38706257 | O83: 1.84 | P83: -0.11 | Q83: 8010 | R83: =[1]Feuil1!J117/panel_choc_taux_suisse_2014_202!Q83 -> 81907.889 | S83: 34.2 | T83: =(R83-AVERAGE($R$2:$R$261))/STDEV($R$2:$R$261) -> 0.43320588 | U83: =(S83-AVERAGE($S$2:$S$261))/STDEV($S$2:$S$261) -> -0.6581194 | V83: 71571.373 | W83: =(V83-AVERAGE($V$2:$V$261))/STDEV($V$2:$V$261) -> -0.96587835 | X83: =LN(V83) -> 11.17845 | Y83: 2.1 | Z83: =(Y83-AVERAGE($Y$2:$Y$261))/STDEV($Y$2:$Y$261) -> -0.37338004 | AA83: =LN(Y83) -> 0.74193734 | AB83: 7483 | AC83: 176 | AD83: =AC83/I83 -> 0.0043969222 | AE83: =0.5*T83+0.5*U83 -> -0.11245676 | AF83: =AE83*P83 -> 0.012370244 | AG83: =LN(1+AF83) -> 0.012294358 | AH83: =(AF83-AVERAGE($AF$2:$AF$261))/STDEV($AF$2:$AF$261) -> 0.13274078 | AI83: =LN(F83)-LN(F82) -> 0.03296465 | AJ83: =K83-K82 -> -0.12131253 | AK83: =Y83-Y82 -> -0.1 | AL83: =LN(V83)-LN(V82) -> 0.0039920212
A84: GL | B84: 2016 | C84: 1 | D84: 0 | E84: 0 | F84: 1025.5 | G84: =(F84-AVERAGE($F$2:$F$261))/STDEV($F$2:$F$261) -> -1.2594113 | H84: =LN(F84) -> 6.9329356 | I84: 40147 | J84: -135 | K84: =(J84/I84)*100 -> -0.33626423 | L84: =(K84-AVERAGE($K$2:$K$261))/STDEV($K$2:$K$261) -> -0.99688259 | M84: 0.98347652 | N84: =(M84-AVERAGE($M$2:$M$261))/STDEV($M$2:$M$261) -> -1.8033694 | O84: 1.71 | P84: -0.13 | Q84: 8222 | R84: =[1]Feuil1!J118/panel_choc_taux_suisse_2014_202!Q84 -> 82167.732 | S84: 34.5 | T84: =(R84-AVERAGE($R$2:$R$261))/STDEV($R$2:$R$261) -> 0.43757553 | U84: =(S84-AVERAGE($S$2:$S$261))/STDEV($S$2:$S$261) -> -0.62783069 | V84: 72072.373 | W84: =(V84-AVERAGE($V$2:$V$261))/STDEV($V$2:$V$261) -> -0.93745357 | X84: =LN(V84) -> 11.185426 | Y84: 2.4 | Z84: =(Y84-AVERAGE($Y$2:$Y$261))/STDEV($Y$2:$Y$261) -> -0.11496262 | AA84: =LN(Y84) -> 0.87546874 | AB84: 7628 | AC84: 276 | AD84: =AC84/I84 -> 0.0068747353 | AE84: =0.5*T84+0.5*U84 -> -0.095127578 | AF84: =AE84*P84 -> 0.012366585 | AG84: =LN(1+AF84) -> 0.012290744 | AH84: =(AF84-AVERAGE($AF$2:$AF$261))/STDEV($AF$2:$AF$261) -> 0.13270316 | AI84: =LN(F84)-LN(F83) -> -0.063379878 | AJ84: =K84-K83 -> -0.026481077 | AK84: =Y84-Y83 -> 0.3 | AL84: =LN(V84)-LN(V83) -> 0.0069756138
A85: GL | B85: 2017 | C85: 1 | D85: 0 | E85: 0 | F85: 1027 | G85: =(F85-AVERAGE($F$2:$F$261))/STDEV($F$2:$F$261) -> -1.2518078 | H85: =LN(F85) -> 6.9343972 | I85: 40349 | J85: -52 | K85: =(J85/I85)*100 -> -0.12887556 | L85: =(K85-AVERAGE($K$2:$K$261))/STDEV($K$2:$K$261) -> -0.35522533 | M85: 1.0635157 | N85: =(M85-AVERAGE($M$2:$M$261))/STDEV($M$2:$M$261) -> 1.538032 | O85: 1.56 | P85: -0.15 | Q85: 8106 | R85: =[1]Feuil1!J119/panel_choc_taux_suisse_2014_202!Q85 -> 85414.817 | S85: 33.8 | T85: =(R85-AVERAGE($R$2:$R$261))/STDEV($R$2:$R$261) -> 0.49218015 | U85: =(S85-AVERAGE($S$2:$S$261))/STDEV($S$2:$S$261) -> -0.69850436 | V85: 72360.662 | W85: =(V85-AVERAGE($V$2:$V$261))/STDEV($V$2:$V$261) -> -0.92109714 | X85: =LN(V85) -> 11.189418 | Y85: 2.1 | Z85: =(Y85-AVERAGE($Y$2:$Y$261))/STDEV($Y$2:$Y$261) -> -0.37338004 | AA85: =LN(Y85) -> 0.74193734 | AB85: 7957 | AC85: 272 | AD85: =AC85/I85 -> 0.0067411832 | AE85: =0.5*T85+0.5*U85 -> -0.10316211 | AF85: =AE85*P85 -> 0.015474316 | AG85: =LN(1+AF85) -> 0.01535581 | AH85: =(AF85-AVERAGE($AF$2:$AF$261))/STDEV($AF$2:$AF$261) -> 0.16466192 | AI85: =LN(F85)-LN(F84) -> 0.0014616324 | AJ85: =K85-K84 -> 0.20738867 | AK85: =Y85-Y84 -> -0.3 | AL85: =LN(V85)-LN(V84) -> 0.0039920212
A86: GL | B86: 2018 | C86: 1 | D86: 0 | E86: 0 | F86: 1062.17 | G86: =(F86-AVERAGE($F$2:$F$261))/STDEV($F$2:$F$261) -> -1.0735296 | H86: =LN(F86) -> 6.9680693 | I86: 40403 | J86: -66 | K86: =(J86/I86)*100 -> -0.16335421 | L86: =(K86-AVERAGE($K$2:$K$261))/STDEV($K$2:$K$261) -> -0.46190172 | M86: 1.0301139 | N86: =(M86-AVERAGE($M$2:$M$261))/STDEV($M$2:$M$261) -> 0.14360417 | O86: 1.5 | P86: -0.06 | Q86: 8026 | R86: =[1]Feuil1!J120/panel_choc_taux_suisse_2014_202!Q86 -> 88567.05 | S86: 33.3 | T86: =(R86-AVERAGE($R$2:$R$261))/STDEV($R$2:$R$261) -> 0.54518966 | U86: =(S86-AVERAGE($S$2:$S$261))/STDEV($S$2:$S$261) -> -0.74898555 | V86: 72722.466 | W86: =(V86-AVERAGE($V$2:$V$261))/STDEV($V$2:$V$261) -> -0.90056983 | X86: =LN(V86) -> 11.194406 | Y86: 1.7 | Z86: =(Y86-AVERAGE($Y$2:$Y$261))/STDEV($Y$2:$Y$261) -> -0.71793661 | AA86: =LN(Y86) -> 0.53062825 | AB86: 8111 | AC86: 267 | AD86: =AC86/I86 -> 0.0066084202 | AE86: =0.5*T86+0.5*U86 -> -0.10189794 | AF86: =AE86*P86 -> 0.0061138766 | AG86: =LN(1+AF86) -> 0.0060952627 | AH86: =(AF86-AVERAGE($AF$2:$AF$261))/STDEV($AF$2:$AF$261) -> 0.068402594 | AI86: =LN(F86)-LN(F85) -> 0.033672054 | AJ86: =K86-K85 -> -0.034478646 | AK86: =Y86-Y85 -> -0.4 | AL86: =LN(V86)-LN(V85) -> 0.0049875415
A87: GL | B87: 2019 | C87: 1 | D87: 0 | E87: 0 | F87: 1106.5 | G87: =(F87-AVERAGE($F$2:$F$261))/STDEV($F$2:$F$261) -> -0.8488191 | H87: =LN(F87) -> 7.0089572 | I87: 40590 | J87: 3 | K87: =(J87/I87)*100 -> 0.007390983 | L87: =(K87-AVERAGE($K$2:$K$261))/STDEV($K$2:$K$261) -> 0.066381199 | M87: 1.0368889 | N87: =(M87-AVERAGE($M$2:$M$261))/STDEV($M$2:$M$261) -> 0.42644191 | O87: 1.43 | P87: -0.07 | Q87: 8154 | R87: =[1]Feuil1!J121/panel_choc_taux_suisse_2014_202!Q87 -> 89547.063 | S87: 32.6 | T87: =(R87-AVERAGE($R$2:$R$261))/STDEV($R$2:$R$261) -> 0.56167006 | U87: =(S87-AVERAGE($S$2:$S$261))/STDEV($S$2:$S$261) -> -0.81965921 | V87: 73377 | W87: =(V87-AVERAGE($V$2:$V$261))/STDEV($V$2:$V$261) -> -0.86343409 | X87: =LN(V87) -> 11.203366 | Y87: 1.4 | Z87: =(Y87-AVERAGE($Y$2:$Y$261))/STDEV($Y$2:$Y$261) -> -0.97635403 | AA87: =LN(Y87) -> 0.33647224 | AB87: 8262 | AC87: 117 | AD87: =AC87/I87 -> 0.0028824834 | AE87: =0.5*T87+0.5*U87 -> -0.12899458 | AF87: =AE87*P87 -> 0.0090296205 | AG87: =LN(1+AF87) -> 0.0089890972 | AH87: =(AF87-AVERAGE($AF$2:$AF$261))/STDEV($AF$2:$AF$261) -> 0.098387035 | AI87: =LN(F87)-LN(F86) -> 0.040887895 | AJ87: =K87-K86 -> 0.17074519 | AK87: =Y87-Y86 -> -0.3 | AL87: =LN(V87)-LN(V86) -> 0.0089601791
A88: GL | B88: 2020 | C88: 1 | D88: 0 | E88: 0 | F88: 1113.33 | G88: =(F88-AVERAGE($F$2:$F$261))/STDEV($F$2:$F$261) -> -0.81419756 | H88: =LN(F88) -> 7.0151108 | I88: 40851 | J88: 17 | K88: =(J88/I88)*100 -> 0.041614648 | L88: =(K88-AVERAGE($K$2:$K$261))/STDEV($K$2:$K$261) -> 0.17226868 | M88: 1.0413346 | N88: =(M88-AVERAGE($M$2:$M$261))/STDEV($M$2:$M$261) -> 0.61203885 | O88: 1.33 | P88: -0.1 | Q88: 7519 | R88: =[1]Feuil1!J122/panel_choc_taux_suisse_2014_202!Q88 -> 99669.739 | S88: 32.1 | T88: =(R88-AVERAGE($R$2:$R$261))/STDEV($R$2:$R$261) -> 0.73189804 | U88: =(S88-AVERAGE($S$2:$S$261))/STDEV($S$2:$S$261) -> -0.8701404 | V88: 73963.984 | W88: =(V88-AVERAGE($V$2:$V$261))/STDEV($V$2:$V$261) -> -0.83013091 | X88: =LN(V88) -> 11.211334 | Y88: 2.1 | Z88: =(Y88-AVERAGE($Y$2:$Y$261))/STDEV($Y$2:$Y$261) -> -0.37338004 | AA88: =LN(Y88) -> 0.74193734 | AB88: 8420 | AC88: 177 | AD88: =AC88/I88 -> 0.0043328193 | AE88: =0.5*T88+0.5*U88 -> -0.069121185 | AF88: =AE88*P88 -> 0.0069121185 | AG88: =LN(1+AF88) -> 0.0068883393 | AH88: =(AF88-AVERAGE($AF$2:$AF$261))/STDEV($AF$2:$AF$261) -> 0.076611421 | AI88: =LN(F88)-LN(F87) -> 0.0061536438 | AJ88: =K88-K87 -> 0.034223665 | AK88: =Y88-Y87 -> 0.7 | AL88: =LN(V88)-LN(V87) -> 0.007967732
A89: GL | B89: 2021 | C89: 1 | D89: 0 | E89: 0 | F89: 1129.5 | G89: =(F89-AVERAGE($F$2:$F$261))/STDEV($F$2:$F$261) -> -0.73223119 | H89: =LN(F89) -> 7.0295303 | I89: 41190 | J89: 99 | K89: =(J89/I89)*100 -> 0.2403496 | L89: =(K89-AVERAGE($K$2:$K$261))/STDEV($K$2:$K$261) -> 0.78715147 | M89: 1.0457436 | N89: =(M89-AVERAGE($M$2:$M$261))/STDEV($M$2:$M$261) -> 0.79609897 | O89: 1.25 | P89: -0.08 | Q89: 7927 | R89: =[1]Feuil1!J123/panel_choc_taux_suisse_2014_202!Q89 -> 97533.718 | S89: 31.8 | T89: =(R89-AVERAGE($R$2:$R$261))/STDEV($R$2:$R$261) -> 0.69597765 | U89: =(S89-AVERAGE($S$2:$S$261))/STDEV($S$2:$S$261) -> -0.90042912 | V89: 73816.056 | W89: =(V89-AVERAGE($V$2:$V$261))/STDEV($V$2:$V$261) -> -0.83852377 | X89: =LN(V89) -> 11.209332 | Y89: 2 | Z89: =(Y89-AVERAGE($Y$2:$Y$261))/STDEV($Y$2:$Y$261) -> -0.45951918 | AA89: =LN(Y89) -> 0.69314718 | AB89: 8554 | AC89: 187 | AD89: =AC89/I89 -> 0.0045399369 | AE89: =0.5*T89+0.5*U89 -> -0.10222574 | AF89: =AE89*P89 -> 0.0081780589 | AG89: =LN(1+AF89) -> 0.0081447998 | AH89: =(AF89-AVERAGE($AF$2:$AF$261))/STDEV($AF$2:$AF$261) -> 0.089629888 | AI89: =LN(F89)-LN(F88) -> 0.014419533 | AJ89: =K89-K88 -> 0.19873495 | AK89: =Y89-Y88 -> -0.1 | AL89: =LN(V89)-LN(V88) -> -0.0020020027
A90: GL | B90: 2022 | C90: 1 | D90: 0 | E90: 0 | F90: 1153.83 | G90: =(F90-AVERAGE($F$2:$F$261))/STDEV($F$2:$F$261) -> -0.60890145 | H90: =LN(F90) -> 7.0508421 | I90: 41471 | J90: 44 | K90: =(J90/I90)*100 -> 0.10609824 | L90: =(K90-AVERAGE($K$2:$K$261))/STDEV($K$2:$K$261) -> 0.37177988 | M90: 0.98600652 | N90: =(M90-AVERAGE($M$2:$M$261))/STDEV($M$2:$M$261) -> -1.6977493 | O90: 1.21 | P90: -0.04 | Q90: 7540 | R90: =[1]Feuil1!J124/panel_choc_taux_suisse_2014_202!Q90 -> 105587.86 | S90: 31.1 | T90: =(R90-AVERAGE($R$2:$R$261))/STDEV($R$2:$R$261) -> 0.83142019 | U90: =(S90-AVERAGE($S$2:$S$261))/STDEV($S$2:$S$261) -> -0.97110279 | V90: 74480.4 | W90: =(V90-AVERAGE($V$2:$V$261))/STDEV($V$2:$V$261) -> -0.80083144 | X90: =LN(V90) -> 11.218291 | Y90: 1.3 | Z90: =(Y90-AVERAGE($Y$2:$Y$261))/STDEV($Y$2:$Y$261) -> -1.0624932 | AA90: =LN(Y90) -> 0.26236426 | AB90: 8745 | AC90: 90 | AD90: =AC90/I90 -> 0.0021701912 | AE90: =0.5*T90+0.5*U90 -> -0.069841297 | AF90: =AE90*P90 -> 0.0027936519 | AG90: =LN(1+AF90) -> 0.0027897569 | AH90: =(AF90-AVERAGE($AF$2:$AF$261))/STDEV($AF$2:$AF$261) -> 0.034258621 | AI90: =LN(F90)-LN(F89) -> 0.021311787 | AJ90: =K90-K89 -> -0.13425136 | AK90: =Y90-Y89 -> -0.7 | AL90: =LN(V90)-LN(V89) -> 0.0089597414
A91: GL | B91: 2023 | C91: 1 | D91: 0 | E91: 0 | F91: 1309.14 | G91: =(F91-AVERAGE($F$2:$F$261))/STDEV($F$2:$F$261) -> 0.17837113 | H91: =LN(F91) -> 7.1771257 | I91: 42056 | J91: 36 | K91: =(J91/I91)*100 -> 0.085600152 | L91: =(K91-AVERAGE($K$2:$K$261))/STDEV($K$2:$K$261) -> 0.30835913 | M91: 1.0341431 | N91: =(M91-AVERAGE($M$2:$M$261))/STDEV($M$2:$M$261) -> 0.31181116 | O91: 1.48 | P91: 0.27 | Q91: 7958 | R91: =[1]Feuil1!J125/panel_choc_taux_suisse_2014_202!Q91 -> 102172.45 | S91: 31.6 | T91: =(R91-AVERAGE($R$2:$R$261))/STDEV($R$2:$R$261) -> 0.77398484 | U91: =(S91-AVERAGE($S$2:$S$261))/STDEV($S$2:$S$261) -> -0.9206216 | V91: 87142.068 | W91: =(V91-AVERAGE($V$2:$V$261))/STDEV($V$2:$V$261) -> -0.082457503 | X91: =LN(V91) -> 11.375295 | Y91: 1.3 | Z91: =(Y91-AVERAGE($Y$2:$Y$261))/STDEV($Y$2:$Y$261) -> -1.0624932 | AA91: =LN(Y91) -> 0.26236426 | AB91: 8980 | AC91: 143 | AD91: =AC91/I91 -> 0.0034002283 | AE91: =0.5*T91+0.5*U91 -> -0.073318376 | AF91: =AE91*P91 -> -0.019795962 | AG91: =LN(1+AF91) -> -0.019994527 | AH91: =(AF91-AVERAGE($AF$2:$AF$261))/STDEV($AF$2:$AF$261) -> -0.19804468 | AI91: =LN(F91)-LN(F90) -> 0.12628359 | AJ91: =K91-K90 -> -0.020498085 | AK91: =Y91-Y90 -> 0 | AL91: =LN(V91)-LN(V90) -> 0.15700375
A92: GR | B92: 2014 | C92: 1 | D92: 0 | E92: 0 | F92: 1220.5 | G92: =(F92-AVERAGE($F$2:$F$261))/STDEV($F$2:$F$261) -> -0.27094856 | H92: =LN(F92) -> 7.1070159 | I92: 195886 | J92: -719 | K92: =(J92/I92)*100 -> -0.36705022 | L92: =(K92-AVERAGE($K$2:$K$261))/STDEV($K$2:$K$261) -> -1.092134 | M92: 1.0281149 | N92: =(M92-AVERAGE($M$2:$M$261))/STDEV($M$2:$M$261) -> 0.060154245 | O92: 1.95 | P92: 0 | Q92: 42567 | R92: =[1]Feuil1!J126/panel_choc_taux_suisse_2014_202!Q92 -> 14913.25 | S92: 43.2 | T92: =(R92-AVERAGE($R$2:$R$261))/STDEV($R$2:$R$261) -> -0.69340946 | U92: =(S92-AVERAGE($S$2:$S$261))/STDEV($S$2:$S$261) -> 0.25054203 | V92: 72117.901 | W92: =(V92-AVERAGE($V$2:$V$261))/STDEV($V$2:$V$261) -> -0.93487047 | X92: =LN(V92) -> 11.186058 | Y92: 3.4 | Z92: =(Y92-AVERAGE($Y$2:$Y$261))/STDEV($Y$2:$Y$261) -> 0.74642878 | AA92: =LN(Y92) -> 1.2237754 | AB92: 37423 | AC92: 1776 | AD92: =AC92/I92 -> 0.0090664979 | AE92: =0.5*T92+0.5*U92 -> -0.22143371 | AF92: =AE92*P92 -> 0 | AG92: =LN(1+AF92) -> 0 | AH92: =(AF92-AVERAGE($AF$2:$AF$261))/STDEV($AF$2:$AF$261) -> 0.0055297297 | AI92: 0 | AJ92: 0 | AK92: 0 | AL92: 0
A93: GR | B93: 2015 | C93: 1 | D93: 0 | E93: 0 | F93: 1178.67 | G93: =(F93-AVERAGE($F$2:$F$261))/STDEV($F$2:$F$261) -> -0.4829865 | H93: =LN(F93) -> 7.072142 | I93: 196610 | J93: -657 | K93: =(J93/I93)*100 -> -0.33416408 | L93: =(K93-AVERAGE($K$2:$K$261))/STDEV($K$2:$K$261) -> -0.99038477 | M93: 1.0174024 | N93: =(M93-AVERAGE($M$2:$M$261))/STDEV($M$2:$M$261) -> -0.38706257 | O93: 1.84 | P93: -0.11 | Q93: 44707 | R93: =[1]Feuil1!J127/panel_choc_taux_suisse_2014_202!Q93 -> 14675.156 | S93: 44.9 | T93: =(R93-AVERAGE($R$2:$R$261))/STDEV($R$2:$R$261) -> -0.69741338 | U93: =(S93-AVERAGE($S$2:$S$261))/STDEV($S$2:$S$261) -> 0.42217808 | V93: 72406.373 | W93: =(V93-AVERAGE($V$2:$V$261))/STDEV($V$2:$V$261) -> -0.91850371 | X93: =LN(V93) -> 11.19005 | Y93: 3.2 | Z93: =(Y93-AVERAGE($Y$2:$Y$261))/STDEV($Y$2:$Y$261) -> 0.5741505 | AA93: =LN(Y93) -> 1.1631508 | AB93: 38473 | AC93: 1952 | AD93: =AC93/I93 -> 0.0099282844 | AE93: =0.5*T93+0.5*U93 -> -0.13761765 | AF93: =AE93*P93 -> 0.015137941 | AG93: =LN(1+AF93) -> 0.015024506 | AH93: =(AF93-AVERAGE($AF$2:$AF$261))/STDEV($AF$2:$AF$261) -> 0.16120276 | AI93: =LN(F93)-LN(F92) -> -0.034873927 | AJ93: =K93-K92 -> 0.032886142 | AK93: =Y93-Y92 -> -0.2 | AL93: =LN(V93)-LN(V92) -> 0.0039920212
A94: GR | B94: 2016 | C94: 1 | D94: 0 | E94: 0 | F94: 1178.33 | G94: =(F94-AVERAGE($F$2:$F$261))/STDEV($F$2:$F$261) -> -0.48470997 | H94: =LN(F94) -> 7.0718535 | I94: 197550 | J94: -671 | K94: =(J94/I94)*100 -> -0.33966085 | L94: =(K94-AVERAGE($K$2:$K$261))/STDEV($K$2:$K$261) -> -1.0073917 | M94: 0.98347652 | N94: =(M94-AVERAGE($M$2:$M$261))/STDEV($M$2:$M$261) -> -1.8033694 | O94: 1.71 | P94: -0.13 | Q94: 44624 | R94: =[1]Feuil1!J128/panel_choc_taux_suisse_2014_202!Q94 -> 15139.456 | S94: 44.3 | T94: =(R94-AVERAGE($R$2:$R$261))/STDEV($R$2:$R$261) -> -0.68960547 | U94: =(S94-AVERAGE($S$2:$S$261))/STDEV($S$2:$S$261) -> 0.36160065 | V94: 72913.217 | W94: =(V94-AVERAGE($V$2:$V$261))/STDEV($V$2:$V$261) -> -0.88974731 | X94: =LN(V94) -> 11.197025 | Y94: 3.3 | Z94: =(Y94-AVERAGE($Y$2:$Y$261))/STDEV($Y$2:$Y$261) -> 0.66028964 | AA94: =LN(Y94) -> 1.1939225 | AB94: 39434 | AC94: 1343 | AD94: =AC94/I94 -> 0.0067982789 | AE94: =0.5*T94+0.5*U94 -> -0.16400241 | AF94: =AE94*P94 -> 0.021320313 | AG94: =LN(1+AF94) -> 0.021096215 | AH94: =(AF94-AVERAGE($AF$2:$AF$261))/STDEV($AF$2:$AF$261) -> 0.22478001 | AI94: =LN(F94)-LN(F93) -> -0.00028850234 | AJ94: =K94-K93 -> -0.0054967642 | AK94: =Y94-Y93 -> 0.1 | AL94: =LN(V94)-LN(V93) -> 0.0069756139
A95: GR | B95: 2017 | C95: 1 | D95: 0 | E95: 0 | F95: 1172.5 | G95: =(F95-AVERAGE($F$2:$F$261))/STDEV($F$2:$F$261) -> -0.51426247 | H95: =LN(F95) -> 7.0668935 | I95: 197888 | J95: -637 | K95: =(J95/I95)*100 -> -0.32189926 | L95: =(K95-AVERAGE($K$2:$K$261))/STDEV($K$2:$K$261) -> -0.95243759 | M95: 1.0635157 | N95: =(M95-AVERAGE($M$2:$M$261))/STDEV($M$2:$M$261) -> 1.538032 | O95: 1.56 | P95: -0.15 | Q95: 45232 | R95: =[1]Feuil1!J129/panel_choc_taux_suisse_2014_202!Q95 -> 15307.139 | S95: 44.4 | T95: =(R95-AVERAGE($R$2:$R$261))/STDEV($R$2:$R$261) -> -0.68678563 | U95: =(S95-AVERAGE($S$2:$S$261))/STDEV($S$2:$S$261) -> 0.37169689 | V95: 73204.87 | W95: =(V95-AVERAGE($V$2:$V$261))/STDEV($V$2:$V$261) -> -0.87320006 | X95: =LN(V95) -> 11.201017 | Y95: 3.2 | Z95: =(Y95-AVERAGE($Y$2:$Y$261))/STDEV($Y$2:$Y$261) -> 0.5741505 | AA95: =LN(Y95) -> 1.1631508 | AB95: 41350 | AC95: 1296 | AD95: =AC95/I95 -> 0.0065491591 | AE95: =0.5*T95+0.5*U95 -> -0.15754437 | AF95: =AE95*P95 -> 0.023631655 | AG95: =LN(1+AF95) -> 0.02335675 | AH95: =(AF95-AVERAGE($AF$2:$AF$261))/STDEV($AF$2:$AF$261) -> 0.24854901 | AI95: =LN(F95)-LN(F94) -> -0.0049599605 | AJ95: =K95-K94 -> 0.017761589 | AK95: =Y95-Y94 -> -0.1 | AL95: =LN(V95)-LN(V94) -> 0.0039920213
A96: GR | B96: 2018 | C96: 1 | D96: 0 | E96: 0 | F96: 1184.5 | G96: =(F96-AVERAGE($F$2:$F$261))/STDEV($F$2:$F$261) -> -0.453434 | H96: =LN(F96) -> 7.077076 | I96: 198379 | J96: -217 | K96: =(J96/I96)*100 -> -0.10938658 | L96: =(K96-AVERAGE($K$2:$K$261))/STDEV($K$2:$K$261) -> -0.29492673 | M96: 1.0301139 | N96: =(M96-AVERAGE($M$2:$M$261))/STDEV($M$2:$M$261) -> 0.14360417 | O96: 1.5 | P96: -0.06 | Q96: 43485 | R96: =[1]Feuil1!J130/panel_choc_taux_suisse_2014_202!Q96 -> 16346.766 | S96: 43.2 | T96: =(R96-AVERAGE($R$2:$R$261))/STDEV($R$2:$R$261) -> -0.66930274 | U96: =(S96-AVERAGE($S$2:$S$261))/STDEV($S$2:$S$261) -> 0.25054203 | V96: 73570.895 | W96: =(V96-AVERAGE($V$2:$V$261))/STDEV($V$2:$V$261) -> -0.85243326 | X96: =LN(V96) -> 11.206005 | Y96: 3.2 | Z96: =(Y96-AVERAGE($Y$2:$Y$261))/STDEV($Y$2:$Y$261) -> 0.5741505 | AA96: =LN(Y96) -> 1.1631508 | AB96: 42306 | AC96: 1477 | AD96: =AC96/I96 -> 0.0074453445 | AE96: =0.5*T96+0.5*U96 -> -0.20938035 | AF96: =AE96*P96 -> 0.012562821 | AG96: =LN(1+AF96) -> 0.012484564 | AH96: =(AF96-AVERAGE($AF$2:$AF$261))/STDEV($AF$2:$AF$261) -> 0.13472117 | AI96: =LN(F96)-LN(F95) -> 0.010182523 | AJ96: =K96-K95 -> 0.21251268 | AK96: =Y96-Y95 -> 0 | AL96: =LN(V96)-LN(V95) -> 0.0049875415
A97: GR | B97: 2019 | C97: 1 | D97: 0 | E97: 0 | F97: 1212.83 | G97: =(F97-AVERAGE($F$2:$F$261))/STDEV($F$2:$F$261) -> -0.3098281 | H97: =LN(F97) -> 7.1007118 | I97: 199021 | J97: -80 | K97: =(J97/I97)*100 -> -0.040196763 | L97: =(K97-AVERAGE($K$2:$K$261))/STDEV($K$2:$K$261) -> -0.080854535 | M97: 1.0368889 | N97: =(M97-AVERAGE($M$2:$M$261))/STDEV($M$2:$M$261) -> 0.42644191 | O97: 1.43 | P97: -0.07 | Q97: 43911 | R97: =[1]Feuil1!J131/panel_choc_taux_suisse_2014_202!Q97 -> 16628.334 | S97: 42.2 | T97: =(R97-AVERAGE($R$2:$R$261))/STDEV($R$2:$R$261) -> -0.66456776 | U97: =(S97-AVERAGE($S$2:$S$261))/STDEV($S$2:$S$261) -> 0.14957965 | V97: 74233 | W97: =(V97-AVERAGE($V$2:$V$261))/STDEV($V$2:$V$261) -> -0.81486797 | X97: =LN(V97) -> 11.214964 | Y97: 2.9 | Z97: =(Y97-AVERAGE($Y$2:$Y$261))/STDEV($Y$2:$Y$261) -> 0.31573308 | AA97: =LN(Y97) -> 1.0647107 | AB97: 43173 | AC97: 1294 | AD97: =AC97/I97 -> 0.0065018264 | AE97: =0.5*T97+0.5*U97 -> -0.25749406 | AF97: =AE97*P97 -> 0.018024584 | AG97: =LN(1+AF97) -> 0.017864067 | AH97: =(AF97-AVERAGE($AF$2:$AF$261))/STDEV($AF$2:$AF$261) -> 0.19088794 | AI97: =LN(F97)-LN(F96) -> 0.023635727 | AJ97: =K97-K96 -> 0.069189815 | AK97: =Y97-Y96 -> -0.3 | AL97: =LN(V97)-LN(V96) -> 0.0089592999
A98: GR | B98: 2020 | C98: 1 | D98: 0 | E98: 0 | F98: 1220.5 | G98: =(F98-AVERAGE($F$2:$F$261))/STDEV($F$2:$F$261) -> -0.27094856 | H98: =LN(F98) -> 7.1070159 | I98: 200096 | J98: -148 | K98: =(J98/I98)*100 -> -0.073964497 | L98: =(K98-AVERAGE($K$2:$K$261))/STDEV($K$2:$K$261) -> -0.18533137 | M98: 1.0413346 | N98: =(M98-AVERAGE($M$2:$M$261))/STDEV($M$2:$M$261) -> 0.61203885 | O98: 1.33 | P98: -0.1 | Q98: 43590 | R98: =[1]Feuil1!J132/panel_choc_taux_suisse_2014_202!Q98 -> 17192.401 | S98: 41.3 | T98: =(R98-AVERAGE($R$2:$R$261))/STDEV($R$2:$R$261) -> -0.65508212 | U98: =(S98-AVERAGE($S$2:$S$261))/STDEV($S$2:$S$261) -> 0.058713508 | V98: 74826.897 | W98: =(V98-AVERAGE($V$2:$V$261))/STDEV($V$2:$V$261) -> -0.78117255 | X98: =LN(V98) -> 11.222933 | Y98: 3.6 | Z98: =(Y98-AVERAGE($Y$2:$Y$261))/STDEV($Y$2:$Y$261) -> 0.91870706 | AA98: =LN(Y98) -> 1.2809338 | AB98: 44150 | AC98: 1250 | AD98: =AC98/I98 -> 0.0062470014 | AE98: =0.5*T98+0.5*U98 -> -0.29818431 | AF98: =AE98*P98 -> 0.029818431 | AG98: =LN(1+AF98) -> 0.029382506 | AH98: =(AF98-AVERAGE($AF$2:$AF$261))/STDEV($AF$2:$AF$261) -> 0.31217153 | AI98: =LN(F98)-LN(F97) -> 0.0063041391 | AJ98: =K98-K97 -> -0.033767734 | AK98: =Y98-Y97 -> 0.7 | AL98: =LN(V98)-LN(V97) -> 0.0079686111
A99: GR | B99: 2021 | C99: 1 | D99: 0 | E99: 0 | F99: 1227.33 | G99: =(F99-AVERAGE($F$2:$F$261))/STDEV($F$2:$F$261) -> -0.23632702 | H99: =LN(F99) -> 7.1125964 | I99: 201376 | J99: 34 | K99: =(J99/I99)*100 -> 0.016883839 | L99: =(K99-AVERAGE($K$2:$K$261))/STDEV($K$2:$K$261) -> 0.095751946 | M99: 1.0457436 | N99: =(M99-AVERAGE($M$2:$M$261))/STDEV($M$2:$M$261) -> 0.79609897 | O99: 1.25 | P99: -0.08 | Q99: 43271 | R99: =[1]Feuil1!J133/panel_choc_taux_suisse_2014_202!Q99 -> 17867.62 | S99: 41.4 | T99: =(R99-AVERAGE($R$2:$R$261))/STDEV($R$2:$R$261) -> -0.6437273 | U99: =(S99-AVERAGE($S$2:$S$261))/STDEV($S$2:$S$261) -> 0.068809746 | V99: 74677.243 | W99: =(V99-AVERAGE($V$2:$V$261))/STDEV($V$2:$V$261) -> -0.78966333 | X99: =LN(V99) -> 11.220931 | Y99: 3.3 | Z99: =(Y99-AVERAGE($Y$2:$Y$261))/STDEV($Y$2:$Y$261) -> 0.66028964 | AA99: =LN(Y99) -> 1.1939225 | AB99: 45104 | AC99: 1078 | AD99: =AC99/I99 -> 0.0053531702 | AE99: =0.5*T99+0.5*U99 -> -0.28745878 | AF99: =AE99*P99 -> 0.022996702 | AG99: =LN(1+AF99) -> 0.022736263 | AH99: =(AF99-AVERAGE($AF$2:$AF$261))/STDEV($AF$2:$AF$261) -> 0.24201938 | AI99: =LN(F99)-LN(F98) -> 0.0055804674 | AJ99: =K99-K98 -> 0.090848336 | AK99: =Y99-Y98 -> -0.3 | AL99: =LN(V99)-LN(V98) -> -0.0020020026
A100: GR | B100: 2022 | C100: 1 | D100: 0 | E100: 0 | F100: 1263.33 | G100: =(F100-AVERAGE($F$2:$F$261))/STDEV($F$2:$F$261) -> -0.053841586 | H100: =LN(F100) -> 7.1415064 | I100: 202538 | J100: -140 | K100: =(J100/I100)*100 -> -0.069122831 | L100: =(K100-AVERAGE($K$2:$K$261))/STDEV($K$2:$K$261) -> -0.17035133 | M100: 0.98600652 | N100: =(M100-AVERAGE($M$2:$M$261))/STDEV($M$2:$M$261) -> -1.6977493 | O100: 1.21 | P100: -0.04 | Q100: 43692 | R100: =[1]Feuil1!J134/panel_choc_taux_suisse_2014_202!Q100 -> 18221.471 | S100: 41.7 | T100: =(R100-AVERAGE($R$2:$R$261))/STDEV($R$2:$R$261) -> -0.63777677 | U100: =(S100-AVERAGE($S$2:$S$261))/STDEV($S$2:$S$261) -> 0.099098461 | V100: 75349.338 | W100: =(V100-AVERAGE($V$2:$V$261))/STDEV($V$2:$V$261) -> -0.75153126 | X100: =LN(V100) -> 11.22989 | Y100: 2.5 | Z100: =(Y100-AVERAGE($Y$2:$Y$261))/STDEV($Y$2:$Y$261) -> -0.028823482 | AA100: =LN(Y100) -> 0.91629073 | AB100: 46125 | AC100: 1126 | AD100: =AC100/I100 -> 0.0055594506 | AE100: =0.5*T100+0.5*U100 -> -0.26933916 | AF100: =AE100*P100 -> 0.010773566 | AG100: =LN(1+AF100) -> 0.010715945 | AH100: =(AF100-AVERAGE($AF$2:$AF$261))/STDEV($AF$2:$AF$261) -> 0.11632113 | AI100: =LN(F100)-LN(F99) -> 0.028910014 | AJ100: =K100-K99 -> -0.08600667 | AK100: =Y100-Y99 -> -0.8 | AL100: =LN(V100)-LN(V99) -> 0.0089597414
...

Sheet Feuil1
A1: canton | B1: year | C1: CLUSTER 0 | D1: CLUSTER 1 | E1: CLUSTER 2
A2: AG | B2: 2014 | C2: 1 | D2: 0 | E2: 0
A3: AG | B3: 2015 | C3: 1 | D3: 0 | E3: 0
A4: AG | B4: 2016 | C4: 1 | D4: 0 | E4: 0
A5: AG | B5: 2017 | C5: 1 | D5: 0 | E5: 0
A6: AG | B6: 2018 | C6: 1 | D6: 0 | E6: 0
A7: AG | B7: 2019 | C7: 1 | D7: 0 | E7: 0
A8: AG | B8: 2020 | C8: 1 | D8: 0 | E8: 0
A9: AG | B9: 2021 | C9: 1 | D9: 0 | E9: 0
A10: AG | B10: 2022 | C10: 1 | D10: 0 | E10: 0
A11: AG | B11: 2023 | C11: 1 | D11: 0 | E11: 0
A12: AI | B12: 2014 | C12: 1 | D12: 0 | E12: 0
A13: AI | B13: 2015 | C13: 1 | D13: 0 | E13: 0
... A261: ZH | B261: 2023 | C261: 0 | D261: 1 | E261: 0
